Workbook

Sheet Dashboard
G1: General Notes
B2: Total Revenue Projected Monthly | C2: =C6/12 -> 145522 | G2: Revenue Projections are based on rental income only
B3: Total Expenses Projected Monthly | C3: =C7/12 -> 123550 | G3: Expenses include (Taxes, Insurance, Mortgage Interest, Management, Utilities, R&M, Turns)
B4: Total Net Income Projected Monthly | C4: =C8/12 -> 21972 | G4: Vacancy is pre-factored into revenue projections
G5: Building Improvement Expenses Tagged on far right not in monthly expense actual figure
B6: Total Revenue Projected Annual | C6: =sum('Lancaster Hotel'!I75,'Concord Manor Apts'!I75,'Bavarian Village'!I75,'Glasstown Holdings'!I75,'Rain Tree Apts'!I75,'RDE Central'!I75,ENPH!I75,'RD Sidney'!I75,'New Lex MHP'!I75) -> 1746264 | G6: MT Vernon Not Calculated in Dashboard
B7: Total Expenses Projected Annual | C7: =sum('Lancaster Hotel'!M75,'Concord Manor Apts'!M75,'Bavarian Village'!M75,'Glasstown Holdings'!M75,'Rain Tree Apts'!M75,'RDE Central'!M75,ENPH!M75,'RD Sidney'!M75,'New Lex MHP'!I75) -> 1482600 | G7: Cap Ex & Prop. Stab. staring in June is on the far right column but not factored into expenses.
B8: Total Net Income Projected Annual | C8: =C6-C7 -> 263664
B10: January
B11: Monthly Revenue | C11: =sum('Lancaster Hotel'!H15,'Concord Manor Apts'!H15,'Bavarian Village'!H15,'Glasstown Holdings'!H15,'Rain Tree Apts'!H15,'RDE Central'!H15,ENPH!H15,'RD Sidney'!H15,'New Lex MHP'!H15) -> 136059
B12: Monthly Expenses | C12: =sum('Lancaster Hotel'!L15,'Concord Manor Apts'!L15,'Bavarian Village'!L15,'Glasstown Holdings'!L15,'Rain Tree Apts'!L15,'RDE Central'!L15,ENPH!L15,'RD Sidney'!L15,'New Lex MHP'!L15) -> 136807
B13: Monthly Net Income | C13: =C11-C12 -> -748
B15: February
B16: Monthly Revenue | C16: =sum('Lancaster Hotel'!H20,'Concord Manor Apts'!L20,'Bavarian Village'!H20,'Glasstown Holdings'!L20,'Rain Tree Apts'!L20,'RDE Central'!L20,ENPH!L20,'RD Sidney'!H20,'New Lex MHP'!L20) -> 149324
B17: Monthly Expenses | C17: =sum('Lancaster Hotel'!L20,'Concord Manor Apts'!L20,'Bavarian Village'!L20,'Glasstown Holdings'!L20,'Rain Tree Apts'!L20,'RDE Central'!L20,ENPH!L20,'RD Sidney'!L20,'New Lex MHP'!L20) -> 119716
B18: Monthly Net Income | C18: =C16-C17 -> 29608
B20: March
B21: Monthly Revenue | C21: =sum('Lancaster Hotel'!H26,'Concord Manor Apts'!H26,'Bavarian Village'!H26,'Glasstown Holdings'!H26,'Rain Tree Apts'!H26,'RDE Central'!H26,ENPH!H26,'RD Sidney'!H26,'New Lex MHP'!H26) -> 137959
B22: Monthly Expenses | C22: =sum('Lancaster Hotel'!L26,'Concord Manor Apts'!L26,'Bavarian Village'!L26,'Glasstown Holdings'!L26,'Rain Tree Apts'!L26,'RDE Central'!L26,ENPH!L26,'RD Sidney'!L26,'New Lex MHP'!L26) -> 170556
B23: Monthly Net Income | C23: =C21-C22 -> -32597
B25: April
B26: Monthly Revenue | C26: =sum('Lancaster Hotel'!H31,'Concord Manor Apts'!H31,'Bavarian Village'!H31,'Glasstown Holdings'!H31,'Rain Tree Apts'!H31,'RDE Central'!H31,ENPH!H31,'RD Sidney'!H31,'New Lex MHP'!H31,'TRS Portfolio'!H31) -> 156446
B27: Monthly Expenses | C27: =sum('Lancaster Hotel'!L36,'Concord Manor Apts'!L31,'Bavarian Village'!L31,'Glasstown Holdings'!L31,'Rain Tree Apts'!L31,'RDE Central'!L31,ENPH!L31,'RD Sidney'!L31,'New Lex MHP'!L31,'TRS Portfolio'!L31) -> 175922
B28: Monthly Net Income | C28: =C26-C27 -> -19476
B30: May
B31: Monthly Revenue | C31: =sum('Lancaster Hotel'!H36,'Concord Manor Apts'!H36,'Bavarian Village'!H36,'Glasstown Holdings'!H36,'Rain Tree Apts'!H36,'RDE Central'!H36,ENPH!H36,'RD Sidney'!H36,'New Lex MHP'!H36,'TRS Portfolio'!H36,'MT Vernon Studios'!H36) -> 193775
B32: Monthly Expenses | C32: =sum('Lancaster Hotel'!L36,'Bavarian Village'!L36,'Glasstown Holdings'!L36,'Rain Tree Apts'!L36,'RDE Central'!L36,ENPH!L36,'RD Sidney'!L36,'New Lex MHP'!L36,'TRS Portfolio'!L36,'MT Vernon Studios'!L36) -> 130236
B33: Monthly Net Income | C33: =C31-C32 -> 63539
B35: June
B36: Monthly Revenue
B37: Monthly Expenses
B38: Monthly Net Income | C38: =C36-C37 -> 0
B40: July
B41: Monthly Revenue
B42: Monthly Expenses
B43: Monthly Net Income
B45: August
B46: Monthly Revenue
B47: Monthly Expenses
B48: Monthly Net Income
B50: Septemeber
B51: Monthly Revenue
B52: Monthly Expenses
B53: Monthly Net Income
... B68: Monthly Net Income

Sheet Lancaster Hotel
A1: KEY
A2: Manual Input
A3: Owner Input or Formula
A4: Formula
B5: # of Units | C5: 24 | I5: KPI Tracker
A10: Week Ending Sunday | B10: # of Occupied Units | C10: Occupancy % | D10: Total Leased Rent Amount $ | E10: Average Rent | F10: Total Collections to Date $ | G10: Collection Percentage | H10: Actual Revenue (Monthly Only) | I10: Budgeted Revenue (Monthly Only) | J10: Variance $ | K10: Variance % | L10: Actual Expense (Monthly Only) | M10: Budgeted Expense (Monthly Only | N10: Variance $ | O10: Variance % | P10: Net Income | Q10: Net Income Budgeteted | R10: Total Expenses
A11: 45662 | B11: 19 | C11: =IF(B11=0,"",B11/C$5) -> 0.79166667 | D11: 24845 | E11: =IFERROR(D11/B11,"") -> 1307.6316 | F11: 24030 | G11: =IFERROR(F11/D11,"") -> 0.96719662 | R11: 123 N Broad Street, Lancaster, Ohio 43130
A12: =A11+7 -> 45669 | B12: 19 | C12: =IF(B12=0,"",B12/C$5) -> 0.79166667 | D12: 24845 | E12: =IFERROR(D12/B12,"") -> 1307.6316 | F12: 24845 | G12: =IFERROR(F12/D12,"") -> 1
A13: =A12+7 -> 45676 | B13: 20 | C13: =IF(B13=0,"",B13/C$5) -> 0.83333333 | D13: 25895 | E13: =IFERROR(D13/B13,"") -> 1294.75 | F13: 25488 | G13: =IFERROR(F13/D13,"") -> 0.98428268
A14: =A13+7 -> 45683 | B14: 20 | C14: =IF(B14=0,"",B14/C$5) -> 0.83333333 | D14: 25895 | E14: =IFERROR(D14/B14,"") -> 1294.75 | F14: 25488 | G14: =IFERROR(F14/D14,"") -> 0.98428268
A15: Monthly Target | B15: 23 | C15: =IF(B15=0,"",B15/C$5) -> 0.95833333 | D15: 33500 | E15: =D15/B15 -> 1456.5217 | F15: 33500 | G15: =IFERROR(F15/D15,"") -> 1 | H15: 25488 | I15: 33500 | J15: =IF(H15=0,"",H15-I15) -> -8012 | K15: =IFERROR((H15-I15)/H15,"") -> -0.314344 | L15: 36130 | M15: 29500 | N15: =IF(L15=0,"",L15-M15) -> 6630 | O15: =IFERROR((L15-M15)/L15,"") -> 0.18350401 | P15: =H15-L15 -> -10642 | Q15: =I15-M15 -> 4000 | R15: Dual Lease Option Expense paid on the 29th of January
A16: =A14+7 -> 45690 | B16: 20 | C16: =IF(B16=0,"",B16/C$5) -> 0.83333333 | D16: 25895 | E16: =IFERROR(D16/B16,"") -> 1294.75 | F16: 25895 | G16: =IFERROR(F16/D16,"") -> 1
A17: =A16+7 -> 45697 | B17: 21 | C17: =IF(B17=0,"",B17/C$5) -> 0.875 | D17: 27945 | E17: =IFERROR(D17/B17,"") -> 1330.7143 | F17: 27695 | G17: =IFERROR(F17/D17,"") -> 0.99105386
A18: =A17+7 -> 45704 | B18: 21 | C18: =IF(B18=0,"",B18/C$5) -> 0.875 | D18: 27945 | E18: =IFERROR(D18/B18,"") -> 1330.7143 | F18: 27695 | G18: =IFERROR(F18/D18,"") -> 0.99105386
A19: =A18+7 -> 45711 | B19: 21 | C19: =IF(B19=0,"",B19/C$5) -> 0.875 | D19: 27945 | E19: =IFERROR(D19/B19,"") -> 1330.7143 | F19: 27695 | G19: =IFERROR(F19/D19,"") -> 0.99105386
A20: Monthly Target | B20: 23 | C20: =IF(B20=0,"",B20/C$5) -> 0.95833333 | D20: 33500 | E20: =D20/B20 -> 1456.5217 | F20: 33500 | G20: =IFERROR(F20/D20,"") -> 1 | H20: 27348 | I20: 33500 | J20: =IF(H20=0,"",H20-I20) -> -6152 | K20: =IFERROR((H20-I20)/H20,"") -> -0.22495246 | L20: 13155 | M20: 29500 | N20: =IF(L20=0,"",L20-M20) -> -16345 | O20: =IFERROR((L20-M20)/L20,"") -> -1.2424933 | P20: =H20-L20 -> 14193 | Q20: =I20-M20 -> 4000 | R20: $3500 in Building imrpovements NOT included in expenses
A21: =A19+7 -> 45718 | B21: 21 | C21: =IF(B21=0,"",B21/C$5) -> 0.875 | D21: 28150 | E21: =IFERROR(D21/B21,"") -> 1340.4762 | F21: 15530 | G21: =IFERROR(F21/D21,"") -> 0.55168739
A22: =A21+7 -> 45725 | B22: 21 | C22: =IF(B22=0,"",B22/C$5) -> 0.875 | D22: 28150 | E22: =IFERROR(D22/B22,"") -> 1340.4762 | F22: 27343 | G22: =IFERROR(F22/D22,"") -> 0.97133215
A23: =A22+7 -> 45732 | B23: 21 | C23: =IF(B23=0,"",B23/C$5) -> 0.875 | D23: 28150 | E23: =IFERROR(D23/B23,"") -> 1340.4762 | F23: 27343 | G23: =IFERROR(F23/D23,"") -> 0.97133215
A24: =A23+7 -> 45739 | B24: 21 | C24: =IF(B24=0,"",B24/C$5) -> 0.875 | D24: 28150 | E24: =IFERROR(D24/B24,"") -> 1340.4762 | F24: 27343 | G24: =IFERROR(F24/D24,"") -> 0.97133215
A25: =A24+7 -> 45746 | B25: 20 | C25: =IF(B25=0,"",B25/C$5) -> 0.83333333 | D25: 27350 | E25: =IFERROR(D25/B25,"") -> 1367.5 | F25: 27343 | G25: =IFERROR(F25/D25,"") -> 0.99974406
A26: Monthly Target | B26: 23 | C26: =IF(B26=0,"",B26/C$5) -> 0.95833333 | D26: 33500 | E26: =D26/B26 -> 1456.5217 | F26: 33500 | G26: =IFERROR(F26/D26,"") -> 1 | H26: 27343 | I26: 33500 | J26: =IF(H26=0,"",H26-I26) -> -6157 | K26: =IFERROR((H26-I26)/H26,"") -> -0.22517646 | L26: 33780 | M26: 29500 | N26: =IF(L26=0,"",L26-M26) -> 4280 | O26: =IFERROR((L26-M26)/L26,"") -> 0.12670219 | P26: =H26-L26 -> -6437 | Q26: =I26-M26 -> 4000 | R26: $1,060 building improvements and 6 months proeprty taxes
A27: =A25+7 -> 45753 | B27: 19 | C27: =IF(B27=0,"",B27/C$5) -> 0.79166667 | D27: 26630 | E27: =IFERROR(D27/B27,"") -> 1401.5789 | F27: 26630 | G27: =IFERROR(F27/D27,"") -> 1
A28: =A27+7 -> 45760 | B28: 19 | C28: =IF(B28=0,"",B28/C$5) -> 0.79166667 | D28: 26630 | E28: =IFERROR(D28/B28,"") -> 1401.5789 | F28: 26630 | G28: =IFERROR(F28/D28,"") -> 1
A29: =A28+7 -> 45767 | B29: 21 | C29: =IF(B29=0,"",B29/C$5) -> 0.875 | D29: 29230 | E29: =IFERROR(D29/B29,"") -> 1391.9048 | F29: 27215 | G29: =IFERROR(F29/D29,"") -> 0.93106398
A30: =A29+7 -> 45774 | B30: 21 | C30: =IF(B30=0,"",B30/C$5) -> 0.875 | D30: 29230 | E30: =IFERROR(D30/B30,"") -> 1391.9048 | F30: 27757 | G30: =IFERROR(F30/D30,"") -> 0.94960657
A31: Monthly Target | B31: 23 | C31: =IF(B31=0,"",B31/C$5) -> 0.95833333 | D31: 33500 | E31: =D31/B31 -> 1456.5217 | F31: 33500 | G31: =IFERROR(F31/D31,"") -> 1 | H31: 34355 | I31: 33500 | J31: =IF(H31=0,"",H31-I31) -> 855 | K31: =IFERROR((H31-I31)/H31,"") -> 0.024887207 | L31: 29115 | M31: 29500 | N31: =IF(L31=0,"",L31-M31) -> -385 | O31: =IFERROR((L31-M31)/L31,"") -> -0.013223424 | P31: =H31-L31 -> 5240 | Q31: =I31-M31 -> 4000 | R31: $7,300 in Building Improvements (Lowes Materials for Unit Turns)
A32: =A30+7 -> 45781 | B32: 21 | C32: =IF(B32=0,"",B32/C$5) -> 0.875 | D32: 29230 | E32: =IFERROR(D32/B32,"") -> 1391.9048 | F32: 27980 | G32: =IFERROR(F32/D32,"") -> 0.95723572
A33: =A32+7 -> 45788 | B33: 21 | C33: =IF(B33=0,"",B33/C$5) -> 0.875 | D33: 29230 | E33: =IFERROR(D33/B33,"") -> 1391.9048 | F33: 29230 | G33: =IFERROR(F33/D33,"") -> 1
A34: =A33+7 -> 45795 | B34: 21 | C34: =IF(B34=0,"",B34/C$5) -> 0.875 | D34: 29230 | E34: =IFERROR(D34/B34,"") -> 1391.9048 | F34: 29230 | G34: =IFERROR(F34/D34,"") -> 1
A35: =A34+7 -> 45802 | B35: 21 | C35: =IF(B35=0,"",B35/C$5) -> 0.875 | D35: 29230 | E35: =IFERROR(D35/B35,"") -> 1391.9048 | F35: 29230 | G35: =IFERROR(F35/D35,"") -> 1
A36: Monthly Target | B36: 23 | C36: =IF(B36=0,"",B36/C$5) -> 0.95833333 | D36: 33500 | E36: =D36/B36 -> 1456.5217 | F36: 33500 | G36: =IFERROR(F36/D36,"") -> 1 | H36: 26055 | I36: 33500 | J36: =IF(H36=0,"",H36-I36) -> -7445 | K36: =IFERROR((H36-I36)/H36,"") -> -0.2857417 | L36: 25161 | M36: 29500 | N36: =IF(L36=0,"",L36-M36) -> -4339 | O36: =IFERROR((L36-M36)/L36,"") -> -0.17244943 | P36: =H36-L36 -> 894 | Q36: =I36-M36 -> 4000 | R36: $1000 additional in building improvements
A37: =A35+7 -> 45809 | B37: 19 | C37: =IF(B37=0,"",B37/C$5) -> 0.79166667 | D37: 27285 | E37: =IFERROR(D37/B37,"") -> 1436.0526 | F37: 20090 | G37: =IFERROR(F37/D37,"") -> 0.736302
A38: =A37+7 -> 45816 | B38: 19 | C38: =IF(B38=0,"",B38/C$5) -> 0.79166667 | D38: 27285 | E38: =IFERROR(D38/B38,"") -> 1436.0526 | F38: 27285 | G38: =IFERROR(F38/D38,"") -> 1
A39: =A38+7 -> 45823 | B39: 19 | C39: =IF(B39=0,"",B39/C$5) -> 0.79166667 | D39: 27285 | E39: =IFERROR(D39/B39,"") -> 1436.0526 | F39: 27285 | G39: =IFERROR(F39/D39,"") -> 1
A40: =A39+7 -> 45830 | B40: 19 | C40: =IF(B40=0,"",B40/C$5) -> 0.79166667 | D40: 27285 | E40: =IFERROR(D40/B40,"") -> 1436.0526 | F40: 27285 | G40: =IFERROR(F40/D40,"") -> 1
A41: =A40+7 -> 45837 | B41: 19 | C41: =IF(B41=0,"",B41/C$5) -> 0.79166667 | D41: 27285 | E41: =IFERROR(D41/B41,"") -> 1436.0526 | F41: 27285 | G41: =IFERROR(F41/D41,"") -> 1
A42: Monthly Target | B42: 23 | C42: =IF(B42=0,"",B42/C$5) -> 0.95833333 | D42: 33500 | E42: =D42/B42 -> 1456.5217 | F42: 33500 | G42: =IFERROR(F42/D42,"") -> 1 | H42: 26698 | I42: 33500 | J42: =IF(H42=0,"",H42-I42) -> -6802 | K42: =IFERROR((H42-I42)/H42,"") -> -0.25477564 | L42: 25727 | M42: 29500 | N42: =IF(L42=0,"",L42-M42) -> -3773 | O42: =IFERROR((L42-M42)/L42,"") -> -0.14665526 | P42: =H42-L42 -> 971 | Q42: =I42-M42 -> 4000
A43: =A41+7 -> 45844 | B43: 19 | C43: =IF(B43=0,"",B43/C$5) -> 0.79166667 | D43: 27490 | E43: =IFERROR(D43/B43,"") -> 1446.8421 | F43: 27490 | G43: =IFERROR(F43/D43,"") -> 1
A44: =A43+7 -> 45851 | B44: 20 | C44: =IF(B44=0,"",B44/C$5) -> 0.83333333 | D44: 28840 | E44: =IFERROR(D44/B44,"") -> 1442 | F44: 27490 | G44: =IFERROR(F44/D44,"") -> 0.95319001
A45: =A44+7 -> 45858 | B45: 20 | C45: =IF(B45=0,"",B45/C$5) -> 0.83333333 | D45: 28840 | E45: =IFERROR(D45/B45,"") -> 1442 | F45: 28317 | G45: =IFERROR(F45/D45,"") -> 0.98186546
A46: =A45+7 -> 45865 | B46: 20 | C46: =IF(B46=0,"",B46/C$5) -> 0.83333333 | D46: 28840 | E46: =IFERROR(D46/B46,"") -> 1442 | F46: 28317 | G46: =IFERROR(F46/D46,"") -> 0.98186546
A47: Monthly Target | B47: 24 | C47: =IF(B47=0,"",B47/C$5) -> 1 | D47: 33500 | E47: =D47/B47 -> 1395.8333 | F47: 33500 | G47: =IFERROR(F47/D47,"") -> 1 | H47: 27472 | I47: 33500 | J47: =IF(H47=0,"",H47-I47) -> -6028 | K47: =IFERROR((H47-I47)/H47,"") -> -0.21942341 | L47: 48251 | M47: 29500 | N47: =IF(L47=0,"",L47-M47) -> 18751 | O47: =IFERROR((L47-M47)/L47,"") -> 0.38861371 | P47: =H47-L47 -> -20779 | Q47: =I47-M47 -> 4000 | R47: Property Taxes and Gas Leak 10k building imrovments
A48: =A46+7 -> 45872 | B48: 20 | C48: =IF(B48=0,"",B48/C$5) -> 0.83333333 | D48: 28965 | E48: =IFERROR(D48/B48,"") -> 1448.25 | F48: 26560 | G48: =IFERROR(F48/D48,"") -> 0.91696876
A49: =A48+7 -> 45879 | B49: 20 | C49: =IF(B49=0,"",B49/C$5) -> 0.83333333 | D49: 28965 | E49: =IFERROR(D49/B49,"") -> 1448.25 | F49: 27720 | G49: =IFERROR(F49/D49,"") -> 0.95701709
A50: =A49+7 -> 45886 | B50: 20 | C50: =IF(B50=0,"",B50/C$5) -> 0.83333333 | D50: 28965 | E50: =IFERROR(D50/B50,"") -> 1448.25 | F50: 28965 | G50: =IFERROR(F50/D50,"") -> 1
A51: =A50+7 -> 45893 | B51: 20 | C51: =IF(B51=0,"",B51/C$5) -> 0.83333333 | D51: 28965 | E51: =IFERROR(D51/B51,"") -> 1448.25 | F51: 28965 | G51: =IFERROR(F51/D51,"") -> 1
A52: =A51+7 -> 45900 | B52: 20 | C52: =IF(B52=0,"",B52/C$5) -> 0.83333333 | D52: 28965 | E52: =IFERROR(D52/B52,"") -> 1448.25 | F52: 28965 | G52: =IFERROR(F52/D52,"") -> 1
A53: Monthly Target | B53: 24 | C53: =IF(B53=0,"",B53/C$5) -> 1 | D53: 33500 | E53: =D53/B53 -> 1395.8333 | F53: 33500 | G53: =IFERROR(F53/D53,"") -> 1 | H53: 26629 | I53: 33500 | J53: =IF(H53=0,"",H53-I53) -> -6871 | K53: =IFERROR((H53-I53)/H53,"") -> -0.25802696 | L53: 25945 | M53: 29500 | N53: =IF(L53=0,"",L53-M53) -> -3555 | O53: =IFERROR((L53-M53)/L53,"") -> -0.13702062 | P53: =H53-L53 -> 684 | Q53: =I53-M53 -> 4000 | R53: Utilities over 10k a month
A54: =A52+7 -> 45907 | B54: 20 | C54: =IF(B54=0,"",B54/C$5) -> 0.83333333 | D54: 29565 | E54: =IFERROR(D54/B54,"") -> 1478.25 | F54: 28315 | G54: =IFERROR(F54/D54,"") -> 0.95772028
A55: =A54+7 -> 45914 | B55: 20 | C55: =IF(B55=0,"",B55/C$5) -> 0.83333333 | D55: 29565 | E55: =IFERROR(D55/B55,"") -> 1478.25 | F55: 29565 | G55: =IFERROR(F55/D55,"") -> 1
A56: =A55+7 -> 45921 | B56: 20 | C56: =IF(B56=0,"",B56/C$5) -> 0.83333333 | D56: 29565 | E56: =IFERROR(D56/B56,"") -> 1478.25 | F56: 29565 | G56: =IFERROR(F56/D56,"") -> 1
A57: =A56+7 -> 45928 | B57: 20 | C57: =IF(B57=0,"",B57/C$5) -> 0.83333333 | D57: 29565 | E57: =IFERROR(D57/B57,"") -> 1478.25 | F57: 29565 | G57: =IFERROR(F57/D57,"") -> 1
A58: Monthly Target | B58: 24 | C58: =IF(B58=0,"",B58/C$5) -> 1 | D58: 33500 | E58: =D58/B58 -> 1395.8333 | F58: 33500 | G58: =IFERROR(F58/D58,"") -> 1 | H58: 28497 | I58: 33500 | J58: =IF(H58=0,"",H58-I58) -> -5003 | K58: =IFERROR((H58-I58)/H58,"") -> -0.17556234 | L58: 27533 | M58: 29500 | N58: =IF(L58=0,"",L58-M58) -> -1967 | O58: =IFERROR((L58-M58)/L58,"") -> -0.071441543 | P58: =H58-L58 -> 964 | Q58: =I58-M58 -> 4000
A59: =A57+7 -> 45935 | B59: 20 | C59: =IF(B59=0,"",B59/C$5) -> 0.83333333 | D59: 29565 | E59: =IFERROR(D59/B59,"") -> 1478.25 | F59: 25810 | G59: =IFERROR(F59/D59,"") -> 0.87299171
A60: =A59+7 -> 45942 | B60: 20 | C60: =IF(B60=0,"",B60/C$5) -> 0.83333333 | D60: 29565 | E60: =IFERROR(D60/B60,"") -> 1478.25 | F60: 29565 | G60: =IFERROR(F60/D60,"") -> 1
A61: =A60+7 -> 45949 | B61: 20 | C61: =IF(B61=0,"",B61/C$5) -> 0.83333333 | D61: 29565 | E61: =IFERROR(D61/B61,"") -> 1478.25 | F61: 29565 | G61: =IFERROR(F61/D61,"") -> 1
A62: =A61+7 -> 45956 | B62: 20 | C62: =IF(B62=0,"",B62/C$5) -> 0.83333333 | D62: 29565 | E62: =IFERROR(D62/B62,"") -> 1478.25 | F62: 29565 | G62: =IFERROR(F62/D62,"") -> 1
A63: Monthly Target | B63: 24 | C63: =IF(B63=0,"",B63/C$5) -> 1 | D63: 33500 | E63: =D63/B63 -> 1395.8333 | F63: 33500 | G63: =IFERROR(F63/D63,"") -> 1 | H63: 33317 | I63: 33500 | J63: =IF(H63=0,"",H63-I63) -> -183 | K63: =IFERROR((H63-I63)/H63,"") -> -0.0054926914 | L63: 36841 | M63: 29500 | N63: =IF(L63=0,"",L63-M63) -> 7341 | O63: =IFERROR((L63-M63)/L63,"") -> 0.19926169 | P63: =H63-L63 -> -3524 | Q63: =I63-M63 -> 4000 | R63: Turn repositions
A64: =A62+7 -> 45963 | B64: 20 | C64: =IF(B64=0,"",B64/C$5) -> 0.83333333 | D64: 29835 | E64: =IFERROR(D64/B64,"") -> 1491.75 | F64: 15845 | G64: =IFERROR(F64/D64,"") -> 0.53108765
A65: =A64+7 -> 45970 | B65: 21 | C65: =IF(B65=0,"",B65/C$5) -> 0.875 | D65: 30835 | E65: =IFERROR(D65/B65,"") -> 1468.3333 | F65: 28585 | G65: =IFERROR(F65/D65,"") -> 0.92703097
A66: =A65+7 -> 45977 | B66: 21 | C66: =IF(B66=0,"",B66/C$5) -> 0.875 | D66: 30835 | E66: =IFERROR(D66/B66,"") -> 1468.3333 | F66: 29318 | G66: =IFERROR(F66/D66,"") -> 0.95080266
A67: =A66+7 -> 45984 | B67: 20 | C67: =IF(B67=0,"",B67/C$5) -> 0.83333333 | D67: 29785 | E67: =IFERROR(D67/B67,"") -> 1489.25 | F67: 29318 | G67: =IFERROR(F67/D67,"") -> 0.98432097
A68: =A67+7 -> 45991 | B68: 22 | C68: =IF(B68=0,"",B68/C$5) -> 0.91666667 | D68: 31985 | E68: =IFERROR(D68/B68,"") -> 1453.8636 | F68: 32768 | G68: =IFERROR(F68/D68,"") -> 1.0244802
A69: Monthly Target | B69: 24 | C69: =IF(B69=0,"",B69/C$5) -> 1 | D69: 33500 | E69: =D69/B69 -> 1395.8333 | F69: 33500 | G69: =IFERROR(F69/D69,"") -> 1 | I69: 33500 | J69: =IF(H69=0,"",H69-I69) | K69: =IFERROR((H69-I69)/H69,"") | M69: 29500 | N69: =IF(L69=0,"",L69-M69) | O69: =IFERROR((L69-M69)/L69,"") | P69: =H69-L69 -> 0 | Q69: =I69-M69 -> 4000
A70: =A68+7 -> 45998 | B70: 21 | C70: =IF(B70=0,"",B70/C$5) -> 0.875 | D70: 30735 | E70: =IFERROR(D70/B70,"") -> 1463.5714 | F70: 27185 | G70: =IFERROR(F70/D70,"") -> 0.8844965
A71: =A70+7 -> 46005 | B71: 21 | C71: =IF(B71=0,"",B71/C$5) -> 0.875 | D71: 30735 | E71: =IFERROR(D71/B71,"") -> 1463.5714 | F71: 29635 | G71: =IFERROR(F71/D71,"") -> 0.96421018
A72: =A71+7 -> 46012 | C72: =IF(B72=0,"",B72/C$5) | E72: =IFERROR(D72/B72,"") | G72: =IFERROR(F72/D72,"")
A73: =A72+7 -> 46019 | C73: =IF(B73=0,"",B73/C$5) | E73: =IFERROR(D73/B73,"") | G73: =IFERROR(F73/D73,"")
A74: Monthly Target | B74: 24 | C74: =IF(B74=0,"",B74/C$5) -> 1 | D74: 33500 | E74: =D74/B74 -> 1395.8333 | F74: 33500 | G74: =IFERROR(F74/D74,"") -> 1 | I74: 33500 | J74: =IF(H74=0,"",H74-I74) | K74: =IFERROR((H74-I74)/H74,"") | M74: 29500 | N74: =IF(L74=0,"",L74-M74) | O74: =IFERROR((L74-M74)/L74,"") | P74: =H74-L74 -> 0 | Q74: =I74-M74 -> 4000
A75: Annual Total | C75: =IF(B75=0,"",B75/C$5) | E75: =IFERROR(D75/B75,"") | G75: =IFERROR(F75/D75,"") | H75: =H15+H20+H26+H31+H36+H42+H47+H53+H58+H63+H69+H74 -> 283202 | I75: =I15+I20+I26+I31+I36+I42+I47+I53+I58+I63+I69+I74 -> 402000 | J75: =IF(H75=0,"",H75-I75) -> -118798 | K75: =IFERROR((H75-I75)/H75,"") -> -0.4194815 | L75: =L15+L20+L26+L31+L36+L42+L47+L53+L58+L63+L69+L74 -> 301638 | M75: =M15+M20+M26+M31+M36+M42+M47+M53+M58+M63+M69+M74 -> 354000 | N75: =IF(L75=0,"",L75-M75) -> -52362 | O75: =IFERROR((L75-M75)/L75,"") -> -0.17359219 | P75: =P15+P20+P26+P31+P36+P42+P47+P53+P58+P63+P69+P74 -> -18436 | Q75: =Q15+Q20+Q26+Q31+Q36+Q42+Q47+Q53+Q58+Q63+Q69+Q74 -> 48000
A76: ** | B76: ** | C76: ** | D76: ** | E76: ** | F76: ** | G76: ** | H76: ** | I76: ** | J76: ** | K76: ** | L76: ** | M76: ** | N76: ** | O76: ** | P76: ** | Q76: ** | R76: **

Sheet Concord Manor Apts
A1: KEY
A2: Manual Input
A3: Owner Input or Formula
A4: Formula | B4: Concord Manor Apartments
B5: # of Units | C5: 35 | I5: KPI Tracker
A10: Week Ending Sunday | B10: # of Occupied Units | C10: Occupancy % | D10: Total Leased Rent Amount $ | E10: Average Rent | F10: Total Collections to Date $ | G10: Collection Percentage | H10: Actual Revenue (Monthly Only) | I10: Budgeted Revenue (Monthly Only) | J10: Variance $ | K10: Variance % | L10: Actual Expense (Monthly Only) | M10: Budgeted Expense (Monthly Only | N10: Variance $ | O10: Variance % | P10: Net Income | Q10: Net Income Budgeted | R10: Notes:
A11: 45662 | B11: 34 | C11: =IF(B11=0,"",B11/C$5) -> 0.97142857 | D11: 28175 | E11: =IFERROR(D11/B11,"") -> 828.67647 | F11: 24688 | G11: =IFERROR(F11/D11,"") -> 0.8762378 | R11: 123 & 129 W Walnut Street, Lancaster, Ohio 43130
A12: =A11+7 -> 45669 | B12: 33 | C12: =IF(B12=0,"",B12/C$5) -> 0.94285714 | D12: 27400 | E12: =IFERROR(D12/B12,"") -> 830.30303 | F12: 27825 | G12: =IFERROR(F12/D12,"") -> 1.0155109
A13: =A12+7 -> 45676 | B13: 33 | C13: =IF(B13=0,"",B13/C$5) -> 0.94285714 | D13: 27400 | E13: =IFERROR(D13/B13,"") -> 830.30303 | F13: 28275 | G13: =IFERROR(F13/D13,"") -> 1.0319343
A14: =A13+7 -> 45683 | B14: 34 | C14: =IF(B14=0,"",B14/C$5) -> 0.97142857 | D14: 28400 | E14: =IFERROR(D14/B14,"") -> 835.29412 | F14: 28597 | G14: =IFERROR(F14/D14,"") -> 1.0069366
A15: Monthly Target | B15: 33 | C15: =IF(B15=0,"",B15/C$5) -> 0.94285714 | D15: 28500 | E15: =D15/B15 -> 863.63636 | F15: 28500 | G15: =IFERROR(F15/D15,"") -> 1 | H15: 28597 | I15: 28500 | J15: =IF(H15=0,"",H15-I15) -> 97 | K15: =IFERROR((H15-I15)/H15,"") -> 0.0033919642 | L15: 26662 | M15: 23100 | N15: =IF(L15=0,"",L15-M15) -> 3562 | O15: =IFERROR((L15-M15)/L15,"") -> 0.13359838 | P15: =H15-L15 -> 1935 | Q15: =I15-M15 -> 5400
A16: =A14+7 -> 45690 | B16: 34 | C16: =IF(B16=0,"",B16/C$5) -> 0.97142857 | D16: 28400 | E16: =D16/B16 -> 835.29412 | F16: 28597 | G16: =IFERROR(F16/D16,"") -> 1.0069366
A17: =A16+7 -> 45697 | B17: 34 | C17: =IF(B17=0,"",B17/C$5) -> 0.97142857 | D17: 28400 | E17: =D17/B17 -> 835.29412 | F17: 25809 | G17: =IFERROR(F17/D17,"") -> 0.90876761
A18: =A17+7 -> 45704 | B18: 34 | C18: =IF(B18=0,"",B18/C$5) -> 0.97142857 | D18: 28400 | E18: =D18/B18 -> 835.29412 | F18: 26881 | G18: =IFERROR(F18/D18,"") -> 0.94651408
A19: =A18+7 -> 45711 | B19: 34 | C19: =IF(B19=0,"",B19/C$5) -> 0.97142857 | D19: 28400 | E19: =D19/B19 -> 835.29412 | F19: 28063 | G19: =IFERROR(F19/D19,"") -> 0.9881338
A20: Monthly Target | B20: 33 | C20: =IF(B20=0,"",B20/C$5) -> 0.94285714 | D20: 28500 | E20: =D20/B20 -> 863.63636 | F20: 28500 | G20: =IFERROR(F20/D20,"") -> 1 | H20: 29178 | I20: 28500 | J20: =IF(H20=0,"",H20-I20) -> 678 | K20: =IFERROR((H20-I20)/H20,"") -> 0.023236685 | L20: 26814 | M20: 23100 | N20: =IF(L20=0,"",L20-M20) -> 3714 | O20: =IFERROR((L20-M20)/L20,"") -> 0.13850973 | P20: =H20-L20 -> 2364 | Q20: =I20-M20 -> 5400 | R20: $23,125 in building improvements not included in expenses
A21: =A19+7 -> 45718 | B21: 35 | C21: =IF(B21=0,"",B21/C$5) -> 1 | D21: 29400 | E21: =D21/B21 -> 840 | F21: 14427 | G21: =IFERROR(F21/D21,"") -> 0.49071429
A22: =A21+7 -> 45725 | B22: 35 | C22: =IF(B22=0,"",B22/C$5) -> 1 | D22: 29400 | E22: =D22/B22 -> 840 | F22: 28106 | G22: =IFERROR(F22/D22,"") -> 0.95598639
A23: =A22+7 -> 45732 | B23: 35 | C23: =IF(B23=0,"",B23/C$5) -> 1 | D23: 29400 | E23: =D23/B23 -> 840 | F23: 28676 | G23: =IFERROR(F23/D23,"") -> 0.97537415
A24: =A23+7 -> 45739 | B24: 34 | C24: =IF(B24=0,"",B24/C$5) -> 0.97142857 | D24: 28550 | E24: =D24/B24 -> 839.70588 | F24: 29269 | G24: =IFERROR(F24/D24,"") -> 1.0251839
A25: =A24+7 -> 45746 | B25: 34 | C25: =IF(B25=0,"",B25/C$5) -> 0.97142857 | D25: 28550 | E25: =D25/B25 -> 839.70588 | F25: 29269 | G25: =IFERROR(F25/D25,"") -> 1.0251839
A26: Monthly Target | B26: 33 | C26: =IF(B26=0,"",B26/C$5) -> 0.94285714 | D26: 28500 | E26: =D26/B26 -> 863.63636 | F26: 28500 | G26: =IFERROR(F26/D26,"") -> 1 | H26: 29269 | I26: 28500 | J26: =IF(H26=0,"",H26-I26) -> 769 | K26: =IFERROR((H26-I26)/H26,"") -> 0.026273532 | L26: 32121 | M26: 23100 | N26: =IF(L26=0,"",L26-M26) -> 9021 | O26: =IFERROR((L26-M26)/L26,"") -> 0.28084431 | P26: =H26-L26 -> -2852 | Q26: =I26-M26 -> 5400 | R26: $4,000 appraisal fee
A27: =A25+7 -> 45753 | B27: 31 | C27: =IF(B27=0,"",B27/C$5) -> 0.88571429 | D27: 25850 | E27: =D27/B27 -> 833.87097 | F27: 23967 | G27: =IFERROR(F27/D27,"") -> 0.92715667
A28: =A27+7 -> 45760 | B28: 31 | C28: =IF(B28=0,"",B28/C$5) -> 0.88571429 | D28: 25850 | E28: =D28/B28 -> 833.87097 | F28: 25134 | G28: =IFERROR(F28/D28,"") -> 0.97230174
A29: =A28+7 -> 45767 | B29: 31 | C29: =IF(B29=0,"",B29/C$5) -> 0.88571429 | D29: 25850 | E29: =D29/B29 -> 833.87097 | F29: 26810 | G29: =IFERROR(F29/D29,"") -> 1.0371373
A30: =A29+7 -> 45774 | B30: 31 | C30: =IF(B30=0,"",B30/C$5) -> 0.88571429 | D30: 25850 | E30: =D30/B30 -> 833.87097 | F30: 27250 | G30: =IFERROR(F30/D30,"") -> 1.0541586
A31: Monthly Target | B31: 33 | C31: =IF(B31=0,"",B31/C$5) -> 0.94285714 | D31: 28500 | E31: =D31/B31 -> 863.63636 | F31: 28500 | G31: =IFERROR(F31/D31,"") -> 1 | H31: 28318 | I31: 28500 | J31: =IF(H31=0,"",H31-I31) -> -182 | K31: =IFERROR((H31-I31)/H31,"") -> -0.0064270076 | L31: 22554 | M31: 23100 | N31: =IF(L31=0,"",L31-M31) -> -546 | O31: =IFERROR((L31-M31)/L31,"") -> -0.024208566 | P31: =H31-L31 -> 5764 | Q31: =I31-M31 -> 5400
A32: =A30+7 -> 45781 | B32: 30 | C32: =IF(B32=0,"",B32/C$5) -> 0.85714286 | D32: 24875 | E32: =D32/B32 -> 829.16667 | F32: 14533 | G32: =IFERROR(F32/D32,"") -> 0.58424121
A33: =A32+7 -> 45788 | B33: 30 | C33: =IF(B33=0,"",B33/C$5) -> 0.85714286 | D33: 24875 | E33: =D33/B33 -> 829.16667 | F33: 20765 | G33: =IFERROR(F33/D33,"") -> 0.83477387
A34: =A33+7 -> 45795 | B34: 30 | C34: =IF(B34=0,"",B34/C$5) -> 0.85714286 | D34: 24875 | E34: =D34/B34 -> 829.16667 | F34: 20765 | G34: =IFERROR(F34/D34,"") -> 0.83477387
A35: =A34+7 -> 45802 | B35: 30 | C35: =IF(B35=0,"",B35/C$5) -> 0.85714286 | D35: 24875 | E35: =D35/B35 -> 829.16667 | F35: 22206 | G35: =IFERROR(F35/D35,"") -> 0.89270352
A36: Monthly Target | B36: 33 | C36: =IF(B36=0,"",B36/C$5) -> 0.94285714 | D36: 28500 | E36: =D36/B36 -> 863.63636 | F36: 28500 | G36: =IFERROR(F36/D36,"") -> 1 | H36: 25889 | I36: 28500 | J36: =IF(H36=0,"",H36-I36) -> -2611 | K36: =IFERROR((H36-I36)/H36,"") -> -0.10085364 | L36: 25143 | M36: 23100 | N36: =IF(L36=0,"",L36-M36) -> 2043 | O36: =IFERROR((L36-M36)/L36,"") -> 0.08125522 | P36: =H36-L36 -> 746 | Q36: =I36-M36 -> 5400 | R36: Additional $6700 in building improvments for sewer project
A37: =A35+7 -> 45809 | B37: 30 | C37: =IF(B37=0,"",B37/C$5) -> 0.85714286 | D37: 24875 | E37: =D37/B37 -> 829.16667 | F37: 8869 | G37: =IFERROR(F37/D37,"") -> 0.35654271
A38: =A37+7 -> 45816 | B38: 30 | C38: =IF(B38=0,"",B38/C$5) -> 0.85714286 | D38: 24875 | E38: =D38/B38 -> 829.16667 | F38: 19595 | G38: =IFERROR(F38/D38,"") -> 0.78773869
A39: =A38+7 -> 45823 | B39: 30 | C39: =IF(B39=0,"",B39/C$5) -> 0.85714286 | D39: 24875 | E39: =D39/B39 -> 829.16667 | F39: 21964 | G39: =IFERROR(F39/D39,"") -> 0.88297487
A40: =A39+7 -> 45830 | B40: 32 | C40: =IF(B40=0,"",B40/C$5) -> 0.91428571 | D40: 26725 | E40: =D40/B40 -> 835.15625 | F40: 21904 | G40: =IFERROR(F40/D40,"") -> 0.81960711
A41: =A40+7 -> 45837 | B41: 34 | C41: =IF(B41=0,"",B41/C$5) -> 0.97142857 | D41: 28517 | E41: =D41/B41 -> 838.73529 | F41: 22576 | G41: =IFERROR(F41/D41,"") -> 0.79166813
A42: Monthly Target | B42: 33 | C42: =IF(B42=0,"",B42/C$5) -> 0.94285714 | D42: 28500 | E42: =D42/B42 -> 863.63636 | F42: 28500 | G42: =IFERROR(F42/D42,"") -> 1 | H42: 20382 | I42: 28500 | J42: =IF(H42=0,"",H42-I42) -> -8118 | K42: =IFERROR((H42-I42)/H42,"") -> -0.39829261 | L42: 44238 | M42: 23100 | N42: =IF(L42=0,"",L42-M42) -> 21138 | O42: =IFERROR((L42-M42)/L42,"") -> 0.47782449 | P42: =H42-L42 -> -23856 | Q42: =I42-M42 -> 5400 | R42: 5980 In Building Improvmeents 129 Sewer Project ($20,000 in R&M in house for sewer project as well)
A43: =A41+7 -> 45844 | B43: 33 | C43: =IF(B43=0,"",B43/C$5) -> 0.94285714 | D43: 27967 | E43: =D43/B43 -> 847.48485 | F43: 25679 | G43: =IFERROR(F43/D43,"") -> 0.91818929
A44: =A43+7 -> 45851 | B44: 33 | C44: =IF(B44=0,"",B44/C$5) -> 0.94285714 | D44: 27967 | E44: =D44/B44 -> 847.48485 | F44: 26454 | G44: =IFERROR(F44/D44,"") -> 0.94590053
A45: =A44+7 -> 45858 | B45: 33 | C45: =IF(B45=0,"",B45/C$5) -> 0.94285714 | D45: 27967 | E45: =D45/B45 -> 847.48485 | F45: 28374 | G45: =IFERROR(F45/D45,"") -> 1.0145529
A46: =A45+7 -> 45865 | B46: 33 | C46: =IF(B46=0,"",B46/C$5) -> 0.94285714 | D46: 27967 | E46: =D46/B46 -> 847.48485 | F46: 29679 | G46: =IFERROR(F46/D46,"") -> 1.061215
A47: Monthly Target | B47: 33 | C47: =IF(B47=0,"",B47/C$5) -> 0.94285714 | D47: 29000 | E47: =D47/B47 -> 878.78788 | F47: 29000 | G47: =IFERROR(F47/D47,"") -> 1 | H47: 32669 | I47: 29000 | J47: =IF(H47=0,"",H47-I47) -> 3669 | K47: =IFERROR((H47-I47)/H47,"") -> 0.1123083 | L47: 29165 | M47: 23100 | N47: =IF(L47=0,"",L47-M47) -> 6065 | O47: =IFERROR((L47-M47)/L47,"") -> 0.20795474 | P47: =H47-L47 -> 3504 | Q47: =I47-M47 -> 5900 | R47: 8,000 in building improvements property taxes
A48: =A46+7 -> 45872 | B48: 34 | C48: =IF(B48=0,"",B48/C$5) -> 0.97142857 | D48: 28885 | E48: =D48/B48 -> 849.55882 | F48: 18935 | G48: =IFERROR(F48/D48,"") -> 0.65553055
A49: =A48+7 -> 45879 | B49: 33 | C49: =IF(B49=0,"",B49/C$5) -> 0.94285714 | D49: 28035 | E49: =D49/B49 -> 849.54545 | F49: 24139 | G49: =IFERROR(F49/D49,"") -> 0.86103085
A50: =A49+7 -> 45886 | B50: 33 | C50: =IF(B50=0,"",B50/C$5) -> 0.94285714 | D50: 28035 | E50: =D50/B50 -> 849.54545 | F50: 26896 | G50: =IFERROR(F50/D50,"") -> 0.95937221
A51: =A50+7 -> 45893 | B51: 33 | C51: =IF(B51=0,"",B51/C$5) -> 0.94285714 | D51: 28035 | E51: =D51/B51 -> 849.54545 | F51: 29599 | G51: =IFERROR(F51/D51,"") -> 1.0557874
A52: =A51+7 -> 45900 | B52: 33 | C52: =IF(B52=0,"",B52/C$5) -> 0.94285714 | D52: 28035 | E52: =D52/B52 -> 849.54545 | F52: 29608 | G52: =IFERROR(F52/D52,"") -> 1.0561084
A53: Monthly Target | B53: 33 | C53: =IF(B53=0,"",B53/C$5) -> 0.94285714 | D53: 29000 | E53: =D53/B53 -> 878.78788 | F53: 29000 | G53: =IFERROR(F53/D53,"") -> 1 | H53: 35461 | I53: 29000 | J53: =IF(H53=0,"",H53-I53) -> 6461 | K53: =IFERROR((H53-I53)/H53,"") -> 0.18220016 | L53: 19675 | M53: 23100 | N53: =IF(L53=0,"",L53-M53) -> -3425 | O53: =IFERROR((L53-M53)/L53,"") -> -0.17407878 | P53: =H53-L53 -> 15786 | Q53: =I53-M53 -> 5900
A54: =A52+7 -> 45907 | B54: 33 | C54: =IF(B54=0,"",B54/C$5) -> 0.94285714 | D54: 27960 | E54: =D54/B54 -> 847.27273 | F54: 26174 | G54: =IFERROR(F54/D54,"") -> 0.93612303
A55: =A54+7 -> 45914 | B55: 33 | C55: =IF(B55=0,"",B55/C$5) -> 0.94285714 | D55: 27960 | E55: =D55/B55 -> 847.27273 | F55: 27124 | G55: =IFERROR(F55/D55,"") -> 0.97010014
A56: =A55+7 -> 45921 | B56: 33 | C56: =IF(B56=0,"",B56/C$5) -> 0.94285714 | D56: 27960 | E56: =D56/B56 -> 847.27273 | F56: 28668 | G56: =IFERROR(F56/D56,"") -> 1.0253219
A57: =A56+7 -> 45928 | B57: 33 | C57: =IF(B57=0,"",B57/C$5) -> 0.94285714 | D57: 27960 | E57: =D57/B57 -> 847.27273 | F57: 28668 | G57: =IFERROR(F57/D57,"") -> 1.0253219
A58: Monthly Target | B58: 33 | C58: =IF(B58=0,"",B58/C$5) -> 0.94285714 | D58: 29000 | E58: =D58/B58 -> 878.78788 | F58: 29000 | G58: =IFERROR(F58/D58,"") -> 1 | H58: 24464 | I58: 29000 | J58: =IF(H58=0,"",H58-I58) -> -4536 | K58: =IFERROR((H58-I58)/H58,"") -> -0.1854153 | L58: 27486 | M58: 23100 | N58: =IF(L58=0,"",L58-M58) -> 4386 | O58: =IFERROR((L58-M58)/L58,"") -> 0.15957215 | P58: =H58-L58 -> -3022 | Q58: =I58-M58 -> 5900 | R58: Heavy Turn 129 J
A59: =A57+7 -> 45935 | B59: 33 | C59: =IF(B59=0,"",B59/C$5) -> 0.94285714 | D59: 28110 | E59: =D59/B59 -> 851.81818 | F59: 19585 | G59: =IFERROR(F59/D59,"") -> 0.69672714
A60: =A59+7 -> 45942 | B60: 33 | C60: =IF(B60=0,"",B60/C$5) -> 0.94285714 | D60: 28110 | E60: =D60/B60 -> 851.81818 | F60: 24755 | G60: =IFERROR(F60/D60,"") -> 0.88064746
A61: =A60+7 -> 45949 | B61: 33 | C61: =IF(B61=0,"",B61/C$5) -> 0.94285714 | D61: 28110 | E61: =D61/B61 -> 851.81818 | F61: 27510 | G61: =IFERROR(F61/D61,"") -> 0.97865528
A62: =A61+7 -> 45956 | B62: 33 | C62: =IF(B62=0,"",B62/C$5) -> 0.94285714 | D62: 28110 | E62: =D62/B62 -> 851.81818 | F62: 27510 | G62: =IFERROR(F62/D62,"") -> 0.97865528
A63: Monthly Target | B63: 33 | C63: =IF(B63=0,"",B63/C$5) -> 0.94285714 | D63: 29000 | E63: =D63/B63 -> 878.78788 | F63: 29000 | G63: =IFERROR(F63/D63,"") -> 1 | H63: 33145 | I63: 29000 | J63: =IF(H63=0,"",H63-I63) -> 4145 | K63: =IFERROR((H63-I63)/H63,"") -> 0.12505657 | L63: 32278 | M63: 23100 | N63: =IF(L63=0,"",L63-M63) -> 9178 | O63: =IFERROR((L63-M63)/L63,"") -> 0.28434228 | P63: =H63-L63 -> 867 | Q63: =I63-M63 -> 5900 | R63: 15k in unit turns and (15k sewer replacment not included)
A64: =A62+7 -> 45963 | B64: 32 | C64: =IF(B64=0,"",B64/C$5) -> 0.91428571 | D64: 27160 | E64: =D64/B64 -> 848.75 | F64: 11930 | G64: =IFERROR(F64/D64,"") -> 0.4392489
A65: =A64+7 -> 45970 | B65: 33 | C65: =IF(B65=0,"",B65/C$5) -> 0.94285714 | D65: 28260 | E65: =D65/B65 -> 856.36364 | F65: 23814 | G65: =IFERROR(F65/D65,"") -> 0.84267516
A66: =A65+7 -> 45977 | B66: 34 | C66: =IF(B66=0,"",B66/C$5) -> 0.97142857 | D66: 29360 | E66: =D66/B66 -> 863.52941 | F66: 25929 | G66: =IFERROR(F66/D66,"") -> 0.88314033
A67: =A66+7 -> 45984 | B67: 34 | C67: =IF(B67=0,"",B67/C$5) -> 0.97142857 | D67: 29360 | E67: =D67/B67 -> 863.52941 | F67: 27237 | G67: =IFERROR(F67/D67,"") -> 0.92769074
A68: =A67+7 -> 45991 | B68: 35 | C68: =IF(B68=0,"",B68/C$5) -> 1 | D68: 30460 | E68: =D68/B68 -> 870.28571 | F68: 28337 | G68: =IFERROR(F68/D68,"") -> 0.93030204
A69: Monthly Target | B69: 33 | C69: =IF(B69=0,"",B69/C$5) -> 0.94285714 | D69: 29000 | E69: =D69/B69 -> 878.78788 | F69: 29000 | G69: =IFERROR(F69/D69,"") -> 1 | I69: 29000 | J69: =IF(H69=0,"",H69-I69) | K69: =IFERROR((H69-I69)/H69,"") | M69: 23100 | N69: =IF(L69=0,"",L69-M69) | O69: =IFERROR((L69-M69)/L69,"") | P69: =H69-L69 -> 0 | Q69: =I69-M69 -> 5900
A70: =A68+7 -> 45998 | B70: 34 | C70: =IF(B70=0,"",B70/C$5) -> 0.97142857 | D70: 29685 | E70: =D70/B70 -> 873.08824 | F70: 23697 | G70: =IFERROR(F70/D70,"") -> 0.79828196
A71: =A70+7 -> 46005 | B71: 34 | C71: =IF(B71=0,"",B71/C$5) -> 0.97142857 | D71: 29685 | E71: =D71/B71 -> 873.08824 | F71: 27281 | G71: =IFERROR(F71/D71,"") -> 0.91901634
A72: =A71+7 -> 46012 | C72: =IF(B72=0,"",B72/C$5) | G72: =IFERROR(F72/D72,"")
A73: =A72+7 -> 46019 | C73: =IF(B73=0,"",B73/C$5) | G73: =IFERROR(F73/D73,"") | R73: No Property Stabalization factored into Total Expenses / Total Expenses Budgeted
A74: Monthly Target | B74: 33 | C74: =AVERAGE(C15,C20,C26,C31,C36,C42,C47,C53,C58,C63,C69) -> 0.94285714 | D74: 29000 | E74: =D74/B74 -> 878.78788 | F74: 29000 | G74: =IFERROR(F74/D74,"") -> 1 | I74: 29000 | J74: =IF(H74=0,"",H74-I74) | K74: =IFERROR((H74-I74)/H74,"") | M74: 23100 | N74: =IF(L74=0,"",L74-M74) | O74: =IFERROR((L74-M74)/L74,"") | P74: =H74-L74 -> 0 | Q74: =I74-M74 -> 5900
A75: Annual Total | B75: =AVERAGE(B15,B20,B26,B31,B36,B42,B47,B53,B58,B63,B69,B74) -> 33 | C75: =AVERAGE(C15,C20,C26,C31,C36,C42,C47,C53,C58,C63,C69,C74) -> 0.94285714 | D75: =SUM(D15,D20,D26,D31,D36,D42,D47,D53,D58,D63,D69,D74) -> 345000 | E75: =AVERAGE(E15,E20,E26,E31,E36,E42,E47,E53,E58,E63,E69,E74) -> 871.21212 | F75: =SUM(F15,F20,F26,F31,F36,F42,F47,F53,F58,F63,F69,F74) -> 345000 | G75: =AVERAGE(G15,G20,G26,G31,G36,G42,G47,G53,G58,G63,G69,G74) -> 1 | H75: =sum(H15,H20,H26,H31,H36,H42,H47,H53,H58,H63,H69,H74) -> 287372 | I75: =SUM(I15,I20,I26,I31,I36,I42,I47,I53,I58,I63,I69,I74) -> 345000 | J75: =IF(H75=0,"",H75-I75) -> -57628 | K75: =IFERROR((H75-I75)/H75,"") -> -0.2005345 | L75: =L15+L20+L26+L31+L36+L42+L47+L53+L58+L63+L69+L74 -> 286136 | M75: =M15+M20+M26+M31+M36+M42+M47+M53+M58+M63+M69+M74 -> 277200 | N75: =IF(L75=0,"",L75-M75) -> 8936 | O75: =IFERROR((L75-M75)/L75,"") -> 0.031229905 | P75: =SUM(P15,P20,P26,P31,P36,P42,P47,P53,P58,P63,P69,P74) -> 1236 | Q75: =sum(Q11:Q74) -> 67800
A76: ** | B76: ** | C76: ** | D76: ** | E76: ** | F76: ** | G76: ** | H76: ** | I76: ** | J76: ** | K76: ** | L76: ** | M76: ** | N76: ** | O76: ** | R76: **

Sheet Bavarian Village
A1: KEY
A2: Manual Input
A3: Owner Input or Formula
A4: Formula | B4: 250 Angle Street
B5: # of Units | C5: 20 | I5: KPI Tracker
A10: Week Ending Sunday | B10: # of Occupied Units | C10: Occupancy % | D10: Total Leased Rent Amount $ | E10: Average Rent | F10: Total Collections to Date $ | G10: Collection Percentage | H10: Actual Revenue (Monthly Only) | I10: Budgeted Revenue (Monthly Only) | J10: Variance $ | K10: Variance % | L10: Actual Expense (Monthly Only) | M10: Budgeted Expense (Monthly Only | N10: Variance $ | O10: Variance % | P10: Net Income | Q10: Net Income Budgeted | R10: Notes:
A11: 45662 | B11: 18 | C11: =IF(B11=0,"",B11/C$5) -> 0.9 | D11: 17000 | E11: =IFERROR(D11/B11,"") -> 944.44444 | F11: 18045 | G11: =IFERROR(F11/D11,"") -> 1.0614706 | R11: 250 Angle Street, Bremen, Ohio
A12: =A11+7 -> 45669 | B12: 18 | C12: =IF(B12=0,"",B12/C$5) -> 0.9 | D12: 17000 | E12: =IFERROR(D12/B12,"") -> 944.44444 | F12: 19095 | G12: =IFERROR(F12/D12,"") -> 1.1232353
A13: =A12+7 -> 45676 | B13: 18 | C13: =IF(B13=0,"",B13/C$5) -> 0.9 | D13: 17000 | E13: =IFERROR(D13/B13,"") -> 944.44444 | F13: 19095 | G13: =IFERROR(F13/D13,"") -> 1.1232353
A14: =A13+7 -> 45683 | B14: 18 | C14: =IF(B14=0,"",B14/C$5) -> 0.9 | D14: 17000 | E14: =IFERROR(D14/B14,"") -> 944.44444 | F14: 19095 | G14: =IFERROR(F14/D14,"") -> 1.1232353
A15: Monthly Target | B15: 19 | C15: =IF(B15=0,"",B15/C$5) -> 0.95 | D15: 18000 | E15: =D15/B15 -> 947.36842 | F15: 18000 | G15: =IFERROR(F15/D15,"") -> 1 | H15: 21040 | I15: 18000 | J15: =IF(H15=0,"",H15-I15) -> 3040 | K15: =IFERROR((H15-I15)/H15,"") -> 0.14448669 | L15: 15803 | M15: 16100 | N15: =IF(L15=0,"",L15-M15) -> -297 | O15: =IFERROR((L15-M15)/L15,"") -> -0.0187939 | P15: =H15-L15 -> 5237 | Q15: =I15-M15 -> 1900
A16: =A14+7 -> 45690 | B16: 20 | C16: =IF(B16=0,"",B16/C$5) -> 1 | D16: 19025 | E16: =IFERROR(D16/B16,"") -> 951.25 | F16: 10870 | G16: =IFERROR(F16/D16,"") -> 0.57135348
A17: =A16+7 -> 45697 | B17: 20 | C17: =IF(B17=0,"",B17/C$5) -> 1 | D17: 19025 | E17: =IFERROR(D17/B17,"") -> 951.25 | F17: 17075 | G17: =IFERROR(F17/D17,"") -> 0.89750329
A18: =A17+7 -> 45704 | B18: 20 | C18: =IF(B18=0,"",B18/C$5) -> 1 | D18: 19025 | E18: =IFERROR(D18/B18,"") -> 951.25 | F18: 17075 | G18: =IFERROR(F18/D18,"") -> 0.89750329
A19: =A18+7 -> 45711 | B19: 20 | C19: =IF(B19=0,"",B19/C$5) -> 1 | D19: 19025 | E19: =IFERROR(D19/B19,"") -> 951.25 | F19: 17325 | G19: =IFERROR(F19/D19,"") -> 0.91064389
A20: Monthly Target | B20: 19 | C20: =IF(B20=0,"",B20/C$5) -> 0.95 | D20: 18000 | E20: =D20/B20 -> 947.36842 | F20: 18000 | G20: =IFERROR(F20/D20,"") -> 1 | H20: 22035 | I20: 18000 | J20: =IF(H20=0,"",H20-I20) -> 4035 | K20: =IFERROR((H20-I20)/H20,"") -> 0.18311777 | L20: 13082 | M20: 16100 | N20: =IF(L20=0,"",L20-M20) -> -3018 | O20: =IFERROR((L20-M20)/L20,"") -> -0.23069867 | P20: =H20-L20 -> 8953 | Q20: =I20-M20 -> 1900
A21: =A19+7 -> 45718 | B21: 20 | C21: =IF(B21=0,"",B21/C$5) -> 1 | D21: 19025 | E21: =IFERROR(D21/B21,"") -> 951.25 | F21: 13325 | G21: =IFERROR(F21/D21,"") -> 0.70039422
A22: =A21+7 -> 45725 | B22: 20 | C22: =IF(B22=0,"",B22/C$5) -> 1 | D22: 19025 | E22: =IFERROR(D22/B22,"") -> 951.25 | F22: 18075 | G22: =IFERROR(F22/D22,"") -> 0.9500657
A23: =A22+7 -> 45732 | B23: 20 | C23: =IF(B23=0,"",B23/C$5) -> 1 | D23: 19025 | E23: =IFERROR(D23/B23,"") -> 951.25 | F23: 18075 | G23: =IFERROR(F23/D23,"") -> 0.9500657
A24: =A23+7 -> 45739 | B24: 20 | C24: =IF(B24=0,"",B24/C$5) -> 1 | D24: 19025 | E24: =IFERROR(D24/B24,"") -> 951.25 | F24: 18075 | G24: =IFERROR(F24/D24,"") -> 0.9500657
A25: =A24+7 -> 45746 | B25: 20 | C25: =IF(B25=0,"",B25/C$5) -> 1 | D25: 19025 | E25: =IFERROR(D25/B25,"") -> 951.25 | F25: 18075 | G25: =IFERROR(F25/D25,"") -> 0.9500657
A26: Monthly Target | B26: 19 | C26: =IF(B26=0,"",B26/C$5) -> 0.95 | D26: 18000 | E26: =D26/B26 -> 947.36842 | F26: 18000 | G26: =IFERROR(F26/D26,"") -> 1 | H26: 18075 | I26: 18000 | J26: =IF(H26=0,"",H26-I26) -> 75 | K26: =IFERROR((H26-I26)/H26,"") -> 0.0041493776 | L26: 16516 | M26: 16100 | N26: =IF(L26=0,"",L26-M26) -> 416 | O26: =IFERROR((L26-M26)/L26,"") -> 0.025187697 | P26: =H26-L26 -> 1559 | Q26: =I26-M26 -> 1900
A27: =A25+7 -> 45753 | B27: 20 | C27: =IF(B27=0,"",B27/C$5) -> 1 | D27: 19025 | E27: =IFERROR(D27/B27,"") -> 951.25 | F27: 17125 | G27: =IFERROR(F27/D27,"") -> 0.90013141
A28: =A27+7 -> 45760 | B28: 20 | C28: =IF(B28=0,"",B28/C$5) -> 1 | D28: 19025 | E28: =IFERROR(D28/B28,"") -> 951.25 | F28: 17125 | G28: =IFERROR(F28/D28,"") -> 0.90013141
A29: =A28+7 -> 45767 | B29: 19 | C29: =IF(B29=0,"",B29/C$5) -> 0.95 | D29: 18250 | E29: =IFERROR(D29/B29,"") -> 960.52632 | F29: 17125 | G29: =IFERROR(F29/D29,"") -> 0.93835616
A30: =A29+7 -> 45774 | B30: 19 | C30: =IF(B30=0,"",B30/C$5) -> 0.95 | D30: 18250 | E30: =IFERROR(D30/B30,"") -> 960.52632 | F30: 17125 | G30: =IFERROR(F30/D30,"") -> 0.93835616
A31: Monthly Target | B31: 19 | C31: =IF(B31=0,"",B31/C$5) -> 0.95 | D31: 18000 | E31: =D31/B31 -> 947.36842 | F31: 18000 | G31: =IFERROR(F31/D31,"") -> 1 | H31: 17125 | I31: 18000 | J31: =IF(H31=0,"",H31-I31) -> -875 | K31: =IFERROR((H31-I31)/H31,"") -> -0.051094891 | L31: 23963 | M31: 16100 | N31: =IF(L31=0,"",L31-M31) -> 7863 | O31: =IFERROR((L31-M31)/L31,"") -> 0.32813087 | P31: =H31-L31 -> -6838 | Q31: =I31-M31 -> 1900 | R31: OUCU double mortgage payment
A32: =A30+7 -> 45781 | B32: 20 | C32: =IF(B32=0,"",B32/C$5) -> 1 | D32: 19075 | E32: =IFERROR(D32/B32,"") -> 953.75 | F32: 15975 | G32: =IFERROR(F32/D32,"") -> 0.83748362
A33: =A32+7 -> 45788 | B33: 20 | C33: =IF(B33=0,"",B33/C$5) -> 1 | D33: 19075 | E33: =IFERROR(D33/B33,"") -> 953.75 | F33: 21680 | G33: =IFERROR(F33/D33,"") -> 1.1365662
A34: =A33+7 -> 45795 | B34: 20 | C34: =IF(B34=0,"",B34/C$5) -> 1 | D34: 19075 | E34: =IFERROR(D34/B34,"") -> 953.75 | F34: 21930 | G34: =IFERROR(F34/D34,"") -> 1.1496723
A35: =A34+7 -> 45802 | B35: 20 | C35: =IF(B35=0,"",B35/C$5) -> 1 | D35: 19075 | E35: =IFERROR(D35/B35,"") -> 953.75 | F35: 21930 | G35: =IFERROR(F35/D35,"") -> 1.1496723
A36: Monthly Target | B36: 19 | C36: =IF(B36=0,"",B36/C$5) -> 0.95 | D36: 18000 | E36: =D36/B36 -> 947.36842 | F36: 18000 | G36: =IFERROR(F36/D36,"") -> 1 | H36: 30293 | I36: 18000 | J36: =IF(H36=0,"",H36-I36) -> 12293 | K36: =IFERROR((H36-I36)/H36,"") -> 0.40580332 | L36: 6125 | M36: 16100 | N36: =IF(L36=0,"",L36-M36) -> -9975 | O36: =IFERROR((L36-M36)/L36,"") -> -1.6285714 | P36: =H36-L36 -> 24168 | Q36: =I36-M36 -> 1900 | R36: Mortgage credited in June and double payment the month before
A37: =A35+7 -> 45809 | B37: 19 | C37: =IF(B37=0,"",B37/C$5) -> 0.95 | D37: 18125 | E37: =IFERROR(D37/B37,"") -> 953.94737 | F37: 13225 | G37: =IFERROR(F37/D37,"") -> 0.72965517
A38: =A37+7 -> 45816 | B38: 19 | C38: =IF(B38=0,"",B38/C$5) -> 0.95 | D38: 18125 | E38: =IFERROR(D38/B38,"") -> 953.94737 | F38: 18025 | G38: =IFERROR(F38/D38,"") -> 0.99448276
A39: =A38+7 -> 45823 | B39: 19 | C39: =IF(B39=0,"",B39/C$5) -> 0.95 | D39: 18125 | E39: =IFERROR(D39/B39,"") -> 953.94737 | F39: 18025 | G39: =IFERROR(F39/D39,"") -> 0.99448276
A40: =A39+7 -> 45830 | B40: 19 | C40: =IF(B40=0,"",B40/C$5) -> 0.95 | D40: 18125 | E40: =IFERROR(D40/B40,"") -> 953.94737 | F40: 18025 | G40: =IFERROR(F40/D40,"") -> 0.99448276
A41: =A40+7 -> 45837 | B41: 19 | C41: =IF(B41=0,"",B41/C$5) -> 0.95 | D41: 18125 | E41: =IFERROR(D41/B41,"") -> 953.94737 | F41: 18025 | G41: =IFERROR(F41/D41,"") -> 0.99448276
A42: Monthly Target | B42: 19 | C42: =IF(B42=0,"",B42/C$5) -> 0.95 | D42: 18000 | E42: =D42/B42 -> 947.36842 | F42: 18000 | G42: =IFERROR(F42/D42,"") -> 1 | H42: 11643 | I42: 18000 | J42: =IF(H42=0,"",H42-I42) -> -6357 | K42: =IFERROR((H42-I42)/H42,"") -> -0.5459933 | L42: 26152 | M42: 16100 | N42: =IF(L42=0,"",L42-M42) -> 10052 | O42: =IFERROR((L42-M42)/L42,"") -> 0.38436831 | P42: =H42-L42 -> -14509 | Q42: =I42-M42 -> 1900 | R42: Double Mortgage Payment & prepaid rent reduced income
A43: =A41+7 -> 45844 | B43: 19 | C43: =IF(B43=0,"",B43/C$5) -> 0.95 | D43: 18175 | E43: =IFERROR(D43/B43,"") -> 956.57895 | F43: 16750 | G43: =IFERROR(F43/D43,"") -> 0.9215956
A44: =A43+7 -> 45851 | B44: 20 | C44: =IF(B44=0,"",B44/C$5) -> 1 | D44: 19175 | E44: =IFERROR(D44/B44,"") -> 958.75 | F44: 17750 | G44: =IFERROR(F44/D44,"") -> 0.92568449
A45: =A44+7 -> 45858 | B45: 20 | C45: =IF(B45=0,"",B45/C$5) -> 1 | D45: 19175 | E45: =IFERROR(D45/B45,"") -> 958.75 | F45: 17750 | G45: =IFERROR(F45/D45,"") -> 0.92568449
A46: =A45+7 -> 45865 | B46: 20 | C46: =IF(B46=0,"",B46/C$5) -> 1 | D46: 19175 | E46: =IFERROR(D46/B46,"") -> 958.75 | F46: 18200 | G46: =IFERROR(F46/D46,"") -> 0.94915254
A47: Monthly Target | B47: 19 | C47: =IF(B47=0,"",B47/C$5) -> 0.95 | D47: 18000 | E47: =D47/B47 -> 947.36842 | F47: 18000 | G47: =IFERROR(F47/D47,"") -> 1 | H47: 19704 | I47: 18000 | J47: =IF(H47=0,"",H47-I47) -> 1704 | K47: =IFERROR((H47-I47)/H47,"") -> 0.086479903 | L47: 19647 | M47: 16100 | N47: =IF(L47=0,"",L47-M47) -> 3547 | O47: =IFERROR((L47-M47)/L47,"") -> 0.18053647 | P47: =H47-L47 -> 57 | Q47: =I47-M47 -> 1900 | R47: Property Taxes
A48: =A46+7 -> 45872 | B48: 20 | C48: =IF(B48=0,"",B48/C$5) -> 1 | D48: 19275 | E48: =IFERROR(D48/B48,"") -> 963.75 | F48: 16318 | G48: =IFERROR(F48/D48,"") -> 0.84658885
A49: =A48+7 -> 45879 | B49: 20 | C49: =IF(B49=0,"",B49/C$5) -> 1 | D49: 19275 | E49: =IFERROR(D49/B49,"") -> 963.75 | F49: 17293 | G49: =IFERROR(F49/D49,"") -> 0.8971725
A50: =A49+7 -> 45886 | B50: 20 | C50: =IF(B50=0,"",B50/C$5) -> 1 | D50: 19275 | E50: =IFERROR(D50/B50,"") -> 963.75 | F50: 17293 | G50: =IFERROR(F50/D50,"") -> 0.8971725
A51: =A50+7 -> 45893 | B51: 20 | C51: =IF(B51=0,"",B51/C$5) -> 1 | D51: 19275 | E51: =IFERROR(D51/B51,"") -> 963.75 | F51: 17293 | G51: =IFERROR(F51/D51,"") -> 0.8971725
A52: =A51+7 -> 45900 | B52: 20 | C52: =IF(B52=0,"",B52/C$5) -> 1 | D52: 19275 | E52: =IFERROR(D52/B52,"") -> 963.75 | F52: 17293 | G52: =IFERROR(F52/D52,"") -> 0.8971725
A53: Monthly Target | B53: 19 | C53: =IF(B53=0,"",B53/C$5) -> 0.95 | D53: 18000 | E53: =D53/B53 -> 947.36842 | F53: 18000 | G53: =IFERROR(F53/D53,"") -> 1 | H53: 22028 | I53: 18000 | J53: =IF(H53=0,"",H53-I53) -> 4028 | K53: =IFERROR((H53-I53)/H53,"") -> 0.18285818 | L53: 15481 | M53: 16100 | N53: =IF(L53=0,"",L53-M53) -> -619 | O53: =IFERROR((L53-M53)/L53,"") -> -0.039984497 | P53: =H53-L53 -> 6547 | Q53: =I53-M53 -> 1900
A54: =A52+7 -> 45907 | B54: 20 | C54: =IF(B54=0,"",B54/C$5) -> 1 | D54: 19275 | E54: =IFERROR(D54/B54,"") -> 963.75 | F54: 19275 | G54: =IFERROR(F54/D54,"") -> 1
A55: =A54+7 -> 45914 | B55: 20 | C55: =IF(B55=0,"",B55/C$5) -> 1 | D55: 19275 | E55: =IFERROR(D55/B55,"") -> 963.75 | F55: 19275 | G55: =IFERROR(F55/D55,"") -> 1
A56: =A55+7 -> 45921 | B56: 20 | C56: =IF(B56=0,"",B56/C$5) -> 1 | D56: 19275 | E56: =IFERROR(D56/B56,"") -> 963.75 | F56: 19275 | G56: =IFERROR(F56/D56,"") -> 1
A57: =A56+7 -> 45928 | B57: 20 | C57: =IF(B57=0,"",B57/C$5) -> 1 | D57: 19275 | E57: =IFERROR(D57/B57,"") -> 963.75 | F57: 19275 | G57: =IFERROR(F57/D57,"") -> 1
A58: Monthly Target | B58: 19 | C58: =IF(B58=0,"",B58/C$5) -> 0.95 | D58: 18000 | E58: =D58/B58 -> 947.36842 | F58: 18000 | G58: =IFERROR(F58/D58,"") -> 1 | H58: 16468 | I58: 18000 | J58: =IF(H58=0,"",H58-I58) -> -1532 | K58: =IFERROR((H58-I58)/H58,"") -> -0.093028905 | L58: 25728 | M58: 16100 | N58: =IF(L58=0,"",L58-M58) -> 9628 | O58: =IFERROR((L58-M58)/L58,"") -> 0.37422264 | P58: =H58-L58 -> -9260 | Q58: =I58-M58 -> 1900 | R58: Property Insurance for the year
A59: =A57+7 -> 45935 | B59: 20 | C59: =IF(B59=0,"",B59/C$5) -> 1 | D59: 19275 | E59: =IFERROR(D59/B59,"") -> 963.75 | F59: 16390 | G59: =IFERROR(F59/D59,"") -> 0.85032425
A60: =A59+7 -> 45942 | B60: 20 | C60: =IF(B60=0,"",B60/C$5) -> 1 | D60: 19275 | E60: =IFERROR(D60/B60,"") -> 963.75 | F60: 18120 | G60: =IFERROR(F60/D60,"") -> 0.94007782
A61: =A60+7 -> 45949 | B61: 20 | C61: =IF(B61=0,"",B61/C$5) -> 1 | D61: 19275 | E61: =IFERROR(D61/B61,"") -> 963.75 | F61: 18595 | G61: =IFERROR(F61/D61,"") -> 0.96472114
A62: =A61+7 -> 45956 | B62: 20 | C62: =IF(B62=0,"",B62/C$5) -> 1 | D62: 19275 | E62: =IFERROR(D62/B62,"") -> 963.75 | F62: 18595 | G62: =IFERROR(F62/D62,"") -> 0.96472114
A63: Monthly Target | B63: 19 | C63: =IF(B63=0,"",B63/C$5) -> 0.95 | D63: 18000 | E63: =D63/B63 -> 947.36842 | F63: 18000 | G63: =IFERROR(F63/D63,"") -> 1 | H63: 22356 | I63: 18000 | J63: =IF(H63=0,"",H63-I63) -> 4356 | K63: =IFERROR((H63-I63)/H63,"") -> 0.19484702 | L63: 14925 | M63: 16100 | N63: =IF(L63=0,"",L63-M63) -> -1175 | O63: =IFERROR((L63-M63)/L63,"") -> -0.078726968 | P63: =H63-L63 -> 7431 | Q63: =I63-M63 -> 1900
A64: =A62+7 -> 45963 | B64: 20 | C64: =IF(B64=0,"",B64/C$5) -> 1 | D64: 19275 | E64: =IFERROR(D64/B64,"") -> 963.75 | F64: 14305 | G64: =IFERROR(F64/D64,"") -> 0.74215305
A65: =A64+7 -> 45970 | B65: 20 | C65: =IF(B65=0,"",B65/C$5) -> 1 | D65: 19275 | E65: =IFERROR(D65/B65,"") -> 963.75 | F65: 18220 | G65: =IFERROR(F65/D65,"") -> 0.94526589
A66: =A65+7 -> 45977 | B66: 20 | C66: =IF(B66=0,"",B66/C$5) -> 1 | D66: 19275 | E66: =IFERROR(D66/B66,"") -> 963.75 | F66: 19220 | G66: =IFERROR(F66/D66,"") -> 0.99714656
A67: =A66+7 -> 45984 | B67: 19 | C67: =IF(B67=0,"",B67/C$5) -> 0.95 | D67: 18300 | E67: =IFERROR(D67/B67,"") -> 963.15789 | F67: 19220 | G67: =IFERROR(F67/D67,"") -> 1.0502732
A68: =A67+7 -> 45991 | B68: 19 | C68: =IF(B68=0,"",B68/C$5) -> 0.95 | D68: 18300 | E68: =IFERROR(D68/B68,"") -> 963.15789 | F68: 19220 | G68: =IFERROR(F68/D68,"") -> 1.0502732
A69: Monthly Target | B69: 19 | C69: =IF(B69=0,"",B69/C$5) -> 0.95 | D69: 17775 | E69: =D69/B69 -> 935.52632 | F69: 18000 | G69: =IFERROR(F69/D69,"") -> 1.0126582 | I69: 18000 | J69: =IF(H69=0,"",H69-I69) | K69: =IFERROR((H69-I69)/H69,"") | M69: 16100 | N69: =IF(L69=0,"",L69-M69) | O69: =IFERROR((L69-M69)/L69,"") | P69: =H69-L69 -> 0 | Q69: =I69-M69 -> 1900
A70: =A68+7 -> 45998 | B70: 19 | C70: =IF(B70=0,"",B70/C$5) -> 0.95 | D70: 18300 | E70: =IFERROR(D70/B70,"") -> 963.15789 | F70: 18585 | G70: =IFERROR(F70/D70,"") -> 1.0155738
A71: =A70+7 -> 46005 | B71: 19 | C71: =IF(B71=0,"",B71/C$5) -> 0.95 | D71: 18300 | E71: =IFERROR(D71/B71,"") -> 963.15789 | F71: 19070 | G71: =IFERROR(F71/D71,"") -> 1.0420765
A72: =A71+7 -> 46012 | C72: =IF(B72=0,"",B72/C$5) | E72: =IFERROR(D72/B72,"") | G72: =IFERROR(F72/D72,"")
A73: =A72+7 -> 46019 | C73: =IF(B73=0,"",B73/C$5) | E73: =IFERROR(D73/B73,"") | G73: =IFERROR(F73/D73,"")
A74: Monthly Target | B74: 19 | C74: =IF(B74=0,"",B74/C$5) -> 0.95 | D74: 18000 | E74: =D74/B74 -> 947.36842 | F74: 18000 | G74: =IFERROR(F74/D74,"") -> 1 | I74: 18000 | J74: =IF(H74=0,"",H74-I74) | K74: =IFERROR((H74-I74)/H74,"") | M74: 16100 | N74: =IF(L74=0,"",L74-M74) | O74: =IFERROR((L74-M74)/L74,"") | P74: =H74-L74 -> 0 | Q74: =I74-M74 -> 1900
A75: Annual Total | B75: =AVERAGE(B15,B20,B26,B31,B36,B42,B47,B53,B58,B63,B69,B74) -> 19 | C75: =AVERAGE(C15,C20,C26,C31,C36,C42,C47,C53,C58,C63,C69,C74) -> 0.95 | D75: =sum(D15,D20,D26,D31,D36,D42,D47,D53,D58,D63,D69,D74) -> 215775 | E75: =average(E15,E20,E26,E31,E36,E42,E47,E53,E58,E63,E69,E74) -> 946.38158 | F75: =SUM(F15,F20,F26,F31,F36,F42,F47,F53,F58,F63,F69,F74) -> 216000 | G75: =IFERROR(F75/D75,"") -> 1.0010428 | H75: =H15+H20+H26+H31+H36+H42+H47+H53+H58+H63+H69+H74 -> 200767 | I75: =I15+I20+I26+I31+I36+I42+I47+I53+I58+I63+I69+I74 -> 216000 | J75: =IF(H75=0,"",H75-I75) -> -15233 | K75: =IFERROR((H75-I75)/H75,"") -> -0.075874023 | L75: =L15+L20+L26+L31+L36+L42+L47+L53+L58+L63+L69+L74 -> 177422 | M75: =M15+M20+M26+M31+M36+M42+M47+M53+M58+M63+M69+M74 -> 193200 | N75: =IF(L75=0,"",L75-M75) -> -15778 | O75: =IFERROR((L75-M75)/L75,"") -> -0.08892922 | P75: =SUM(P15,P20,P26,P31,P36,P42,P47,P53,P58,P63,P69,P74) -> 23345 | Q75: =SUM(Q15,Q20,Q26,Q31,Q36,Q42,Q47,Q53,Q58,Q63,Q69,Q74) -> 22800
A76: ** | B76: ** | C76: ** | D76: ** | E76: ** | F76: ** | G76: ** | H76: ** | I76: ** | J76: ** | K76: ** | L76: ** | M76: ** | N76: ** | O76: ** | R76: **

Sheet Glasstown Holdings
A1: KEY
A2: Manual Input
A3: Owner Input or Formula
A4: Formula | B4: Slocum & 6th
B5: # of Units | C5: 16 | I5: KPI Tracker
A10: Week Ending Sunday | B10: # of Occupied Units | C10: Occupancy % | D10: Total Leased Rent Amount $ | E10: Average Rent | F10: Total Collections to Date $ | G10: Collection Percentage | H10: Actual Revenue (Monthly Only) | I10: Budgeted Revenue (Monthly Only) | J10: Variance $ | K10: Variance % | L10: Actual Expense (Monthly Only) | M10: Budgeted Expense (Monthly Only | N10: Variance $ | O10: Variance % | P10: Net Income | Q10: Net Income Budgeted | R10: Notes:
A11: 45662 | B11: 16 | C11: =IF(B11=0,"",B11/C$5) -> 1 | D11: 12875 | E11: =IFERROR(D11/B11,"") -> 804.6875 | F11: 11580 | G11: =IFERROR(F11/D11,"") -> 0.89941748 | R11: 709 W 6th and 234 Slocum Ave Lancaster, Ohio 43130 (6 & 10 unit)
A12: =A11+7 -> 45669 | B12: 16 | C12: =IF(B12=0,"",B12/C$5) -> 1 | D12: 12875 | E12: =IFERROR(D12/B12,"") -> 804.6875 | F12: 12025 | G12: =IFERROR(F12/D12,"") -> 0.93398058
A13: =A12+7 -> 45676 | B13: 16 | C13: =IF(B13=0,"",B13/C$5) -> 1 | D13: 12875 | E13: =IFERROR(D13/B13,"") -> 804.6875 | F13: 12025 | G13: =IFERROR(F13/D13,"") -> 0.93398058
A14: =A13+7 -> 45683 | B14: 16 | C14: =IF(B14=0,"",B14/C$5) -> 1 | D14: 12875 | E14: =IFERROR(D14/B14,"") -> 804.6875 | F14: 12025 | G14: =IFERROR(F14/D14,"") -> 0.93398058
A15: Monthly Target | B15: 15 | C15: =IF(B15=0,"",B15/C$5) -> 0.9375 | D15: 12250 | E15: =D15/B15 -> 816.66667 | F15: 12250 | G15: =IFERROR(F15/D15,"") -> 1 | H15: 12025 | I15: 12250 | J15: =IF(H15=0,"",H15-I15) -> -225 | K15: =IFERROR((H15-I15)/H15,"") -> -0.018711019 | L15: 12655 | M15: 9300 | N15: =IF(L15=0,"",L15-M15) -> 3355 | O15: =IFERROR((L15-M15)/L15,"") -> 0.2651126 | P15: =H15-L15 -> -630 | Q15: =I15-M15 -> 2950 | R15: Paid Property Insurance for the year
A16: =A14+7 -> 45690 | B16: 16 | C16: =IF(B16=0,"",B16/C$5) -> 1 | D16: 12875 | E16: =IFERROR(D16/B16,"") -> 804.6875 | F16: 4198 | G16: =IFERROR(F16/D16,"") -> 0.32605825
A17: =A16+7 -> 45697 | B17: 16 | C17: =IF(B17=0,"",B17/C$5) -> 1 | D17: 12875 | E17: =IFERROR(D17/B17,"") -> 804.6875 | F17: 11175 | G17: =IFERROR(F17/D17,"") -> 0.86796116
A18: =A17+7 -> 45704 | B18: 16 | C18: =IF(B18=0,"",B18/C$5) -> 1 | D18: 12875 | E18: =IFERROR(D18/B18,"") -> 804.6875 | F18: 12025 | G18: =IFERROR(F18/D18,"") -> 0.93398058
A19: =A18+7 -> 45711 | B19: 16 | C19: =IF(B19=0,"",B19/C$5) -> 1 | D19: 12875 | E19: =IFERROR(D19/B19,"") -> 804.6875 | F19: 12025 | G19: =IFERROR(F19/D19,"") -> 0.93398058
A20: Monthly Target | B20: 15 | C20: =IF(B20=0,"",B20/C$5) -> 0.9375 | D20: 12250 | E20: =D20/B20 -> 816.66667 | F20: 12250 | G20: =IFERROR(F20/D20,"") -> 1 | H20: 13814 | I20: 12250 | J20: =IF(H20=0,"",H20-I20) -> 1564 | K20: =IFERROR((H20-I20)/H20,"") -> 0.11321847 | L20: 12663 | M20: 9300 | N20: =IF(L20=0,"",L20-M20) -> 3363 | O20: =IFERROR((L20-M20)/L20,"") -> 0.26557688 | P20: =H20-L20 -> 1151 | Q20: =I20-M20 -> 2950 | R20: $769 in building improvements not in expenses. & property taxes 1/2 year paid
A21: =A19+7 -> 45718 | B21: 16 | C21: =IF(B21=0,"",B21/C$5) -> 1 | D21: 12875 | E21: =IFERROR(D21/B21,"") -> 804.6875 | F21: 4344 | G21: =IFERROR(F21/D21,"") -> 0.33739806
A22: =A21+7 -> 45725 | B22: 16 | C22: =IF(B22=0,"",B22/C$5) -> 1 | D22: 12875 | E22: =IFERROR(D22/B22,"") -> 804.6875 | F22: 11600 | G22: =IFERROR(F22/D22,"") -> 0.90097087
A23: =A22+7 -> 45732 | B23: 15 | C23: =IF(B23=0,"",B23/C$5) -> 0.9375 | D23: 12025 | E23: =IFERROR(D23/B23,"") -> 801.66667 | F23: 12025 | G23: =IFERROR(F23/D23,"") -> 1
A24: =A23+7 -> 45739 | B24: 15 | C24: =IF(B24=0,"",B24/C$5) -> 0.9375 | D24: 12025 | E24: =IFERROR(D24/B24,"") -> 801.66667 | F24: 12840 | G24: =IFERROR(F24/D24,"") -> 1.0677755
A25: =A24+7 -> 45746 | B25: 15 | C25: =IF(B25=0,"",B25/C$5) -> 0.9375 | D25: 12025 | E25: =IFERROR(D25/B25,"") -> 801.66667 | F25: 12840 | G25: =IFERROR(F25/D25,"") -> 1.0677755
A26: Monthly Target | B26: 15 | C26: =IF(B26=0,"",B26/C$5) -> 0.9375 | D26: 12250 | E26: =D26/B26 -> 816.66667 | F26: 12250 | G26: =IFERROR(F26/D26,"") -> 1 | H26: 12840 | I26: 12250 | J26: =IF(H26=0,"",H26-I26) -> 590 | K26: =IFERROR((H26-I26)/H26,"") -> 0.045950156 | L26: 14039 | M26: 9300 | N26: =IF(L26=0,"",L26-M26) -> 4739 | O26: =IFERROR((L26-M26)/L26,"") -> 0.33755966 | P26: =H26-L26 -> -1199 | Q26: =I26-M26 -> 2950 | R26: $6,200 property insurance for the year
A27: =A25+7 -> 45753 | B27: 15 | C27: =IF(B27=0,"",B27/C$5) -> 0.9375 | D27: 12025 | E27: =IFERROR(D27/B27,"") -> 801.66667 | F27: 11600 | G27: =IFERROR(F27/D27,"") -> 0.96465696
A28: =A27+7 -> 45760 | B28: 16 | C28: =IF(B28=0,"",B28/C$5) -> 1 | D28: 12875 | E28: =IFERROR(D28/B28,"") -> 804.6875 | F28: 12025 | G28: =IFERROR(F28/D28,"") -> 0.93398058
A29: =A28+7 -> 45767 | B29: 16 | C29: =IF(B29=0,"",B29/C$5) -> 1 | D29: 12875 | E29: =IFERROR(D29/B29,"") -> 804.6875 | F29: 12662 | G29: =IFERROR(F29/D29,"") -> 0.98345631
A30: =A29+7 -> 45774 | B30: 16 | C30: =IF(B30=0,"",B30/C$5) -> 1 | D30: 12875 | E30: =IFERROR(D30/B30,"") -> 804.6875 | F30: 12662 | G30: =IFERROR(F30/D30,"") -> 0.98345631
A31: Monthly Target | B31: 15 | C31: =IF(B31=0,"",B31/C$5) -> 0.9375 | D31: 12250 | E31: =D31/B31 -> 816.66667 | F31: 12250 | G31: =IFERROR(F31/D31,"") -> 1 | H31: 14005 | I31: 12250 | J31: =IF(H31=0,"",H31-I31) -> 1755 | K31: =IFERROR((H31-I31)/H31,"") -> 0.12531239 | L31: 9954 | M31: 9300 | N31: =IF(L31=0,"",L31-M31) -> 654 | O31: =IFERROR((L31-M31)/L31,"") -> 0.06570223 | P31: =H31-L31 -> 4051 | Q31: =I31-M31 -> 2950
A32: =A30+7 -> 45781 | B32: 16 | C32: =IF(B32=0,"",B32/C$5) -> 1 | D32: 12875 | E32: =IFERROR(D32/B32,"") -> 804.6875 | F32: 12005 | G32: =IFERROR(F32/D32,"") -> 0.93242718
A33: =A32+7 -> 45788 | B33: 16 | C33: =IF(B33=0,"",B33/C$5) -> 1 | D33: 12875 | E33: =IFERROR(D33/B33,"") -> 804.6875 | F33: 12855 | G33: =IFERROR(F33/D33,"") -> 0.9984466
A34: =A33+7 -> 45795 | B34: 16 | C34: =IF(B34=0,"",B34/C$5) -> 1 | D34: 12875 | E34: =IFERROR(D34/B34,"") -> 804.6875 | F34: 12855 | G34: =IFERROR(F34/D34,"") -> 0.9984466
A35: =A34+7 -> 45802 | B35: 16 | C35: =IF(B35=0,"",B35/C$5) -> 1 | D35: 12845 | E35: =IFERROR(D35/B35,"") -> 802.8125 | F35: 12855 | G35: =IFERROR(F35/D35,"") -> 1.0007785
A36: Monthly Target | B36: 15 | C36: =IF(B36=0,"",B36/C$5) -> 0.9375 | D36: 12250 | E36: =D36/B36 -> 816.66667 | F36: 12250 | G36: =IFERROR(F36/D36,"") -> 1 | H36: 13249 | I36: 12250 | J36: =IF(H36=0,"",H36-I36) -> 999 | K36: =IFERROR((H36-I36)/H36,"") -> 0.075401917 | L36: 10849 | M36: 9300 | N36: =IF(L36=0,"",L36-M36) -> 1549 | O36: =IFERROR((L36-M36)/L36,"") -> 0.14277814 | P36: =H36-L36 -> 2400 | Q36: =I36-M36 -> 2950 | R36: Flood insuranc eon Slocum for the year
A37: =A35+7 -> 45809 | B37: 16 | C37: =IF(B37=0,"",B37/C$5) -> 1 | D37: 12900 | E37: =IFERROR(D37/B37,"") -> 806.25 | F37: 4001 | G37: =IFERROR(F37/D37,"") -> 0.31015504
A38: =A37+7 -> 45816 | B38: 16 | C38: =IF(B38=0,"",B38/C$5) -> 1 | D38: 12900 | E38: =IFERROR(D38/B38,"") -> 806.25 | F38: 11343 | G38: =IFERROR(F38/D38,"") -> 0.87930233
A39: =A38+7 -> 45823 | B39: 16 | C39: =IF(B39=0,"",B39/C$5) -> 1 | D39: 12900 | E39: =IFERROR(D39/B39,"") -> 806.25 | F39: 12920 | G39: =IFERROR(F39/D39,"") -> 1.0015504
A40: =A39+7 -> 45830 | B40: 16 | C40: =IF(B40=0,"",B40/C$5) -> 1 | D40: 12900 | E40: =IFERROR(D40/B40,"") -> 806.25 | F40: 12920 | G40: =IFERROR(F40/D40,"") -> 1.0015504
A41: =A40+7 -> 45837 | B41: 15 | C41: =IF(B41=0,"",B41/C$5) -> 0.9375 | D41: 12050 | E41: =IFERROR(D41/B41,"") -> 803.33333 | F41: 12920 | G41: =IFERROR(F41/D41,"") -> 1.0721992
A42: Monthly Target | B42: 15 | C42: =IF(B42=0,"",B42/C$5) -> 0.9375 | D42: 12250 | E42: =D42/B42 -> 816.66667 | F42: 12250 | G42: =IFERROR(F42/D42,"") -> 1 | H42: 13609 | I42: 12250 | J42: =IF(H42=0,"",H42-I42) -> 1359 | K42: =IFERROR((H42-I42)/H42,"") -> 0.099860387 | L42: 9391 | M42: 9300 | N42: =IF(L42=0,"",L42-M42) -> 91 | O42: =IFERROR((L42-M42)/L42,"") -> 0.0096901288 | P42: =H42-L42 -> 4218 | Q42: =I42-M42 -> 2950 | R42: Stellar
A43: =A41+7 -> 45844 | B43: 15 | C43: =IF(B43=0,"",B43/C$5) -> 0.9375 | D43: 12110 | E43: =IFERROR(D43/B43,"") -> 807.33333 | F43: 10723 | G43: =IFERROR(F43/D43,"") -> 0.88546656
A44: =A43+7 -> 45851 | B44: 16 | C44: =IF(B44=0,"",B44/C$5) -> 1 | D44: 12960 | E44: =IFERROR(D44/B44,"") -> 810 | F44: 10723 | G44: =IFERROR(F44/D44,"") -> 0.82739198
A45: =A44+7 -> 45858 | B45: 16 | C45: =IF(B45=0,"",B45/C$5) -> 1 | D45: 12960 | E45: =IFERROR(D45/B45,"") -> 810 | F45: 10273 | G45: =IFERROR(F45/D45,"") -> 0.79266975
A46: =A45+7 -> 45865 | B46: 16 | C46: =IF(B46=0,"",B46/C$5) -> 1 | D46: 12960 | E46: =IFERROR(D46/B46,"") -> 810 | F46: 10273 | G46: =IFERROR(F46/D46,"") -> 0.79266975
A47: Monthly Target | B47: 15 | C47: =IF(B47=0,"",B47/C$5) -> 0.9375 | D47: 12250 | E47: =D47/B47 -> 816.66667 | F47: 12250 | G47: =IFERROR(F47/D47,"") -> 1 | H47: 10427 | I47: 12250 | J47: =IF(H47=0,"",H47-I47) -> -1823 | K47: =IFERROR((H47-I47)/H47,"") -> -0.17483456 | L47: 14516 | M47: 9300 | N47: =IF(L47=0,"",L47-M47) -> 5216 | O47: =IFERROR((L47-M47)/L47,"") -> 0.35932764 | P47: =H47-L47 -> -4089 | Q47: =I47-M47 -> 2950 | R47: Property Taxes
A48: =A46+7 -> 45872 | B48: 16 | C48: =IF(B48=0,"",B48/C$5) -> 1 | D48: 12960 | E48: =IFERROR(D48/B48,"") -> 810 | F48: 12950 | G48: =IFERROR(F48/D48,"") -> 0.9992284
A49: =A48+7 -> 45879 | B49: 16 | C49: =IF(B49=0,"",B49/C$5) -> 1 | D49: 12960 | E49: =IFERROR(D49/B49,"") -> 810 | F49: 14585 | G49: =IFERROR(F49/D49,"") -> 1.1253858
A50: =A49+7 -> 45886 | B50: 16 | C50: =IF(B50=0,"",B50/C$5) -> 1 | D50: 12960 | E50: =IFERROR(D50/B50,"") -> 810 | F50: 14585 | G50: =IFERROR(F50/D50,"") -> 1.1253858
A51: =A50+7 -> 45893 | B51: 16 | C51: =IF(B51=0,"",B51/C$5) -> 1 | D51: 12960 | E51: =IFERROR(D51/B51,"") -> 810 | F51: 14585 | G51: =IFERROR(F51/D51,"") -> 1.1253858
A52: =A51+7 -> 45900 | B52: 16 | C52: =IF(B52=0,"",B52/C$5) -> 1 | D52: 12960 | E52: =IFERROR(D52/B52,"") -> 810 | F52: 14585 | G52: =IFERROR(F52/D52,"") -> 1.1253858
A53: Monthly Target | B53: 15 | C53: =IF(B53=0,"",B53/C$5) -> 0.9375 | D53: 12250 | E53: =D53/B53 -> 816.66667 | F53: 12250 | G53: =IFERROR(F53/D53,"") -> 1 | H53: 17994 | I53: 12250 | J53: =IF(H53=0,"",H53-I53) -> 5744 | K53: =IFERROR((H53-I53)/H53,"") -> 0.31921752 | L53: 6854 | M53: 9300 | N53: =IF(L53=0,"",L53-M53) -> -2446 | O53: =IFERROR((L53-M53)/L53,"") -> -0.3568719 | P53: =H53-L53 -> 11140 | Q53: =I53-M53 -> 2950
A54: =A52+7 -> 45907 | B54: 16 | C54: =IF(B54=0,"",B54/C$5) -> 1 | D54: 12985 | E54: =IFERROR(D54/B54,"") -> 811.5625 | F54: 12135 | G54: =IFERROR(F54/D54,"") -> 0.93453985
A55: =A54+7 -> 45914 | B55: 16 | C55: =IF(B55=0,"",B55/C$5) -> 1 | D55: 12985 | E55: =IFERROR(D55/B55,"") -> 811.5625 | F55: 12820 | G55: =IFERROR(F55/D55,"") -> 0.98729303
A56: =A55+7 -> 45921 | B56: 16 | C56: =IF(B56=0,"",B56/C$5) -> 1 | D56: 12985 | E56: =IFERROR(D56/B56,"") -> 811.5625 | F56: 12820 | G56: =IFERROR(F56/D56,"") -> 0.98729303
A57: =A56+7 -> 45928 | B57: 16 | C57: =IF(B57=0,"",B57/C$5) -> 1 | D57: 12985 | E57: =IFERROR(D57/B57,"") -> 811.5625 | F57: 12820 | G57: =IFERROR(F57/D57,"") -> 0.98729303
A58: Monthly Target | B58: 15 | C58: =IF(B58=0,"",B58/C$5) -> 0.9375 | D58: 12250 | E58: =D58/B58 -> 816.66667 | F58: 12250 | G58: =IFERROR(F58/D58,"") -> 1 | H58: 13947 | I58: 12250 | J58: =IF(H58=0,"",H58-I58) -> 1697 | K58: =IFERROR((H58-I58)/H58,"") -> 0.12167491 | L58: 8849 | M58: 9300 | N58: =IF(L58=0,"",L58-M58) -> -451 | O58: =IFERROR((L58-M58)/L58,"") -> -0.050966211 | P58: =H58-L58 -> 5098 | Q58: =I58-M58 -> 2950
A59: =A57+7 -> 45935 | B59: 16 | C59: =IF(B59=0,"",B59/C$5) -> 1 | D59: 12985 | E59: =IFERROR(D59/B59,"") -> 811.5625 | F59: 10885 | G59: =IFERROR(F59/D59,"") -> 0.83827493
A60: =A59+7 -> 45942 | B60: 16 | C60: =IF(B60=0,"",B60/C$5) -> 1 | D60: 12985 | E60: =IFERROR(D60/B60,"") -> 811.5625 | F60: 12687 | G60: =IFERROR(F60/D60,"") -> 0.97705044
A61: =A60+7 -> 45949 | B61: 16 | C61: =IF(B61=0,"",B61/C$5) -> 1 | D61: 12985 | E61: =IFERROR(D61/B61,"") -> 811.5625 | F61: 12973 | G61: =IFERROR(F61/D61,"") -> 0.99907586
A62: =A61+7 -> 45956 | B62: 16 | C62: =IF(B62=0,"",B62/C$5) -> 1 | D62: 12985 | E62: =IFERROR(D62/B62,"") -> 811.5625 | F62: 12973 | G62: =IFERROR(F62/D62,"") -> 0.99907586
A63: Monthly Target | B63: 15 | C63: =IF(B63=0,"",B63/C$5) -> 0.9375 | D63: 12250 | E63: =D63/B63 -> 816.66667 | F63: 12250 | G63: =IFERROR(F63/D63,"") -> 1 | H63: 12282 | I63: 12250 | J63: =IF(H63=0,"",H63-I63) -> 32 | K63: =IFERROR((H63-I63)/H63,"") -> 0.0026054389 | L63: 8724 | M63: 9300 | N63: =IF(L63=0,"",L63-M63) -> -576 | O63: =IFERROR((L63-M63)/L63,"") -> -0.066024759 | P63: =H63-L63 -> 3558 | Q63: =I63-M63 -> 2950
A64: =A62+7 -> 45963 | B64: 16 | C64: =IF(B64=0,"",B64/C$5) -> 1 | D64: 12985 | E64: =IFERROR(D64/B64,"") -> 811.5625 | F64: 4390 | G64: =IFERROR(F64/D64,"") -> 0.3380824
A65: =A64+7 -> 45970 | B65: 16 | C65: =IF(B65=0,"",B65/C$5) -> 1 | D65: 12985 | E65: =IFERROR(D65/B65,"") -> 811.5625 | F65: 11429 | G65: =IFERROR(F65/D65,"") -> 0.88016943
A66: =A65+7 -> 45977 | B66: 16 | C66: =IF(B66=0,"",B66/C$5) -> 1 | D66: 12985 | E66: =IFERROR(D66/B66,"") -> 811.5625 | F66: 11429 | G66: =IFERROR(F66/D66,"") -> 0.88016943
A67: =A66+7 -> 45984 | B67: 16 | C67: =IF(B67=0,"",B67/C$5) -> 1 | D67: 12985 | E67: =IFERROR(D67/B67,"") -> 811.5625 | F67: 11958 | G67: =IFERROR(F67/D67,"") -> 0.92090874
A68: =A67+7 -> 45991 | B68: 16 | C68: =IF(B68=0,"",B68/C$5) -> 1 | D68: 12985 | E68: =IFERROR(D68/B68,"") -> 811.5625 | F68: 12796 | G68: =IFERROR(F68/D68,"") -> 0.98544474
A69: Monthly Target | B69: 15 | C69: =IF(B69=0,"",B69/C$5) -> 0.9375 | D69: 12250 | E69: =D69/B69 -> 816.66667 | F69: 12250 | G69: =IFERROR(F69/D69,"") -> 1 | I69: 12250 | J69: =IF(H69=0,"",H69-I69) | K69: =IFERROR((H69-I69)/H69,"") | M69: 9300 | N69: =IF(L69=0,"",L69-M69) | O69: =IFERROR((L69-M69)/L69,"") | P69: =H69-L69 -> 0 | Q69: =I69-M69 -> 2950
A70: =A68+7 -> 45998 | B70: 16 | C70: =IF(B70=0,"",B70/C$5) -> 1 | D70: 12985 | E70: =IFERROR(D70/B70,"") -> 811.5625 | F70: 11849 | G70: =IFERROR(F70/D70,"") -> 0.91251444
A71: =A70+7 -> 46005 | B71: 16 | C71: =IF(B71=0,"",B71/C$5) -> 1 | D71: 12985 | E71: =IFERROR(D71/B71,"") -> 811.5625 | F71: 11849 | G71: =IFERROR(F71/D71,"") -> 0.91251444
A72: =A71+7 -> 46012 | C72: =IF(B72=0,"",B72/C$5) | E72: =IFERROR(D72/B72,"") | G72: =IFERROR(F72/D72,"")
A73: =A72+7 -> 46019 | C73: =IF(B73=0,"",B73/C$5) | E73: =IFERROR(D73/B73,"") | G73: =IFERROR(F73/D73,"")
A74: Monthly Target | B74: 15 | C74: =IF(B74=0,"",B74/C$5) -> 0.9375 | D74: 12250 | E74: =D74/B74 -> 816.66667 | F74: 12250 | G74: =IFERROR(F74/D74,"") -> 1 | I74: 12250 | J74: =IF(H74=0,"",H74-I74) | K74: =IFERROR((H74-I74)/H74,"") | M74: 9300 | N74: =IF(L74=0,"",L74-M74) | O74: =IFERROR((L74-M74)/L74,"") | P74: =H74-L74 -> 0 | Q74: =I74-M74 -> 2950
A75: Annual Total | B75: =AVERAGE(B15,B20,B26,B31,B36,B42,B47,B53,B58,B63,B69,B74) -> 15 | C75: =AVERAGE(C15,C20,C26,C31,C36,C42,C47,C53,C58,C63,C69,C74) -> 0.9375 | D75: =SUM(D15,D20,D26,D31,D36,D42,D47,D53,D58,D63,D69,D74) -> 147000 | E75: =AVERAGE(E15,E20,E26,E31,E36,E42,E47,E53,E58,E63,E69,E74) -> 816.66667 | F75: =SUM(F15,F20,F26,F31,F36,F42,F47,F53,F58,F63,F69,F74) -> 147000 | G75: =AVERAGE(G15,G20,G26,G31,G36,G42,G47,G53,G58,G63,G69,G74) -> 1 | H75: =H15+H20+H26+H31+H36+H42+H47+H53+H58+H63+H69+H74 -> 134192 | I75: =I15+I20+I26+I31+I36+I42+I47+I53+I58+I63+I69+I74 -> 147000 | J75: =IF(H75=0,"",H75-I75) -> -12808 | K75: =IFERROR((H75-I75)/H75,"") -> -0.095445332 | L75: =L15+L20+L26+L31+L36+L42+L47+L53+L58+L63+L69+L74 -> 108494 | M75: =M15+M20+M26+M31+M36+M42+M47+M53+M58+M63+M69+M74 -> 111600 | N75: =IF(L75=0,"",L75-M75) -> -3106 | O75: =IFERROR((L75-M75)/L75,"") -> -0.028628311 | P75: =P15+P20+P26+P31+P36+P42+P47+P53+P58+P63+P69+P74 -> 25698 | Q75: =Q15+Q20+Q26+Q31+Q36+Q42+Q47+Q53+Q58+Q63+Q69+Q74 -> 35400
A76: ** | B76: ** | C76: ** | D76: ** | E76: ** | F76: ** | G76: ** | H76: ** | I76: ** | J76: ** | K76: ** | L76: ** | M76: ** | N76: ** | O76: ** | R76: **

Sheet Rain Tree Apts
A1: KEY
A2: Manual Input
A3: Owner Input or Formula
A4: Formula | B4: Rain Tree Apartments
B5: # of Units | C5: 8 | I5: KPI Tracker
A10: Week Ending Sunday | B10: # of Occupied Units | C10: Occupancy % | D10: Total Leased Rent Amount $ | E10: Average Rent | F10: Total Collections to Date $ | G10: Collection Percentage | H10: Actual Revenue (Monthly Only) | I10: Budgeted Revenue (Monthly Only) | J10: Variance $ | K10: Variance % | L10: Actual Expense (Monthly Only) | M10: Budgeted Expense (Monthly Only | N10: Variance $ | O10: Variance % | P10: Net Income | Q10: Net Income Budgeted | R10: Total Expenses
A11: 45662 | B11: 6 | C11: =IF(B11=0,"",B11/C$5) -> 0.75 | D11: 6400 | E11: =IFERROR(D11/B11,"") -> 1066.6667 | F11: 6551 | G11: =IFERROR(F11/D11,"") -> 1.0235938 | R11: 1442 Tiki Lane, Lancaster, Ohio 43130
A12: =A11+7 -> 45669 | B12: 6 | C12: =IF(B12=0,"",B12/C$5) -> 0.75 | D12: 6400 | E12: =IFERROR(D12/B12,"") -> 1066.6667 | F12: 7041 | G12: =IFERROR(F12/D12,"") -> 1.1001562
A13: =A12+7 -> 45676 | B13: 6 | C13: =IF(B13=0,"",B13/C$5) -> 0.75 | D13: 6500 | E13: =IFERROR(D13/B13,"") -> 1083.3333 | F13: 8101 | G13: =IFERROR(F13/D13,"") -> 1.2463077
A14: =A13+7 -> 45683 | B14: 6 | C14: =IF(B14=0,"",B14/C$5) -> 0.75 | D14: 6500 | E14: =IFERROR(D14/B14,"") -> 1083.3333 | F14: 8101 | G14: =IFERROR(F14/D14,"") -> 1.2463077
A15: Monthly Target | B15: 7 | C15: =IF(B15=0,"",B15/C$5) -> 0.875 | D15: 7500 | E15: =D15/B15 -> 1071.4286 | F15: 7500 | G15: =IFERROR(F15/D15,"") -> 1 | H15: 8101 | I15: 7500 | J15: =IF(H15=0,"",H15-I15) -> 601 | K15: =IFERROR((H15-I15)/H15,"") -> 0.074188372 | L15: 8925 | M15: 6175 | N15: =IF(L15=0,"",L15-M15) -> 2750 | O15: =IFERROR((L15-M15)/L15,"") -> 0.30812325 | P15: =H15-L15 -> -824 | Q15: =I15-M15 -> 1325 | R15: Really high water bill (addressed)
A16: =A14+7 -> 45690 | B16: 6 | C16: =IF(B16=0,"",B16/C$5) -> 0.75 | D16: 6500 | E16: =IFERROR(D16/B16,"") -> 1083.3333 | F16: 533 | G16: =IFERROR(F16/D16,"") -> 0.082
A17: =A16+7 -> 45697 | B17: 6 | C17: =IF(B17=0,"",B17/C$5) -> 0.75 | D17: 6500 | E17: =IFERROR(D17/B17,"") -> 1083.3333 | F17: 6537 | G17: =IFERROR(F17/D17,"") -> 1.0056923
A18: =A17+7 -> 45704 | B18: 6 | C18: =IF(B18=0,"",B18/C$5) -> 0.75 | D18: 6500 | E18: =IFERROR(D18/B18,"") -> 1083.3333 | F18: 6537 | G18: =IFERROR(F18/D18,"") -> 1.0056923
A19: =A18+7 -> 45711 | B19: 6 | C19: =IF(B19=0,"",B19/C$5) -> 0.75 | D19: 6500 | E19: =IFERROR(D19/B19,"") -> 1083.3333 | F19: 6897 | G19: =IFERROR(F19/D19,"") -> 1.0610769
A20: Monthly Target | B20: 7 | C20: =IF(B20=0,"",B20/C$5) -> 0.875 | D20: 7500 | E20: =D20/B20 -> 1071.4286 | F20: 7500 | G20: =IFERROR(F20/D20,"") -> 1 | H20: 7444 | I20: 7500 | J20: =IF(H20=0,"",H20-I20) -> -56 | K20: =IFERROR((H20-I20)/H20,"") -> -0.0075228372 | L20: 8526 | M20: 6175 | N20: =IF(L20=0,"",L20-M20) -> 2351 | O20: =IFERROR((L20-M20)/L20,"") -> 0.27574478 | P20: =H20-L20 -> -1082 | Q20: =I20-M20 -> 1325 | R20: $730 building improvements not in expenses. (1/2 year property taxes paid)
A21: =A19+7 -> 45718 | B21: 8 | C21: =IF(B21=0,"",B21/C$5) -> 1 | D21: 8850 | E21: =IFERROR(D21/B21,"") -> 1106.25 | F21: 533 | G21: =IFERROR(F21/D21,"") -> 0.060225989
A22: =A21+7 -> 45725 | B22: 8 | C22: =IF(B22=0,"",B22/C$5) -> 1 | D22: 8850 | E22: =IFERROR(D22/B22,"") -> 1106.25 | F22: 7765 | G22: =IFERROR(F22/D22,"") -> 0.87740113
A23: =A22+7 -> 45732 | B23: 8 | C23: =IF(B23=0,"",B23/C$5) -> 1 | D23: 8850 | E23: =IFERROR(D23/B23,"") -> 1106.25 | F23: 7765 | G23: =IFERROR(F23/D23,"") -> 0.87740113
A24: =A23+7 -> 45739 | B24: 8 | C24: =IF(B24=0,"",B24/C$5) -> 1 | D24: 8850 | E24: =IFERROR(D24/B24,"") -> 1106.25 | F24: 7765 | G24: =IFERROR(F24/D24,"") -> 0.87740113
A25: =A24+7 -> 45746 | B25: 8 | C25: =IF(B25=0,"",B25/C$5) -> 1 | D25: 8850 | E25: =IFERROR(D25/B25,"") -> 1106.25 | F25: 7765 | G25: =IFERROR(F25/D25,"") -> 0.87740113
A26: Monthly Target | B26: 7 | C26: =IF(B26=0,"",B26/C$5) -> 0.875 | D26: 7500 | E26: =D26/B26 -> 1071.4286 | F26: 7500 | G26: =IFERROR(F26/D26,"") -> 1 | H26: 7765 | I26: 7500 | J26: =IF(H26=0,"",H26-I26) -> 265 | K26: =IFERROR((H26-I26)/H26,"") -> 0.034127495 | L26: 9661 | M26: 6175 | N26: =IF(L26=0,"",L26-M26) -> 3486 | O26: =IFERROR((L26-M26)/L26,"") -> 0.36083221 | P26: =H26-L26 -> -1896 | Q26: =I26-M26 -> 1325 | R26: $2,500 building improvements
A27: =A25+7 -> 45753 | B27: 8 | C27: =IF(B27=0,"",B27/C$5) -> 1 | D27: 8850 | E27: =IFERROR(D27/B27,"") -> 1106.25 | F27: 6902 | G27: =IFERROR(F27/D27,"") -> 0.77988701
A28: =A27+7 -> 45760 | B28: 8 | C28: =IF(B28=0,"",B28/C$5) -> 1 | D28: 8850 | E28: =IFERROR(D28/B28,"") -> 1106.25 | F28: 8490 | G28: =IFERROR(F28/D28,"") -> 0.95932203
A29: =A28+7 -> 45767 | B29: 8 | C29: =IF(B29=0,"",B29/C$5) -> 1 | D29: 8850 | E29: =IFERROR(D29/B29,"") -> 1106.25 | F29: 8850 | G29: =IFERROR(F29/D29,"") -> 1
A30: =A29+7 -> 45774 | B30: 8 | C30: =IF(B30=0,"",B30/C$5) -> 1 | D30: 8850 | E30: =IFERROR(D30/B30,"") -> 1106.25 | F30: 8850 | G30: =IFERROR(F30/D30,"") -> 1
A31: Monthly Target | B31: 7 | C31: =IF(B31=0,"",B31/C$5) -> 0.875 | D31: 7500 | E31: =D31/B31 -> 1071.4286 | F31: 7500 | G31: =IFERROR(F31/D31,"") -> 1 | H31: 9137 | I31: 7500 | J31: =IF(H31=0,"",H31-I31) -> 1637 | K31: =IFERROR((H31-I31)/H31,"") -> 0.17916165 | L31: 4236 | M31: 6175 | N31: =IF(L31=0,"",L31-M31) -> -1939 | O31: =IFERROR((L31-M31)/L31,"") -> -0.45774315 | P31: =H31-L31 -> 4901 | Q31: =I31-M31 -> 1325 | R31: No OUCU mortgage in April
A32: =A30+7 -> 45781 | B32: 8 | C32: =IF(B32=0,"",B32/C$5) -> 1 | D32: 8950 | E32: =IFERROR(D32/B32,"") -> 1118.75 | F32: 6757 | G32: =IFERROR(F32/D32,"") -> 0.75497207
A33: =A32+7 -> 45788 | B33: 8 | C33: =IF(B33=0,"",B33/C$5) -> 1 | D33: 8950 | E33: =IFERROR(D33/B33,"") -> 1118.75 | F33: 9834 | G33: =IFERROR(F33/D33,"") -> 1.098771
A34: =A33+7 -> 45795 | B34: 8 | C34: =IF(B34=0,"",B34/C$5) -> 1 | D34: 8950 | E34: =IFERROR(D34/B34,"") -> 1118.75 | F34: 9834 | G34: =IFERROR(F34/D34,"") -> 1.098771
A35: =A34+7 -> 45802 | B35: 8 | C35: =IF(B35=0,"",B35/C$5) -> 1 | D35: 8950 | E35: =IFERROR(D35/B35,"") -> 1118.75 | F35: 9834 | G35: =IFERROR(F35/D35,"") -> 1.098771
A36: Monthly Target | B36: 7 | C36: =IF(B36=0,"",B36/C$5) -> 0.875 | D36: 7500 | E36: =D36/B36 -> 1071.4286 | F36: 7500 | G36: =IFERROR(F36/D36,"") -> 1 | H36: 9909 | I36: 7500 | J36: =IF(H36=0,"",H36-I36) -> 2409 | K36: =IFERROR((H36-I36)/H36,"") -> 0.24311232 | L36: 7489 | M36: 6175 | N36: =IF(L36=0,"",L36-M36) -> 1314 | O36: =IFERROR((L36-M36)/L36,"") -> 0.17545734 | P36: =H36-L36 -> 2420 | Q36: =I36-M36 -> 1325
A37: =A35+7 -> 45809 | B37: 8 | C37: =IF(B37=0,"",B37/C$5) -> 1 | D37: 8950 | E37: =IFERROR(D37/B37,"") -> 1118.75 | F37: 1418 | G37: =IFERROR(F37/D37,"") -> 0.15843575
A38: =A37+7 -> 45816 | B38: 8 | C38: =IF(B38=0,"",B38/C$5) -> 1 | D38: 8950 | E38: =IFERROR(D38/B38,"") -> 1118.75 | F38: 8950 | G38: =IFERROR(F38/D38,"") -> 1
A39: =A38+7 -> 45823 | B39: 8 | C39: =IF(B39=0,"",B39/C$5) -> 1 | D39: 8950 | E39: =IFERROR(D39/B39,"") -> 1118.75 | F39: 8950 | G39: =IFERROR(F39/D39,"") -> 1
A40: =A39+7 -> 45830 | B40: 8 | C40: =IF(B40=0,"",B40/C$5) -> 1 | D40: 8950 | E40: =IFERROR(D40/B40,"") -> 1118.75 | F40: 8950 | G40: =IFERROR(F40/D40,"") -> 1
A41: =A40+7 -> 45837 | B41: 8 | C41: =IF(B41=0,"",B41/C$5) -> 1 | D41: 8950 | E41: =IFERROR(D41/B41,"") -> 1118.75 | F41: 8950 | G41: =IFERROR(F41/D41,"") -> 1
A42: Monthly Target | B42: 7 | C42: =IF(B42=0,"",B42/C$5) -> 0.875 | D42: 7500 | E42: =D42/B42 -> 1071.4286 | F42: 7500 | G42: =IFERROR(F42/D42,"") -> 1 | H42: 8685 | I42: 7500 | J42: =IF(H42=0,"",H42-I42) -> 1185 | K42: =IFERROR((H42-I42)/H42,"") -> 0.13644214 | L42: 9138 | M42: 6175 | N42: =IF(L42=0,"",L42-M42) -> 2963 | O42: =IFERROR((L42-M42)/L42,"") -> 0.32425038 | P42: =H42-L42 -> -453 | Q42: =I42-M42 -> 1325 | R42: Property Insurance For Year
A43: =A41+7 -> 45844 | B43: 8 | C43: =IF(B43=0,"",B43/C$5) -> 1 | D43: 8950 | E43: =IFERROR(D43/B43,"") -> 1118.75 | F43: 8423 | G43: =IFERROR(F43/D43,"") -> 0.94111732
A44: =A43+7 -> 45851 | B44: 8 | C44: =IF(B44=0,"",B44/C$5) -> 1 | D44: 8950 | E44: =IFERROR(D44/B44,"") -> 1118.75 | F44: 8423 | G44: =IFERROR(F44/D44,"") -> 0.94111732
A45: =A44+7 -> 45858 | B45: 8 | C45: =IF(B45=0,"",B45/C$5) -> 1 | D45: 8950 | E45: =IFERROR(D45/B45,"") -> 1118.75 | F45: 8898 | G45: =IFERROR(F45/D45,"") -> 0.99418994
A46: =A45+7 -> 45865 | B46: 8 | C46: =IF(B46=0,"",B46/C$5) -> 1 | D46: 8950 | E46: =IFERROR(D46/B46,"") -> 1118.75 | F46: 8950 | G46: =IFERROR(F46/D46,"") -> 1
A47: Monthly Target | B47: 7 | C47: =IF(B47=0,"",B47/C$5) -> 0.875 | D47: 7500 | E47: =D47/B47 -> 1071.4286 | F47: 7500 | G47: =IFERROR(F47/D47,"") -> 1 | H47: 10601 | I47: 7500 | J47: =IF(H47=0,"",H47-I47) -> 3101 | K47: =IFERROR((H47-I47)/H47,"") -> 0.29251957 | L47: 10517 | M47: 6175 | N47: =IF(L47=0,"",L47-M47) -> 4342 | O47: =IFERROR((L47-M47)/L47,"") -> 0.41285538 | P47: =H47-L47 -> 84 | Q47: =I47-M47 -> 1325 | R47: Property Taxes
A48: =A46+7 -> 45872 | B48: 7 | C48: =IF(B48=0,"",B48/C$5) -> 0.875 | D48: 7850 | E48: =IFERROR(D48/B48,"") -> 1121.4286 | F48: 7512 | G48: =IFERROR(F48/D48,"") -> 0.95694268
A49: =A48+7 -> 45879 | B49: 7 | C49: =IF(B49=0,"",B49/C$5) -> 0.875 | D49: 7850 | E49: =IFERROR(D49/B49,"") -> 1121.4286 | F49: 7850 | G49: =IFERROR(F49/D49,"") -> 1
A50: =A49+7 -> 45886 | B50: 7 | C50: =IF(B50=0,"",B50/C$5) -> 0.875 | D50: 7850 | E50: =IFERROR(D50/B50,"") -> 1121.4286 | F50: 7850 | G50: =IFERROR(F50/D50,"") -> 1
A51: =A50+7 -> 45893 | B51: 7 | C51: =IF(B51=0,"",B51/C$5) -> 0.875 | D51: 7850 | E51: =IFERROR(D51/B51,"") -> 1121.4286 | F51: 7850 | G51: =IFERROR(F51/D51,"") -> 1
A52: =A51+7 -> 45900 | B52: 7 | C52: =IF(B52=0,"",B52/C$5) -> 0.875 | D52: 7850 | E52: =IFERROR(D52/B52,"") -> 1121.4286 | F52: 7850 | G52: =IFERROR(F52/D52,"") -> 1
A53: Monthly Target | B53: 7 | C53: =IF(B53=0,"",B53/C$5) -> 0.875 | D53: 7500 | E53: =D53/B53 -> 1071.4286 | F53: 7500 | G53: =IFERROR(F53/D53,"") -> 1 | H53: 7369 | I53: 7500 | J53: =IF(H53=0,"",H53-I53) -> -131 | K53: =IFERROR((H53-I53)/H53,"") -> -0.017777175 | L53: 7441 | M53: 6175 | N53: =IF(L53=0,"",L53-M53) -> 1266 | O53: =IFERROR((L53-M53)/L53,"") -> 0.17013842 | P53: =H53-L53 -> -72 | Q53: =I53-M53 -> 1325
A54: =A52+7 -> 45907 | B54: 7 | C54: =IF(B54=0,"",B54/C$5) -> 0.875 | D54: 7850 | E54: =IFERROR(D54/B54,"") -> 1121.4286 | F54: 7323 | G54: =IFERROR(F54/D54,"") -> 0.93286624
A55: =A54+7 -> 45914 | B55: 7 | C55: =IF(B55=0,"",B55/C$5) -> 0.875 | D55: 7850 | E55: =IFERROR(D55/B55,"") -> 1121.4286 | F55: 7850 | G55: =IFERROR(F55/D55,"") -> 1
A56: =A55+7 -> 45921 | B56: 7 | C56: =IF(B56=0,"",B56/C$5) -> 0.875 | D56: 7850 | E56: =IFERROR(D56/B56,"") -> 1121.4286 | F56: 7850 | G56: =IFERROR(F56/D56,"") -> 1
A57: =A56+7 -> 45928 | B57: 7 | C57: =IF(B57=0,"",B57/C$5) -> 0.875 | D57: 7850 | E57: =IFERROR(D57/B57,"") -> 1121.4286 | F57: 7850 | G57: =IFERROR(F57/D57,"") -> 1
A58: Monthly Target | B58: 7 | C58: =IF(B58=0,"",B58/C$5) -> 0.875 | D58: 7500 | E58: =D58/B58 -> 1071.4286 | F58: 7500 | G58: =IFERROR(F58/D58,"") -> 1 | H58: 7825 | I58: 7500 | J58: =IF(H58=0,"",H58-I58) -> 325 | K58: =IFERROR((H58-I58)/H58,"") -> 0.041533546 | L58: 8150 | M58: 6175 | N58: =IF(L58=0,"",L58-M58) -> 1975 | O58: =IFERROR((L58-M58)/L58,"") -> 0.24233129 | P58: =H58-L58 -> -325 | Q58: =I58-M58 -> 1325
A59: =A57+7 -> 45935 | B59: 7 | C59: =IF(B59=0,"",B59/C$5) -> 0.875 | D59: 7850 | E59: =IFERROR(D59/B59,"") -> 1121.4286 | F59: 6052 | G59: =IFERROR(F59/D59,"") -> 0.77095541
A60: =A59+7 -> 45942 | B60: 7 | C60: =IF(B60=0,"",B60/C$5) -> 0.875 | D60: 7850 | E60: =IFERROR(D60/B60,"") -> 1121.4286 | F60: 7429 | G60: =IFERROR(F60/D60,"") -> 0.94636943
A61: =A60+7 -> 45949 | B61: 7 | C61: =IF(B61=0,"",B61/C$5) -> 0.875 | D61: 7850 | E61: =IFERROR(D61/B61,"") -> 1121.4286 | F61: 7873 | G61: =IFERROR(F61/D61,"") -> 1.0029299
A62: =A61+7 -> 45956 | B62: 7 | C62: =IF(B62=0,"",B62/C$5) -> 0.875 | D62: 7850 | E62: =IFERROR(D62/B62,"") -> 1121.4286 | F62: 7873 | G62: =IFERROR(F62/D62,"") -> 1.0029299
A63: Monthly Target | B63: 7 | C63: =IF(B63=0,"",B63/C$5) -> 0.875 | D63: 7500 | E63: =D63/B63 -> 1071.4286 | F63: 7500 | G63: =IFERROR(F63/D63,"") -> 1 | H63: 9352 | I63: 7500 | J63: =IF(H63=0,"",H63-I63) -> 1852 | K63: =IFERROR((H63-I63)/H63,"") -> 0.19803251 | L63: 6908 | M63: 6175 | N63: =IF(L63=0,"",L63-M63) -> 733 | O63: =IFERROR((L63-M63)/L63,"") -> 0.10610886 | P63: =H63-L63 -> 2444 | Q63: =I63-M63 -> 1325
A64: =A62+7 -> 45963 | B64: 8 | C64: =IF(B64=0,"",B64/C$5) -> 1 | D64: 9000 | E64: =IFERROR(D64/B64,"") -> 1125 | F64: 1230 | G64: =IFERROR(F64/D64,"") -> 0.13666667
A65: =A64+7 -> 45970 | B65: 8 | C65: =IF(B65=0,"",B65/C$5) -> 1 | D65: 9000 | E65: =IFERROR(D65/B65,"") -> 1125 | F65: 7882 | G65: =IFERROR(F65/D65,"") -> 0.87577778
A66: =A65+7 -> 45977 | B66: 8 | C66: =IF(B66=0,"",B66/C$5) -> 1 | D66: 9000 | E66: =IFERROR(D66/B66,"") -> 1125 | F66: 7882 | G66: =IFERROR(F66/D66,"") -> 0.87577778
A67: =A66+7 -> 45984 | B67: 8 | C67: =IF(B67=0,"",B67/C$5) -> 1 | D67: 9000 | E67: =IFERROR(D67/B67,"") -> 1125 | F67: 7882 | G67: =IFERROR(F67/D67,"") -> 0.87577778
A68: =A67+7 -> 45991 | B68: 8 | C68: =IF(B68=0,"",B68/C$5) -> 1 | D68: 9000 | E68: =IFERROR(D68/B68,"") -> 1125 | F68: 7882 | G68: =IFERROR(F68/D68,"") -> 0.87577778
A69: Monthly Target | B69: 7 | C69: =IF(B69=0,"",B69/C$5) -> 0.875 | D69: 7500 | E69: =D69/B69 -> 1071.4286 | F69: 7500 | G69: =IFERROR(F69/D69,"") -> 1 | I69: 7500 | J69: =IF(H69=0,"",H69-I69) | K69: =IFERROR((H69-I69)/H69,"") | M69: 6175 | N69: =IF(L69=0,"",L69-M69) | O69: =IFERROR((L69-M69)/L69,"") | P69: =H69-L69 -> 0 | Q69: =I69-M69 -> 1325
A70: =A68+7 -> 45998 | B70: 8 | C70: =IF(B70=0,"",B70/C$5) -> 1 | D70: 9000 | E70: =IFERROR(D70/B70,"") -> 1125 | F70: 7030 | G70: =IFERROR(F70/D70,"") -> 0.78111111
A71: =A70+7 -> 46005 | B71: 8 | C71: =IF(B71=0,"",B71/C$5) -> 1 | D71: 9000 | E71: =IFERROR(D71/B71,"") -> 1125 | F71: 8280 | G71: =IFERROR(F71/D71,"") -> 0.92
A72: =A71+7 -> 46012 | C72: =IF(B72=0,"",B72/C$5) | E72: =IFERROR(D72/B72,"") | G72: =IFERROR(F72/D72,"")
A73: =A72+7 -> 46019 | C73: =IF(B73=0,"",B73/C$5) | E73: =IFERROR(D73/B73,"") | G73: =IFERROR(F73/D73,"")
A74: Monthly Target | B74: 7 | C74: =IF(B74=0,"",B74/C$5) -> 0.875 | D74: 7500 | E74: =D74/B74 -> 1071.4286 | F74: 7500 | G74: =IFERROR(F74/D74,"") -> 1 | I74: 7500 | J74: =IF(H74=0,"",H74-I74) | K74: =IFERROR((H74-I74)/H74,"") | M74: 6175 | N74: =IF(L74=0,"",L74-M74) | O74: =IFERROR((L74-M74)/L74,"") | P74: =H74-L74 -> 0 | Q74: =I74-M74 -> 1325
A75: Annual Total | C75: =IF(B75=0,"",B75/C$5) | E75: =IFERROR(D75/B75,"") | G75: =IFERROR(F75/D75,"") | H75: =H15+H20+H26+H31+H36+H42+H47+H53+H58+H63+H69+H74 -> 86188 | I75: =I15+I20+I26+I31+I36+I42+I47+I53+I58+I63+I69+I74 -> 90000 | J75: =IF(H75=0,"",H75-I75) -> -3812 | K75: =IFERROR((H75-I75)/H75,"") -> -0.044228895 | L75: =L15+L20+L26+L31+L36+L42+L47+L53+L58+L63+L69+L74 -> 80991 | M75: =M15+M20+M26+M31+M36+M42+M47+M53+M58+M63+M69+M74 -> 74100 | N75: =IF(L75=0,"",L75-M75) -> 6891 | O75: =IFERROR((L75-M75)/L75,"") -> 0.085083528 | P75: =P15+P20+P26+P31+P36+P42+P47+P53+P58+P63+P69+P74 -> 5197 | Q75: =Q15+Q20+Q26+Q31+Q36+Q42+Q47+Q53+Q58+Q63+Q69+Q74 -> 15900
A76: ** | B76: ** | C76: ** | D76: ** | E76: ** | F76: ** | G76: ** | H76: ** | I76: ** | J76: ** | K76: ** | L76: ** | M76: ** | N76: ** | O76: ** | P76: ** | Q76: ** | R76: **

Sheet RDE Central
A1: KEY
A2: Manual Input
A3: Owner Input or Formula
A4: Formula | B4: RDE Central
B5: # of Units | C5: 14 | E5: 45870 | I5: KPI Tracker
B6: 3/16/2025 up to 17 Units | D6: 16 | E6: 18
A10: Week Ending Sunday | B10: # of Occupied Units | C10: Occupancy % | D10: Total Leased Rent Amount $ | E10: Average Rent | F10: Total Collections to Date $ | G10: Collection Percentage | H10: Actual Revenue (Monthly Only) | I10: Budgeted Revenue (Monthly Only) | J10: Variance $ | K10: Variance % | L10: Actual Expense (Monthly Only) | M10: Budgeted Expense (Monthly Only | N10: Variance $ | O10: Variance % | P10: Net Income | Q10: Net Income Budgeted | R10: Total Expenses
A11: 45662 | B11: 12 | C11: =IF(B11=0,"",B11/C$5) -> 0.85714286 | D11: 10275 | E11: =IFERROR(D11/B11,"") -> 856.25 | F11: 8775 | G11: =IFERROR(F11/D11,"") -> 0.8540146 | R11: 1153-1155 N Columbus, 1233 Williams, 508 N Columbus, 530-532 N Columbus, 544-566 E Wheeling
A12: =A11+7 -> 45669 | B12: 12 | C12: =IF(B12=0,"",B12/C$5) -> 0.85714286 | D12: 10275 | E12: =IFERROR(D12/B12,"") -> 856.25 | F12: 9575 | G12: =IFERROR(F12/D12,"") -> 0.93187348
A13: =A12+7 -> 45676 | B13: 12 | C13: =IF(B13=0,"",B13/C$5) -> 0.85714286 | D13: 10275 | E13: =IFERROR(D13/B13,"") -> 856.25 | F13: 9575 | G13: =IFERROR(F13/D13,"") -> 0.93187348
A14: =A13+7 -> 45683 | B14: 12 | C14: =IF(B14=0,"",B14/C$5) -> 0.85714286 | D14: 10275 | E14: =IFERROR(D14/B14,"") -> 856.25 | F14: 9575 | G14: =IFERROR(F14/D14,"") -> 0.93187348
A15: Monthly Target | B15: 12 | C15: =IF(B15=0,"",B15/C$5) -> 0.85714286 | D15: 10850 | E15: =D15/B15 -> 904.16667 | F15: 10850 | G15: =IFERROR(F15/D15,"") -> 1 | H15: 9575 | I15: 10850 | J15: =IF(H15=0,"",H15-I15) -> -1275 | K15: =IFERROR((H15-I15)/H15,"") -> -0.13315927 | L15: 7650 | M15: 10000 | N15: =IF(L15=0,"",L15-M15) -> -2350 | O15: =IFERROR((L15-M15)/L15,"") -> -0.30718954 | P15: =H15-L15 -> 1925 | Q15: =I15-M15 -> 850
A16: =A14+7 -> 45690 | B16: 12 | C16: =IF(B16=0,"",B16/C$5) -> 0.85714286 | D16: 10275 | E16: =IFERROR(D16/B16,"") -> 856.25 | F16: 533 | G16: =IFERROR(F16/D16,"") -> 0.051873479
A17: =A16+7 -> 45697 | B17: 12 | C17: =IF(B17=0,"",B17/C$5) -> 0.85714286 | D17: 10275 | E17: =IFERROR(D17/B17,"") -> 856.25 | F17: 9625 | G17: =IFERROR(F17/D17,"") -> 0.93673966
A18: =A17+7 -> 45704 | B18: 12 | C18: =IF(B18=0,"",B18/C$5) -> 0.85714286 | D18: 10275 | E18: =IFERROR(D18/B18,"") -> 856.25 | F18: 9625 | G18: =IFERROR(F18/D18,"") -> 0.93673966
A19: =A18+7 -> 45711 | B19: 12 | C19: =IF(B19=0,"",B19/C$5) -> 0.85714286 | D19: 10275 | E19: =IFERROR(D19/B19,"") -> 856.25 | F19: 9689 | G19: =IFERROR(F19/D19,"") -> 0.94296837
A20: Monthly Target | B20: 12 | C20: =IF(B20=0,"",B20/C$5) -> 0.85714286 | D20: 10850 | E20: =D20/B20 -> 904.16667 | F20: 10850 | G20: =IFERROR(F20/D20,"") -> 1 | H20: 9789 | I20: 10850 | J20: =IF(H20=0,"",H20-I20) -> -1061 | K20: =IFERROR((H20-I20)/H20,"") -> -0.10838697 | L20: 9702 | M20: 10000 | N20: =IF(L20=0,"",L20-M20) -> -298 | O20: =IFERROR((L20-M20)/L20,"") -> -0.030715316 | P20: =H20-L20 -> 87 | Q20: =I20-M20 -> 850 | R20: $9,000 in building improvements not in expenses (1/2 year property taxes paid)
A21: =A19+7 -> 45718 | B21: 9 | C21: =IF(B21=0,"",B21/C$5) -> 0.64285714 | D21: 8650 | E21: =IFERROR(D21/B21,"") -> 961.11111 | F21: 5350 | G21: =IFERROR(F21/D21,"") -> 0.61849711
A22: =A21+7 -> 45725 | B22: 9 | C22: =IF(B22=0,"",B22/D$6) -> 0.5625 | D22: 8650 | E22: =IFERROR(D22/B22,"") -> 961.11111 | F22: 8650 | G22: =IFERROR(F22/D22,"") -> 1
A23: =A22+7 -> 45732 | B23: 13 | C23: =IF(B23=0,"",B23/D$6) -> 0.8125 | D23: 10835 | E23: =IFERROR(D23/B23,"") -> 833.46154 | F23: 9200 | G23: =IFERROR(F23/D23,"") -> 0.84910014
A24: =A23+7 -> 45739 | B24: 13 | C24: =IF(B24=0,"",B24/D$6) -> 0.8125 | D24: 10835 | E24: =IFERROR(D24/B24,"") -> 833.46154 | F24: 10442 | G24: =IFERROR(F24/D24,"") -> 0.96372866
A25: =A24+7 -> 45746 | B25: 13 | C25: =IF(B25=0,"",B25/D$6) -> 0.8125 | D25: 10835 | E25: =IFERROR(D25/B25,"") -> 833.46154 | F25: 10442 | G25: =IFERROR(F25/D25,"") -> 0.96372866
A26: Monthly Target | B26: 15 | C26: =IF(B26=0,"",B26/D$6) -> 0.9375 | D26: 10850 | E26: =D26/B26 -> 723.33333 | F26: 10850 | G26: =IFERROR(F26/D26,"") -> 1 | H26: 10442 | I26: 10850 | J26: =IF(H26=0,"",H26-I26) -> -408 | K26: =IFERROR((H26-I26)/H26,"") -> -0.039072975 | L26: 23891 | M26: 10000 | N26: =IF(L26=0,"",L26-M26) -> 13891 | O26: =IFERROR((L26-M26)/L26,"") -> 0.58143234 | P26: =H26-L26 -> -13449 | Q26: =I26-M26 -> 850 | R26: $15,000 Building Improvements Sweeneys
A27: =A25+7 -> 45753 | B27: 14 | C27: =IF(B27=0,"",B27/D$6) -> 0.875 | D27: 11600 | E27: =IFERROR(D27/B27,"") -> 828.57143 | F27: 11535 | G27: =IFERROR(F27/D27,"") -> 0.99439655
A28: =A27+7 -> 45760 | B28: 14 | C28: =IF(B28=0,"",B28/D$6) -> 0.875 | D28: 11600 | E28: =IFERROR(D28/B28,"") -> 828.57143 | F28: 11535 | G28: =IFERROR(F28/D28,"") -> 0.99439655
A29: =A28+7 -> 45767 | B29: 14 | C29: =IF(B29=0,"",B29/D$6) -> 0.875 | D29: 11600 | E29: =IFERROR(D29/B29,"") -> 828.57143 | F29: 11353 | G29: =IFERROR(F29/D29,"") -> 0.9787069
A30: =A29+7 -> 45774 | B30: 13 | C30: =IF(B30=0,"",B30/D$6) -> 0.8125 | D30: 10100 | E30: =IFERROR(D30/B30,"") -> 776.92308 | F30: 11535 | G30: =IFERROR(F30/D30,"") -> 1.1420792
A31: Monthly Target | B31: 12 | C31: =IF(B31=0,"",B31/C$5) -> 0.85714286 | D31: 10850 | E31: =D31/B31 -> 904.16667 | F31: 10850 | G31: =IFERROR(F31/D31,"") -> 1 | H31: 9955 | I31: 10850 | J31: =IF(H31=0,"",H31-I31) -> -895 | K31: =IFERROR((H31-I31)/H31,"") -> -0.089904571 | L31: 38751 | M31: 10000 | N31: =IF(L31=0,"",L31-M31) -> 28751 | O31: =IFERROR((L31-M31)/L31,"") -> 0.74194214 | P31: =H31-L31 -> -28796 | Q31: =I31-M31 -> 850
A32: =A30+7 -> 45781 | B32: 14 | C32: =IF(B32=0,"",B32/D$6) -> 0.875 | D32: 10885 | E32: =IFERROR(D32/B32,"") -> 777.5 | F32: 8335 | G32: =IFERROR(F32/D32,"") -> 0.76573266
A33: =A32+7 -> 45788 | B33: 15 | C33: =IF(B33=0,"",B33/D$6) -> 0.9375 | D33: 11735 | E33: =IFERROR(D33/B33,"") -> 782.33333 | F33: 11516 | G33: =IFERROR(F33/D33,"") -> 0.98133788
A34: =A33+7 -> 45795 | B34: 15 | C34: =IF(B34=0,"",B34/D$6) -> 0.9375 | D34: 11735 | E34: =IFERROR(D34/B34,"") -> 782.33333 | F34: 11516 | G34: =IFERROR(F34/D34,"") -> 0.98133788
A35: =A34+7 -> 45802 | B35: 15 | C35: =IF(B35=0,"",B35/D$6) -> 0.9375 | D35: 11735 | E35: =IFERROR(D35/B35,"") -> 782.33333 | F35: 12041 | G35: =IFERROR(F35/D35,"") -> 1.0260758
A36: Monthly Target | B36: 12 | C36: =IF(B36=0,"",B36/C$5) -> 0.85714286 | D36: 10850 | E36: =D36/B36 -> 904.16667 | F36: 10850 | G36: =IFERROR(F36/D36,"") -> 1 | H36: 15061 | I36: 10850 | J36: =IF(H36=0,"",H36-I36) -> 4211 | K36: =IFERROR((H36-I36)/H36,"") -> 0.27959631 | L36: 13324 | M36: 10000 | N36: =IF(L36=0,"",L36-M36) -> 3324 | O36: =IFERROR((L36-M36)/L36,"") -> 0.24947463 | P36: =H36-L36 -> 1737 | Q36: =I36-M36 -> 850 | R36: $4,000 in building improvments on Sweeneys
A37: =A35+7 -> 45809 | B37: 15 | C37: =IF(B37=0,"",B37/D$6) -> 0.9375 | D37: 11735 | E37: =IFERROR(D37/B37,"") -> 782.33333 | F37: 6189 | G37: =IFERROR(F37/D37,"") -> 0.52739668 | R37: 5
A38: =A37+7 -> 45816 | B38: 16 | C38: =IF(B38=0,"",B38/D$6) -> 1 | D38: 13775 | E38: =IFERROR(D38/B38,"") -> 860.9375 | F38: 12025 | G38: =IFERROR(F38/D38,"") -> 0.87295826
A39: =A38+7 -> 45823 | B39: 16 | C39: =IF(B39=0,"",B39/D$6) -> 1 | D39: 13775 | E39: =IFERROR(D39/B39,"") -> 860.9375 | F39: 12825 | G39: =IFERROR(F39/D39,"") -> 0.93103448
A40: =A39+7 -> 45830 | B40: 16 | C40: =IF(B40=0,"",B40/D$6) -> 1 | D40: 13775 | E40: =IFERROR(D40/B40,"") -> 860.9375 | F40: 12825 | G40: =IFERROR(F40/D40,"") -> 0.93103448
A41: =A40+7 -> 45837 | B41: 16 | C41: =IF(B41=0,"",B41/D$6) -> 1 | D41: 13775 | E41: =IFERROR(D41/B41,"") -> 860.9375 | F41: 12825 | G41: =IFERROR(F41/D41,"") -> 0.93103448
A42: Monthly Target | B42: 13 | C42: =IF(B42=0,"",B42/C$5) -> 0.92857143 | D42: 13850 | E42: =D42/B42 -> 1065.3846 | F42: 13850 | G42: =IFERROR(F42/D42,"") -> 1 | H42: 12500 | I42: 13850 | J42: =IF(H42=0,"",H42-I42) -> -1350 | K42: =IFERROR((H42-I42)/H42,"") -> -0.108 | L42: 21151 | M42: 12500 | N42: =IF(L42=0,"",L42-M42) -> 8651 | O42: =IFERROR((L42-M42)/L42,"") -> 0.40901139 | P42: =H42-L42 -> -8651 | Q42: =I42-M42 -> 1350 | R42: 18000 in building improvements mostly Sweeneys
A43: =A41+7 -> 45844 | B43: 15 | C43: =IF(B43=0,"",B43/D$6) -> 0.9375 | D43: 13050 | E43: =IFERROR(D43/B43,"") -> 870 | F43: 10550 | G43: =IFERROR(F43/D43,"") -> 0.80842912
A44: =A43+7 -> 45851 | B44: 15 | C44: =IF(B44=0,"",B44/D$6) -> 0.9375 | D44: 13050 | E44: =IFERROR(D44/B44,"") -> 870 | F44: 11550 | G44: =IFERROR(F44/D44,"") -> 0.88505747
A45: =A44+7 -> 45858 | B45: 15 | C45: =IF(B45=0,"",B45/D$6) -> 0.9375 | D45: 13050 | E45: =IFERROR(D45/B45,"") -> 870 | F45: 12350 | G45: =IFERROR(F45/D45,"") -> 0.94636015
A46: =A45+7 -> 45865 | B46: 15 | C46: =IF(B46=0,"",B46/D$6) -> 0.9375 | D46: 13050 | E46: =IFERROR(D46/B46,"") -> 870 | F46: 12350 | G46: =IFERROR(F46/D46,"") -> 0.94636015
A47: Monthly Target | B47: 13 | C47: =IF(B47=0,"",B47/C$5) -> 0.92857143 | D47: 13850 | E47: =D47/B47 -> 1065.3846 | F47: 13850 | G47: =IFERROR(F47/D47,"") -> 1 | H47: 12742 | I47: 13850 | J47: =IF(H47=0,"",H47-I47) -> -1108 | K47: =IFERROR((H47-I47)/H47,"") -> -0.086956522 | L47: 16720 | M47: 12500 | N47: =IF(L47=0,"",L47-M47) -> 4220 | O47: =IFERROR((L47-M47)/L47,"") -> 0.25239234 | P47: =H47-L47 -> -3978 | Q47: =I47-M47 -> 1350 | R47: 20,000 in building improvements and property taxes
A48: =A46+7 -> 45872 | B48: 17 | C48: =IF(B48=0,"",B48/E$6) -> 0.94444444 | D48: 14595 | E48: =IFERROR(D48/B48,"") -> 858.52941 | F48: 11788 | G48: =IFERROR(F48/D48,"") -> 0.80767386
A49: =A48+7 -> 45879 | B49: 16 | C49: =IF(B49=0,"",B49/E$6) -> 0.88888889 | D49: 13895 | E49: =IFERROR(D49/B49,"") -> 868.4375 | F49: 12638 | G49: =IFERROR(F49/D49,"") -> 0.9095358
A50: =A49+7 -> 45886 | B50: 15 | C50: =IF(B50=0,"",B50/E$6) -> 0.83333333 | D50: 12845 | E50: =IFERROR(D50/B50,"") -> 856.33333 | F50: 12638 | G50: =IFERROR(F50/D50,"") -> 0.98388478
A51: =A50+7 -> 45893 | B51: 15 | C51: =IF(B51=0,"",B51/E$6) -> 0.83333333 | D51: 12845 | E51: =IFERROR(D51/B51,"") -> 856.33333 | F51: 14338 | G51: =IFERROR(F51/D51,"") -> 1.116232
A52: =A51+7 -> 45900 | B52: 15 | C52: =IF(B52=0,"",B52/E$6) -> 0.83333333 | D52: 12845 | E52: =IFERROR(D52/B52,"") -> 856.33333 | F52: 14338 | G52: =IFERROR(F52/D52,"") -> 1.116232
A53: Monthly Target | B53: 13 | C53: =IF(B53=0,"",B53/C$5) -> 0.92857143 | D53: 13850 | E53: =D53/B53 -> 1065.3846 | F53: 13850 | G53: =IFERROR(F53/D53,"") -> 1 | H53: 16902 | I53: 13850 | J53: =IF(H53=0,"",H53-I53) -> 3052 | K53: =IFERROR((H53-I53)/H53,"") -> 0.18057035 | L53: 13380 | M53: 12500 | N53: =IF(L53=0,"",L53-M53) -> 880 | O53: =IFERROR((L53-M53)/L53,"") -> 0.065769806 | P53: =H53-L53 -> 3522 | Q53: =I53-M53 -> 1350 | R53: Plus $8,500 in property stabalization
A54: =A52+7 -> 45907 | B54: 15 | C54: =IF(B54=0,"",B54/E$6) -> 0.83333333 | D54: 12845 | E54: =IFERROR(D54/B54,"") -> 856.33333 | F54: 12047 | G54: =IFERROR(F54/D54,"") -> 0.93787466
A55: =A54+7 -> 45914 | B55: 16 | C55: =IF(B55=0,"",B55/E$6) -> 0.88888889 | D55: 13995 | E55: =IFERROR(D55/B55,"") -> 874.6875 | F55: 12937 | G55: =IFERROR(F55/D55,"") -> 0.92440157
A56: =A55+7 -> 45921 | B56: 16 | C56: =IF(B56=0,"",B56/E$6) -> 0.88888889 | D56: 13995 | E56: =IFERROR(D56/B56,"") -> 874.6875 | F56: 13377 | G56: =IFERROR(F56/D56,"") -> 0.95584137
A57: =A56+7 -> 45928 | B57: 17 | C57: =IF(B57=0,"",B57/E$6) -> 0.94444444 | D57: 14745 | E57: =IFERROR(D57/B57,"") -> 867.35294 | F57: 14127 | G57: =IFERROR(F57/D57,"") -> 0.95808749
A58: Monthly Target | B58: 13 | C58: =IF(B58=0,"",B58/C$5) -> 0.92857143 | D58: 13850 | E58: =D58/B58 -> 1065.3846 | F58: 13850 | G58: =IFERROR(F58/D58,"") -> 1 | H58: 13827 | I58: 13850 | J58: =IF(H58=0,"",H58-I58) -> -23 | K58: =IFERROR((H58-I58)/H58,"") -> -0.0016634122 | L58: 18126 | M58: 12500 | N58: =IF(L58=0,"",L58-M58) -> 5626 | O58: =IFERROR((L58-M58)/L58,"") -> 0.31038288 | P58: =H58-L58 -> -4299 | Q58: =I58-M58 -> 1350 | R58: Plus Sweeneys 10k Building Improvements
A59: =A57+7 -> 45935 | B59: 17 | C59: =IF(B59=0,"",B59/E$6) -> 0.94444444 | D59: 15145 | E59: =IFERROR(D59/B59,"") -> 890.88235 | F59: 12495 | G59: =IFERROR(F59/D59,"") -> 0.82502476
A60: =A59+7 -> 45942 | B60: 16 | C60: =IF(B60=0,"",B60/E$6) -> 0.88888889 | D60: 14395 | E60: =IFERROR(D60/B60,"") -> 899.6875 | F60: 14052 | G60: =IFERROR(F60/D60,"") -> 0.97617228
A61: =A60+7 -> 45949 | B61: 16 | C61: =IF(B61=0,"",B61/E$6) -> 0.88888889 | D61: 14395 | E61: =IFERROR(D61/B61,"") -> 899.6875 | F61: 14598 | G61: =IFERROR(F61/D61,"") -> 1.0141021
A62: =A61+7 -> 45956 | B62: 17 | C62: =IF(B62=0,"",B62/E$6) -> 0.94444444 | D62: 15805 | E62: =IFERROR(D62/B62,"") -> 929.70588 | F62: 14958 | G62: =IFERROR(F62/D62,"") -> 0.94640936
A63: Monthly Target | B63: 13 | C63: =IF(B63=0,"",B63/C$5) -> 0.92857143 | D63: 13850 | E63: =D63/B63 -> 1065.3846 | F63: 13850 | G63: =IFERROR(F63/D63,"") -> 1 | H63: 17039 | I63: 13850 | J63: =IF(H63=0,"",H63-I63) -> 3189 | K63: =IFERROR((H63-I63)/H63,"") -> 0.18715887 | L63: 13038 | M63: 12500 | N63: =IF(L63=0,"",L63-M63) -> 538 | O63: =IFERROR((L63-M63)/L63,"") -> 0.041263998 | P63: =H63-L63 -> 4001 | Q63: =I63-M63 -> 1350 | R63: Plus $56,000 in Stabalization mostly Sweeneys
A64: =A62+7 -> 45963 | B64: 18 | C64: =IF(B64=0,"",B64/E$6) -> 1 | D64: 16695 | E64: =IFERROR(D64/B64,"") -> 927.5 | F64: 10835 | G64: =IFERROR(F64/D64,"") -> 0.64899671
A65: =A64+7 -> 45970 | B65: 18 | C65: =IF(B65=0,"",B65/E$6) -> 1 | D65: 16695 | E65: =IFERROR(D65/B65,"") -> 927.5 | F65: 16292 | G65: =IFERROR(F65/D65,"") -> 0.97586104
A66: =A65+7 -> 45977 | B66: 18 | C66: =IF(B66=0,"",B66/E$6) -> 1 | D66: 16695 | E66: =IFERROR(D66/B66,"") -> 927.5 | F66: 17607 | G66: =IFERROR(F66/D66,"") -> 1.0546271
A67: =A66+7 -> 45984 | B67: 18 | C67: =IF(B67=0,"",B67/E$6) -> 1 | D67: 16695 | E67: =IFERROR(D67/B67,"") -> 927.5 | F67: 17067 | G67: =IFERROR(F67/D67,"") -> 1.0222821
A68: =A67+7 -> 45991 | B68: 18 | C68: =IF(B68=0,"",B68/E$6) -> 1 | D68: 16695 | E68: =IFERROR(D68/B68,"") -> 927.5 | F68: 17067 | G68: =IFERROR(F68/D68,"") -> 1.0222821
A69: Monthly Target | B69: 13 | C69: =IF(B69=0,"",B69/C$5) -> 0.92857143 | D69: 13850 | E69: =D69/B69 -> 1065.3846 | F69: 13850 | G69: =IFERROR(F69/D69,"") -> 1 | I69: 13850 | J69: =IF(H69=0,"",H69-I69) | K69: =IFERROR((H69-I69)/H69,"") | M69: 12500 | N69: =IF(L69=0,"",L69-M69) | O69: =IFERROR((L69-M69)/L69,"") | P69: =H69-L69 -> 0 | Q69: =I69-M69 -> 1350
A70: =A68+7 -> 45998 | B70: 18 | C70: =IF(B70=0,"",B70/E$6) -> 1 | D70: 16695 | E70: =IFERROR(D70/B70,"") -> 927.5 | F70: 14805 | G70: =IFERROR(F70/D70,"") -> 0.88679245
A71: =A70+7 -> 46005 | B71: 18 | C71: =IF(B71=0,"",B71/E$6) -> 1 | D71: 16695 | E71: =IFERROR(D71/B71,"") -> 927.5 | F71: 15695 | G71: =IFERROR(F71/D71,"") -> 0.94010183
A72: =A71+7 -> 46012 | C72: =IF(B72=0,"",B72/C$5) | E72: =IFERROR(D72/B72,"") | G72: =IFERROR(F72/D72,"")
A73: =A72+7 -> 46019 | C73: =IF(B73=0,"",B73/C$5) | E73: =IFERROR(D73/B73,"") | G73: =IFERROR(F73/D73,"")
A74: Monthly Target | B74: 13 | C74: =IF(B74=0,"",B74/C$5) -> 0.92857143 | D74: 13850 | E74: =D74/B74 -> 1065.3846 | F74: 13850 | G74: =IFERROR(F74/D74,"") -> 1 | I74: 13850 | J74: =IF(H74=0,"",H74-I74) | K74: =IFERROR((H74-I74)/H74,"") | M74: 12500 | N74: =IF(L74=0,"",L74-M74) | O74: =IFERROR((L74-M74)/L74,"") | P74: =H74-L74 -> 0 | Q74: =I74-M74 -> 1350
A75: Annual Total | C75: =IF(B75=0,"",B75/C$5) | E75: =IFERROR(D75/B75,"") | G75: =IFERROR(F75/D75,"") | H75: =H15+H20+H26+H31+H36+H42+H47+H53+H58+H63+H69+H74 -> 127832 | I75: =I15+I20+I26+I31+I36+I42+I47+I53+I58+I63+I69+I74 -> 151200 | J75: =IF(H75=0,"",H75-I75) -> -23368 | K75: =IFERROR((H75-I75)/H75,"") -> -0.18280243 | L75: =L15+L20+L26+L31+L36+L42+L47+L53+L58+L63+L69+L74 -> 175733 | M75: =M15+M20+M26+M31+M36+M42+M47+M53+M58+M63+M69+M74 -> 137500 | N75: =IF(L75=0,"",L75-M75) -> 38233 | O75: =IFERROR((L75-M75)/L75,"") -> 0.21756301 | P75: =P15+P20+P26+P31+P36+P42+P47+P53+P58+P63+P69+P74 -> -47901 | Q75: =Q15+Q20+Q26+Q31+Q36+Q42+Q47+Q53+Q58+Q63+Q69+Q74 -> 13700
A76: ** | B76: ** | C76: ** | D76: ** | E76: ** | F76: ** | G76: ** | H76: ** | I76: ** | J76: ** | K76: ** | L76: ** | M76: ** | N76: ** | O76: ** | P76: ** | Q76: ** | R76: **

Sheet ENPH
A1: KEY
A2: Manual Input
A3: Owner Input or Formula
A4: Formula | B4: ENPH
B5: # of Units | C5: 19 | D5: AO 4/1 | E5: 21 | F5: AO 4/20 | G5: 22 | I5: KPI Tracker
A10: Week Ending Sunday | B10: # of Occupied Units | C10: Occupancy % | D10: Total Leased Rent Amount $ | E10: Average Rent | F10: Total Collections to Date $ | G10: Collection Percentage | H10: Actual Revenue (Monthly Only) | I10: Budgeted Revenue (Monthly Only) | J10: Variance $ | K10: Variance % | L10: Actual Expense (Monthly Only) | M10: Budgeted Expense (Monthly Only | N10: Variance $ | O10: Variance % | P10: Net Income | Q10: Net Income Budgeted | R10: Notes:
A11: 45662 | B11: 18 | C11: =IF(B11=0,"",B11/C$5) -> 0.94736842 | D11: 17761 | E11: =IFERROR(D11/B11,"") -> 986.72222 | F11: 14359 | G11: =IFERROR(F11/D11,"") -> 0.80845673 | R11: 122 Harrison, 730 E Mulberry, 410 W Wheeling, 129 E Chestnut, 620 N Zane, 434 N Maple, 720 Hubert, 1215 N Columbus, 1401 W Mulberry (Garage)
A12: =A11+7 -> 45669 | B12: 18 | C12: =IF(B12=0,"",B12/C$5) -> 0.94736842 | D12: 17772 | E12: =IFERROR(D12/B12,"") -> 987.33333 | F12: 17761 | G12: =IFERROR(F12/D12,"") -> 0.99938105
A13: =A12+7 -> 45676 | B13: 18 | C13: =IF(B13=0,"",B13/C$5) -> 0.94736842 | D13: 18147 | E13: =IFERROR(D13/B13,"") -> 1008.1667 | F13: 17772 | G13: =IFERROR(F13/D13,"") -> 0.97933543
A14: =A13+7 -> 45683 | B14: 17 | C14: =IF(B14=0,"",B14/C$5) -> 0.89473684 | D14: 16947 | E14: =IFERROR(D14/B14,"") -> 996.88235 | F14: 17930 | G14: =IFERROR(F14/D14,"") -> 1.0580044
A15: Monthly Target | B15: 18 | C15: =IF(B15=0,"",B15/C$5) -> 0.94736842 | D15: 18850 | E15: =D15/B15 -> 1047.2222 | F15: 18850 | G15: =IFERROR(F15/D15,"") -> 1 | H15: 18824 | I15: 18850 | J15: =IF(H15=0,"",H15-I15) -> -26 | K15: =IFERROR((H15-I15)/H15,"") -> -0.0013812155 | L15: 22008 | M15: 17000 | N15: =IF(L15=0,"",L15-M15) -> 5008 | O15: =IFERROR((L15-M15)/L15,"") -> 0.22755362 | P15: =H15-L15 -> -3184 | Q15: =I15-M15 -> 1850 | R15: Property Tax payment for non escrowed properties
A16: =A14+7 -> 45690 | B16: 17 | C16: =IF(B16=0,"",B16/C$5) -> 0.89473684 | D16: 16947 | E16: =IFERROR(D16/B16,"") -> 996.88235 | F16: 8430 | G16: =IFERROR(F16/D16,"") -> 0.49743317
A17: =A16+7 -> 45697 | B17: 16 | C17: =IF(B17=0,"",B17/C$5) -> 0.84210526 | D17: 17036 | E17: =IFERROR(D17/B17,"") -> 1064.75 | F17: 14415 | G17: =IFERROR(F17/D17,"") -> 0.84614933
A18: =A17+7 -> 45704 | B18: 16 | C18: =IF(B18=0,"",B18/C$5) -> 0.84210526 | D18: 17036 | E18: =IFERROR(D18/B18,"") -> 1064.75 | F18: 15665 | G18: =IFERROR(F18/D18,"") -> 0.91952336
A19: =A18+7 -> 45711 | B19: 16 | C19: =IF(B19=0,"",B19/C$5) -> 0.84210526 | D19: 17036 | E19: =IFERROR(D19/B19,"") -> 1064.75 | F19: 16565 | G19: =IFERROR(F19/D19,"") -> 0.97235266
A20: Monthly Target | B20: 18 | C20: =IF(B20=0,"",B20/C$5) -> 0.94736842 | D20: 18850 | E20: =D20/B20 -> 1047.2222 | F20: 18850 | G20: =IFERROR(F20/D20,"") -> 1 | H20: 22822 | I20: 18850 | J20: =IF(H20=0,"",H20-I20) -> 3972 | K20: =IFERROR((H20-I20)/H20,"") -> 0.17404259 | L20: 19928 | M20: 17000 | N20: =IF(L20=0,"",L20-M20) -> 2928 | O20: =IFERROR((L20-M20)/L20,"") -> 0.14692894 | P20: =H20-L20 -> 2894 | Q20: =I20-M20 -> 1850 | R20: 1/2 year property taxes and $3700 in building improvements not included
A21: =A19+7 -> 45718 | B21: 18 | C21: =IF(B21=0,"",B21/C$5) -> 0.94736842 | D21: 19761 | E21: =IFERROR(D21/B21,"") -> 1097.8333 | F21: 7694 | G21: =IFERROR(F21/D21,"") -> 0.38935277
A22: =A21+7 -> 45725 | B22: 18 | C22: =IF(B22=0,"",B22/C$5) -> 0.94736842 | D22: 19761 | E22: =IFERROR(D22/B22,"") -> 1097.8333 | F22: 16850 | G22: =IFERROR(F22/D22,"") -> 0.85268964
A23: =A22+7 -> 45732 | B23: 18 | C23: =IF(B23=0,"",B23/C$5) -> 0.94736842 | D23: 19761 | E23: =IFERROR(D23/B23,"") -> 1097.8333 | F23: 16850 | G23: =IFERROR(F23/D23,"") -> 0.85268964
A24: =A23+7 -> 45739 | B24: 18 | C24: =IF(B24=0,"",B24/C$5) -> 0.94736842 | D24: 19761 | E24: =IFERROR(D24/B24,"") -> 1097.8333 | F24: 18168 | G24: =IFERROR(F24/D24,"") -> 0.91938667
A25: =A24+7 -> 45746 | B25: 18 | C25: =IF(B25=0,"",B25/C$5) -> 0.94736842 | D25: 19761 | E25: =IFERROR(D25/B25,"") -> 1097.8333 | F25: 18543 | G25: =IFERROR(F25/D25,"") -> 0.93836344
A26: Monthly Target | B26: 18 | C26: =IF(B26=0,"",B26/C$5) -> 0.94736842 | D26: 18850 | E26: =D26/B26 -> 1047.2222 | F26: 18850 | G26: =IFERROR(F26/D26,"") -> 1 | H26: 18543 | I26: 18850 | J26: =IF(H26=0,"",H26-I26) -> -307 | K26: =IFERROR((H26-I26)/H26,"") -> -0.016556113 | L26: 30094 | M26: 17000 | N26: =IF(L26=0,"",L26-M26) -> 13094 | O26: =IFERROR((L26-M26)/L26,"") -> 0.43510334 | P26: =H26-L26 -> -11551 | Q26: =I26-M26 -> 1850 | R26: $6,000 building improvements 1401 Mulberry and $2700 apraisal costs
A27: =A25+7 -> 45753 | B27: 21 | C27: =IF(B27=0,"",B27/E$5) -> 1 | D27: 22861 | E27: =IFERROR(D27/B27,"") -> 1088.619 | F27: 16025 | G27: =IFERROR(F27/D27,"") -> 0.70097546
A28: =A27+7 -> 45760 | B28: 21 | C28: =IF(B28=0,"",B28/E$5) -> 1 | D28: 22861 | E28: =IFERROR(D28/B28,"") -> 1088.619 | F28: 20275 | G28: =IFERROR(F28/D28,"") -> 0.88688159
A29: =A28+7 -> 45767 | B29: 22 | C29: =IF(B29=0,"",B29/G$5) -> 1 | D29: 23861 | E29: =IFERROR(D29/B29,"") -> 1084.5909 | F29: 20275 | G29: =IFERROR(F29/D29,"") -> 0.84971292
A30: =A29+7 -> 45774 | B30: 21 | C30: =IF(B30=0,"",B30/G$5) -> 0.95454545 | D30: 23811 | E30: =IFERROR(D30/B30,"") -> 1133.8571 | F30: 20563 | G30: =IFERROR(F30/D30,"") -> 0.86359246
A31: Monthly Target | B31: 18 | C31: =IF(B31=0,"",B31/C$5) -> 0.94736842 | D31: 18850 | E31: =D31/B31 -> 1047.2222 | F31: 18850 | G31: =IFERROR(F31/D31,"") -> 1 | H31: 17326 | I31: 18850 | J31: =IF(H31=0,"",H31-I31) -> -1524 | K31: =IFERROR((H31-I31)/H31,"") -> -0.087960291 | L31: 33533 | M31: 17000 | N31: =IF(L31=0,"",L31-M31) -> 16533 | O31: =IFERROR((L31-M31)/L31,"") -> 0.49303671 | P31: =H31-L31 -> -16207 | Q31: =I31-M31 -> 1850
A32: =A30+7 -> 45781 | B32: 19 | C32: =IF(B32=0,"",B32/G$5) -> 0.86363636 | D32: 21661 | E32: =IFERROR(D32/B32,"") -> 1140.0526 | F32: 12106 | G32: =IFERROR(F32/D32,"") -> 0.55888463
A33: =A32+7 -> 45788 | B33: 19 | C33: =IF(B33=0,"",B33/G$5) -> 0.86363636 | D33: 21661 | E33: =IFERROR(D33/B33,"") -> 1140.0526 | F33: 17219 | G33: =IFERROR(F33/D33,"") -> 0.79493098
A34: =A33+7 -> 45795 | B34: 20 | C34: =IF(B34=0,"",B34/G$5) -> 0.90909091 | D34: 22436 | E34: =IFERROR(D34/B34,"") -> 1121.8 | F34: 18299 | G34: =IFERROR(F34/D34,"") -> 0.81560884
A35: =A34+7 -> 45802 | B35: 20 | C35: =IF(B35=0,"",B35/G$5) -> 0.90909091 | D35: 22436 | E35: =IFERROR(D35/B35,"") -> 1121.8 | F35: 18299 | G35: =IFERROR(F35/D35,"") -> 0.81560884
A36: Monthly Target | B36: 18 | C36: =IF(B36=0,"",B36/C$5) -> 0.94736842 | D36: 18850 | E36: =D36/B36 -> 1047.2222 | F36: 18850 | G36: =IFERROR(F36/D36,"") -> 1 | H36: 21451 | I36: 18850 | J36: =IF(H36=0,"",H36-I36) -> 2601 | K36: =IFERROR((H36-I36)/H36,"") -> 0.12125309 | L36: 13769 | M36: 17000 | N36: =IF(L36=0,"",L36-M36) -> -3231 | O36: =IFERROR((L36-M36)/L36,"") -> -0.23465756 | P36: =H36-L36 -> 7682 | Q36: =I36-M36 -> 1850 | R36: $11000 in building improvements on 1401 W Mulberry and N Maple Sidewalk
A37: =A35+7 -> 45809 | B37: 21 | C37: =IF(B37=0,"",B37/G$5) -> 0.95454545 | D37: 23191 | E37: =IFERROR(D37/B37,"") -> 1104.3333 | F37: 7790 | G37: =IFERROR(F37/D37,"") -> 0.33590617
A38: =A37+7 -> 45816 | B38: 20 | C38: =IF(B38=0,"",B38/G$5) -> 0.90909091 | D38: 21841 | E38: =IFERROR(D38/B38,"") -> 1092.05 | F38: 15335 | G38: =IFERROR(F38/D38,"") -> 0.70211987
A39: =A38+7 -> 45823 | B39: 20 | C39: =IF(B39=0,"",B39/G$5) -> 0.90909091 | D39: 21871 | E39: =IFERROR(D39/B39,"") -> 1093.55 | F39: 16335 | G39: =IFERROR(F39/D39,"") -> 0.74687943
A40: =A39+7 -> 45830 | B40: 20 | C40: =IF(B40=0,"",B40/G$5) -> 0.90909091 | D40: 21871 | E40: =IFERROR(D40/B40,"") -> 1093.55 | F40: 17535 | G40: =IFERROR(F40/D40,"") -> 0.80174661
A41: =A40+7 -> 45837 | B41: 20 | C41: =IF(B41=0,"",B41/G$5) -> 0.90909091 | D41: 21871 | E41: =IFERROR(D41/B41,"") -> 1093.55 | F41: 17535 | G41: =IFERROR(F41/D41,"") -> 0.80174661
A42: Monthly Target | B42: 18 | C42: =IF(B42=0,"",B42/C$5) -> 0.94736842 | D42: 18850 | E42: =D42/B42 -> 1047.2222 | F42: 18850 | G42: =IFERROR(F42/D42,"") -> 1 | H42: 20731 | I42: 18850 | J42: =IF(H42=0,"",H42-I42) -> 1881 | K42: =IFERROR((H42-I42)/H42,"") -> 0.090733684 | L42: 31373 | M42: 16000 | N42: =IF(L42=0,"",L42-M42) -> 15373 | O42: =IFERROR((L42-M42)/L42,"") -> 0.49000733 | P42: =H42-L42 -> -10642 | Q42: =I42-M42 -> 2850 | R42: New Roof on Chestnut and Ac 1215 ($10,000 in building improvements EXPENSED)
A43: =A41+7 -> 45844 | B43: 19 | C43: =IF(B43=0,"",B43/G$5) -> 0.86363636 | D43: 20691 | E43: =IFERROR(D43/B43,"") -> 1089 | F43: 15287 | G43: =IFERROR(F43/D43,"") -> 0.73882364
A44: =A43+7 -> 45851 | B44: 19 | C44: =IF(B44=0,"",B44/G$5) -> 0.86363636 | D44: 20711 | E44: =IFERROR(D44/B44,"") -> 1090.0526 | F44: 18662 | G44: =IFERROR(F44/D44,"") -> 0.90106707
A45: =A44+7 -> 45858 | B45: 19 | C45: =IF(B45=0,"",B45/G$5) -> 0.86363636 | D45: 20711 | E45: =IFERROR(D45/B45,"") -> 1090.0526 | F45: 20162 | G45: =IFERROR(F45/D45,"") -> 0.97349235
A46: =A45+7 -> 45865 | B46: 19 | C46: =IF(B46=0,"",B46/G$5) -> 0.86363636 | D46: 20711 | E46: =IFERROR(D46/B46,"") -> 1090.0526 | F46: 21584 | G46: =IFERROR(F46/D46,"") -> 1.0421515
A47: Monthly Target | B47: 18 | C47: =IF(B47=0,"",B47/C$5) -> 0.94736842 | D47: 18850 | E47: =D47/B47 -> 1047.2222 | F47: 18850 | G47: =IFERROR(F47/D47,"") -> 1 | H47: 22041 | I47: 18850 | J47: =IF(H47=0,"",H47-I47) -> 3191 | K47: =IFERROR((H47-I47)/H47,"") -> 0.14477565 | L47: 34957 | M47: 16000 | N47: =IF(L47=0,"",L47-M47) -> 18957 | O47: =IFERROR((L47-M47)/L47,"") -> 0.54229482 | P47: =H47-L47 -> -12916 | Q47: =I47-M47 -> 2850 | R47: Fuller & 1101 Unit Turns
A48: =A46+7 -> 45872 | B48: 20 | C48: =IF(B48=0,"",B48/G$5) -> 0.90909091 | D48: 21591 | E48: =IFERROR(D48/B48,"") -> 1079.55 | F48: 13581 | G48: =IFERROR(F48/D48,"") -> 0.62901209
A49: =A48+7 -> 45879 | B49: 20 | C49: =IF(B49=0,"",B49/G$5) -> 0.90909091 | D49: 21591 | E49: =IFERROR(D49/B49,"") -> 1079.55 | F49: 16808 | G49: =IFERROR(F49/D49,"") -> 0.77847251
A50: =A49+7 -> 45886 | B50: 20 | C50: =IF(B50=0,"",B50/G$5) -> 0.90909091 | D50: 21591 | E50: =IFERROR(D50/B50,"") -> 1079.55 | F50: 18008 | G50: =IFERROR(F50/D50,"") -> 0.83405122
A51: =A50+7 -> 45893 | B51: 20 | C51: =IF(B51=0,"",B51/G$5) -> 0.90909091 | D51: 21591 | E51: =IFERROR(D51/B51,"") -> 1079.55 | F51: 18467 | G51: =IFERROR(F51/D51,"") -> 0.85531008
A52: =A51+7 -> 45900 | B52: 21 | C52: =IF(B52=0,"",B52/G$5) -> 0.95454545 | D52: 23041 | E52: =IFERROR(D52/B52,"") -> 1097.1905 | F52: 19028 | G52: =IFERROR(F52/D52,"") -> 0.82583221
A53: Monthly Target | B53: 18 | C53: =IF(B53=0,"",B53/C$5) -> 0.94736842 | D53: 18850 | E53: =D53/B53 -> 1047.2222 | F53: 18850 | G53: =IFERROR(F53/D53,"") -> 1 | H53: 22028 | I53: 18850 | J53: =IF(H53=0,"",H53-I53) -> 3178 | K53: =IFERROR((H53-I53)/H53,"") -> 0.14427093 | L53: 26067 | M53: 16000 | N53: =IF(L53=0,"",L53-M53) -> 10067 | O53: =IFERROR((L53-M53)/L53,"") -> 0.38619711 | P53: =H53-L53 -> -4039 | Q53: =I53-M53 -> 2850 | R53: Plus $3,600 in Building Improvements (Heavy Unit Turns)
A54: =A52+7 -> 45907 | B54: 19 | C54: =IF(B54=0,"",B54/G$5) -> 0.86363636 | D54: 21175 | E54: =IFERROR(D54/B54,"") -> 1114.4737 | F54: 19624 | G54: =IFERROR(F54/D54,"") -> 0.92675325
A55: =A54+7 -> 45914 | B55: 19 | C55: =IF(B55=0,"",B55/G$5) -> 0.86363636 | D55: 21175 | E55: =IFERROR(D55/B55,"") -> 1114.4737 | F55: 20824 | G55: =IFERROR(F55/D55,"") -> 0.98342385
A56: =A55+7 -> 45921 | B56: 20 | C56: =IF(B56=0,"",B56/G$5) -> 0.90909091 | D56: 22725 | E56: =IFERROR(D56/B56,"") -> 1136.25 | F56: 21187 | G56: =IFERROR(F56/D56,"") -> 0.93232123
A57: =A56+7 -> 45928 | B57: 21 | C57: =IF(B57=0,"",B57/G$5) -> 0.95454545 | D57: 22700 | E57: =IFERROR(D57/B57,"") -> 1080.9524 | F57: 21797 | G57: =IFERROR(F57/D57,"") -> 0.96022026
A58: Monthly Target | B58: 18 | C58: =IF(B58=0,"",B58/C$5) -> 0.94736842 | D58: 18850 | E58: =D58/B58 -> 1047.2222 | F58: 18850 | G58: =IFERROR(F58/D58,"") -> 1 | H58: 25933 | I58: 18850 | J58: =IF(H58=0,"",H58-I58) -> 7083 | K58: =IFERROR((H58-I58)/H58,"") -> 0.2731269 | L58: 37678 | M58: 16000 | N58: =IF(L58=0,"",L58-M58) -> 21678 | O58: =IFERROR((L58-M58)/L58,"") -> 0.57534901 | P58: =H58-L58 -> -11745 | Q58: =I58-M58 -> 2850 | R58: 16k in unit turn expenses mostly 720 Hubert
A59: =A57+7 -> 45935 | B59: 18 | C59: =IF(B59=0,"",B59/G$5) -> 0.81818182 | D59: 21675 | E59: =IFERROR(D59/B59,"") -> 1204.1667 | F59: 17869 | G59: =IFERROR(F59/D59,"") -> 0.824406
A60: =A59+7 -> 45942 | B60: 20 | C60: =IF(B60=0,"",B60/G$5) -> 0.90909091 | D60: 22525 | E60: =IFERROR(D60/B60,"") -> 1126.25 | F60: 21644 | G60: =IFERROR(F60/D60,"") -> 0.9608879
A61: =A60+7 -> 45949 | B61: 20 | C61: =IF(B61=0,"",B61/G$5) -> 0.90909091 | D61: 22525 | E61: =IFERROR(D61/B61,"") -> 1126.25 | F61: 23497 | G61: =IFERROR(F61/D61,"") -> 1.0431521
A62: =A61+7 -> 45956 | B62: 20 | C62: =IF(B62=0,"",B62/G$5) -> 0.90909091 | D62: 22525 | E62: =IFERROR(D62/B62,"") -> 1126.25 | F62: 24697 | G62: =IFERROR(F62/D62,"") -> 1.0964262
A63: Monthly Target | B63: 18 | C63: =IF(B63=0,"",B63/C$5) -> 0.94736842 | D63: 18850 | E63: =D63/B63 -> 1047.2222 | F63: 18850 | G63: =IFERROR(F63/D63,"") -> 1 | H63: 26876 | I63: 18850 | J63: =IF(H63=0,"",H63-I63) -> 8026 | K63: =IFERROR((H63-I63)/H63,"") -> 0.29863075 | L63: 35025 | M63: 16000 | N63: =IF(L63=0,"",L63-M63) -> 19025 | O63: =IFERROR((L63-M63)/L63,"") -> 0.54318344 | P63: =H63-L63 -> -8149 | Q63: =I63-M63 -> 2850 | R63: 10k unit turn expenses
A64: =A62+7 -> 45963 | B64: 21 | C64: =IF(B64=0,"",B64/G$5) -> 0.95454545 | D64: 24025 | E64: =IFERROR(D64/B64,"") -> 1144.0476 | F64: 12727 | G64: =IFERROR(F64/D64,"") -> 0.52973985
A65: =A64+7 -> 45970 | B65: 22 | C65: =IF(B65=0,"",B65/G$5) -> 1 | D65: 25225 | E65: =IFERROR(D65/B65,"") -> 1146.5909 | F65: 24792 | G65: =IFERROR(F65/D65,"") -> 0.98283449
A66: =A65+7 -> 45977 | B66: 22 | C66: =IF(B66=0,"",B66/G$5) -> 1 | D66: 25225 | E66: =IFERROR(D66/B66,"") -> 1146.5909 | F66: 25380 | G66: =IFERROR(F66/D66,"") -> 1.0061447
A67: =A66+7 -> 45984 | B67: 22 | C67: =IF(B67=0,"",B67/G$5) -> 1 | D67: 25225 | E67: =IFERROR(D67/B67,"") -> 1146.5909 | F67: 25380 | G67: =IFERROR(F67/D67,"") -> 1.0061447
A68: =A67+7 -> 45991 | B68: 22 | C68: =IF(B68=0,"",B68/G$5) -> 1 | D68: 25225 | E68: =IFERROR(D68/B68,"") -> 1146.5909 | F68: 25380 | G68: =IFERROR(F68/D68,"") -> 1.0061447
A69: Monthly Target | B69: 18 | C69: =IF(B69=0,"",B69/C$5) -> 0.94736842 | D69: 18850 | E69: =D69/B69 -> 1047.2222 | F69: 18850 | G69: =IFERROR(F69/D69,"") -> 1 | I69: 18850 | J69: =IF(H69=0,"",H69-I69) | K69: =IFERROR((H69-I69)/H69,"") | M69: 16000 | N69: =IF(L69=0,"",L69-M69) | O69: =IFERROR((L69-M69)/L69,"") | P69: =H69-L69 -> 0 | Q69: =I69-M69 -> 2850
A70: =A68+7 -> 45998 | B70: 22 | C70: =IF(B70=0,"",B70/G$5) -> 1 | D70: 25225 | E70: =IFERROR(D70/B70,"") -> 1146.5909 | F70: 22401 | G70: =IFERROR(F70/D70,"") -> 0.88804757
A71: =A70+7 -> 46005 | B71: 22 | C71: =IF(B71=0,"",B71/G$5) -> 1 | D71: 25225 | E71: =IFERROR(D71/B71,"") -> 1146.5909 | F71: 23544 | G71: =IFERROR(F71/D71,"") -> 0.93335976
A72: =A71+7 -> 46012 | C72: =IF(B72=0,"",B72/G$5) | E72: =IFERROR(D72/B72,"") | G72: =IFERROR(F72/D72,"")
A73: =A72+7 -> 46019 | C73: =IF(B73=0,"",B73/G$5) | E73: =IFERROR(D73/B73,"") | G73: =IFERROR(F73/D73,"")
A74: Monthly Target | B74: 18 | C74: =IF(B74=0,"",B74/C$5) -> 0.94736842 | D74: 18850 | E74: =D74/B74 -> 1047.2222 | F74: 18850 | G74: =IFERROR(F74/D74,"") -> 1 | I74: 18850 | J74: =IF(H74=0,"",H74-I74) | K74: =IFERROR((H74-I74)/H74,"") | M74: 16000 | N74: =IF(L74=0,"",L74-M74) | O74: =IFERROR((L74-M74)/L74,"") | P74: =H74-L74 -> 0 | Q74: =I74-M74 -> 2850
A75: Annual Total | C75: =IF(B75=0,"",B75/C$5) | E75: =IFERROR(D75/B75,"") | G75: =IFERROR(F75/D75,"") | H75: =H15+H20+H26+H31+H36+H42+H47+H53+H58+H63+H69+H74 -> 216575 | I75: =I15+I20+I26+I31+I36+I42+I47+I53+I58+I63+I69+I74 -> 226200 | J75: =IF(H75=0,"",H75-I75) -> -9625 | K75: =IFERROR((H75-I75)/H75,"") -> -0.044441879 | L75: =L15+L20+L26+L31+L36+L42+L47+L53+L58+L63+L69+L74 -> 284432 | M75: =M15+M20+M26+M31+M36+M42+M47+M53+M58+M63+M69+M74 -> 197000 | N75: =IF(L75=0,"",L75-M75) -> 87432 | O75: =IFERROR((L75-M75)/L75,"") -> 0.30739157 | P75: =sum(P15,P20,P26,P31,P36,P42,P47,P53,P58,P63,P69,P74) -> -67857 | Q75: =I75-M75 -> 29200
A76: ** | B76: ** | C76: ** | D76: ** | E76: ** | F76: ** | G76: ** | H76: ** | I76: ** | J76: ** | K76: ** | L76: ** | M76: ** | N76: ** | O76: ** | R76: **

Sheet RD Sidney
A1: KEY
A2: Manual Input
A3: Owner Input or Formula
A4: Formula | B4: RD Sidney
B5: # of Units | C5: 8 | I5: KPI Tracker
A10: Week Ending Sunday | B10: # of Occupied Units | C10: Occupancy % | D10: Total Leased Rent Amount $ | E10: Average Rent | F10: Total Collections to Date $ | G10: Collection Percentage | H10: Actual Revenue (Monthly Only) | I10: Budgeted Revenue (Monthly Only) | J10: Variance $ | K10: Variance % | L10: Actual Expense (Monthly Only) | M10: Budgeted Expense (Monthly Only | N10: Variance $ | O10: Variance % | P10: Net Income | Q10: Net Income Budgeted | R10: Total Expenses
A11: 45662 | B11: 8 | C11: =IF(B11=0,"",B11/C$5) -> 1 | D11: 6600 | E11: =IFERROR(D11/B11,"") -> 825 | F11: 4700 | G11: =IFERROR(F11/D11,"") -> 0.71212121 | R11: 431 N Miami, 509 S Miami, 824 Spruce
A12: =A11+7 -> 45669 | B12: 8 | C12: =IF(B12=0,"",B12/C$5) -> 1 | D12: 6600 | E12: =IFERROR(D12/B12,"") -> 825 | F12: 4700 | G12: =IFERROR(F12/D12,"") -> 0.71212121 | R12: https://bhhsprofessionalrealty.managebuilding.com/manager/app/accounting/rental-owner-financials MIAMI
A13: =A12+7 -> 45676 | B13: 8 | C13: =IF(B13=0,"",B13/C$5) -> 1 | D13: 6600 | E13: =IFERROR(D13/B13,"") -> 825 | F13: 4999 | G13: =IFERROR(F13/D13,"") -> 0.75742424 | R13: https://bhhsprofessionalrealty.managebuilding.com/manager/app/reports/list S Miami & Spruce
A14: =A13+7 -> 45683 | B14: 8 | C14: =IF(B14=0,"",B14/C$5) -> 1 | D14: 6600 | E14: =IFERROR(D14/B14,"") -> 825 | F14: 5698 | G14: =IFERROR(F14/D14,"") -> 0.86333333
A15: Monthly Target | B15: 7 | C15: =IF(B15=0,"",B15/C$5) -> 0.875 | D15: 6072 | E15: =D15/B15 -> 867.42857 | F15: 6072 | G15: =IFERROR(F15/D15,"") -> 1 | H15: 6450 | I15: 6072 | J15: =IF(H15=0,"",H15-I15) -> 378 | K15: =IFERROR((H15-I15)/H15,"") -> 0.058604651 | L15: 3793 | M15: 3500 | N15: =IF(L15=0,"",L15-M15) -> 293 | O15: =IFERROR((L15-M15)/L15,"") -> 0.077247561 | P15: =H15-L15 -> 2657 | Q15: =I15-M15 -> 2572
A16: =A14+7 -> 45690 | B16: 8 | C16: =IF(B16=0,"",B16/C$5) -> 1 | D16: 6600 | E16: =IFERROR(D16/B16,"") -> 825 | F16: 1700 | G16: =IFERROR(F16/D16,"") -> 0.25757576
A17: =A16+7 -> 45697 | B17: 8 | C17: =IF(B17=0,"",B17/C$5) -> 1 | D17: 6600 | E17: =IFERROR(D17/B17,"") -> 825 | F17: 4000 | G17: =IFERROR(F17/D17,"") -> 0.60606061
A18: =A17+7 -> 45704 | B18: 8 | C18: =IF(B18=0,"",B18/C$5) -> 1 | D18: 6600 | E18: =IFERROR(D18/B18,"") -> 825 | F18: 4750 | G18: =IFERROR(F18/D18,"") -> 0.71969697
A19: =A18+7 -> 45711 | B19: 8 | C19: =IF(B19=0,"",B19/C$5) -> 1 | D19: 6600 | E19: =IFERROR(D19/B19,"") -> 825 | F19: 5916 | G19: =IFERROR(F19/D19,"") -> 0.89636364
A20: Monthly Target | B20: 7 | C20: =IF(B20=0,"",B20/C$5) -> 0.875 | D20: 6072 | E20: =D20/B20 -> 867.42857 | F20: 6072 | G20: =IFERROR(F20/D20,"") -> 1 | H20: 8966 | I20: 6072 | J20: =IF(H20=0,"",H20-I20) -> 2894 | K20: =IFERROR((H20-I20)/H20,"") -> 0.32277493 | L20: 2504 | M20: 3500 | N20: =IF(L20=0,"",L20-M20) -> -996 | O20: =IFERROR((L20-M20)/L20,"") -> -0.39776358 | P20: =H20-L20 -> 6462 | Q20: =I20-M20 -> 2572
A21: =A19+7 -> 45718 | B21: 8 | C21: =IF(B21=0,"",B21/C$5) -> 1 | D21: 6600 | E21: =IFERROR(D21/B21,"") -> 825 | F21: 1700 | G21: =IFERROR(F21/D21,"") -> 0.25757576
A22: =A21+7 -> 45725 | B22: 8 | C22: =IF(B22=0,"",B22/C$5) -> 1 | D22: 6600 | E22: =IFERROR(D22/B22,"") -> 825 | F22: 1700 | G22: =IFERROR(F22/D22,"") -> 0.25757576
A23: =A22+7 -> 45732 | B23: 8 | C23: =IF(B23=0,"",B23/C$5) -> 1 | D23: 6600 | E23: =IFERROR(D23/B23,"") -> 825 | F23: 3750 | G23: =IFERROR(F23/D23,"") -> 0.56818182
A24: =A23+7 -> 45739 | B24: 8 | C24: =IF(B24=0,"",B24/C$5) -> 1 | D24: 6600 | E24: =IFERROR(D24/B24,"") -> 825 | F24: 5700 | G24: =IFERROR(F24/D24,"") -> 0.86363636
A25: =A24+7 -> 45746 | B25: 8 | C25: =IF(B25=0,"",B25/C$5) -> 1 | D25: 6600 | E25: =IFERROR(D25/B25,"") -> 825 | F25: 6800 | G25: =IFERROR(F25/D25,"") -> 1.030303
A26: Monthly Target | B26: 7 | C26: =IF(B26=0,"",B26/C$5) -> 0.875 | D26: 6072 | E26: =D26/B26 -> 867.42857 | F26: 6072 | G26: =IFERROR(F26/D26,"") -> 1 | H26: 6709 | I26: 6072 | J26: =IF(H26=0,"",H26-I26) -> 637 | K26: =IFERROR((H26-I26)/H26,"") -> 0.094947086 | L26: 4283 | M26: 3500 | N26: =IF(L26=0,"",L26-M26) -> 783 | O26: =IFERROR((L26-M26)/L26,"") -> 0.18281578 | P26: =H26-L26 -> 2426 | Q26: =I26-M26 -> 2572
A27: =A25+7 -> 45753 | B27: 8 | C27: =IF(B27=0,"",B27/C$5) -> 1 | D27: 6600 | E27: =IFERROR(D27/B27,"") -> 825 | F27: 1608 | G27: =IFERROR(F27/D27,"") -> 0.24363636
A28: =A27+7 -> 45760 | B28: 8 | C28: =IF(B28=0,"",B28/C$5) -> 1 | D28: 6600 | E28: =IFERROR(D28/B28,"") -> 825 | F28: 3333 | G28: =IFERROR(F28/D28,"") -> 0.505
A29: =A28+7 -> 45767 | B29: 8 | C29: =IF(B29=0,"",B29/C$5) -> 1 | D29: 6600 | E29: =IFERROR(D29/B29,"") -> 825 | F29: 3883 | G29: =IFERROR(F29/D29,"") -> 0.58833333
A30: =A29+7 -> 45774 | B30: 8 | C30: =IF(B30=0,"",B30/C$5) -> 1 | D30: 6600 | E30: =IFERROR(D30/B30,"") -> 825 | F30: 3883 | G30: =IFERROR(F30/D30,"") -> 0.58833333
A31: Monthly Target | B31: 7 | C31: =IF(B31=0,"",B31/C$5) -> 0.875 | D31: 6072 | E31: =D31/B31 -> 867.42857 | F31: 6072 | G31: =IFERROR(F31/D31,"") -> 1 | H31: 3883 | I31: 6072 | J31: =IF(H31=0,"",H31-I31) -> -2189 | K31: =IFERROR((H31-I31)/H31,"") -> -0.56373938 | L31: 3750 | M31: 3500 | N31: =IF(L31=0,"",L31-M31) -> 250 | O31: =IFERROR((L31-M31)/L31,"") -> 0.066666667 | P31: =H31-L31 -> 133 | Q31: =I31-M31 -> 2572
A32: =A30+7 -> 45781 | B32: 8 | C32: =IF(B32=0,"",B32/C$5) -> 1 | D32: 6600 | E32: =IFERROR(D32/B32,"") -> 825 | F32: 1300 | G32: =IFERROR(F32/D32,"") -> 0.1969697
A33: =A32+7 -> 45788 | B33: 8 | C33: =IF(B33=0,"",B33/C$5) -> 1 | D33: 6600 | E33: =IFERROR(D33/B33,"") -> 825 | F33: 1625 | G33: =IFERROR(F33/D33,"") -> 0.24621212
A34: =A33+7 -> 45795 | B34: 8 | C34: =IF(B34=0,"",B34/C$5) -> 1 | D34: 6600 | E34: =IFERROR(D34/B34,"") -> 825 | F34: 2125 | G34: =IFERROR(F34/D34,"") -> 0.3219697
A35: =A34+7 -> 45802 | B35: 8 | C35: =IF(B35=0,"",B35/C$5) -> 1 | D35: 6600 | E35: =IFERROR(D35/B35,"") -> 825 | F35: 2675 | G35: =IFERROR(F35/D35,"") -> 0.40530303
A36: Monthly Target | B36: 7 | C36: =IF(B36=0,"",B36/C$5) -> 0.875 | D36: 6072 | E36: =D36/B36 -> 867.42857 | F36: 6072 | G36: =IFERROR(F36/D36,"") -> 1 | H36: 5525 | I36: 6072 | J36: =IF(H36=0,"",H36-I36) -> -547 | K36: =IFERROR((H36-I36)/H36,"") -> -0.099004525 | L36: 4065 | M36: 3500 | N36: =IF(L36=0,"",L36-M36) -> 565 | O36: =IFERROR((L36-M36)/L36,"") -> 0.13899139 | P36: =H36-L36 -> 1460 | Q36: =I36-M36 -> 2572
A37: =A35+7 -> 45809 | B37: 8 | C37: =IF(B37=0,"",B37/C$5) -> 1 | D37: 6600 | E37: =IFERROR(D37/B37,"") -> 825 | F37: 0 | G37: =IFERROR(F37/D37,"") -> 0
A38: =A37+7 -> 45816 | B38: 8 | C38: =IF(B38=0,"",B38/C$5) -> 1 | D38: 6600 | E38: =IFERROR(D38/B38,"") -> 825 | F38: 1050 | G38: =IFERROR(F38/D38,"") -> 0.15909091
A39: =A38+7 -> 45823 | B39: 8 | C39: =IF(B39=0,"",B39/C$5) -> 1 | D39: 6600 | E39: =IFERROR(D39/B39,"") -> 825 | F39: 1050 | G39: =IFERROR(F39/D39,"") -> 0.15909091
A40: =A39+7 -> 45830 | B40: 8 | C40: =IF(B40=0,"",B40/C$5) -> 1 | D40: 6600 | E40: =IFERROR(D40/B40,"") -> 825 | F40: 3525 | G40: =IFERROR(F40/D40,"") -> 0.53409091
A41: =A40+7 -> 45837 | B41: 8 | C41: =IF(B41=0,"",B41/C$5) -> 1 | D41: 6600 | E41: =IFERROR(D41/B41,"") -> 825 | F41: 4525 | G41: =IFERROR(F41/D41,"") -> 0.68560606
A42: Monthly Target | B42: 7 | C42: =IF(B42=0,"",B42/C$5) -> 0.875 | D42: 6072 | E42: =D42/B42 -> 867.42857 | F42: 6072 | G42: =IFERROR(F42/D42,"") -> 1 | H42: 4375 | I42: 6072 | J42: =IF(H42=0,"",H42-I42) -> -1697 | K42: =IFERROR((H42-I42)/H42,"") -> -0.38788571 | L42: 4500 | M42: 3500 | N42: =IF(L42=0,"",L42-M42) -> 1000 | O42: =IFERROR((L42-M42)/L42,"") -> 0.22222222 | P42: =H42-L42 -> -125 | Q42: =I42-M42 -> 2572
A43: =A41+7 -> 45844 | B43: 8 | C43: =IF(B43=0,"",B43/C$5) -> 1 | D43: 6600 | E43: =IFERROR(D43/B43,"") -> 825 | F43: 0 | G43: =IFERROR(F43/D43,"") -> 0
A44: =A43+7 -> 45851 | B44: 8 | C44: =IF(B44=0,"",B44/C$5) -> 1 | D44: 6600 | E44: =IFERROR(D44/B44,"") -> 825 | F44: 0 | G44: =IFERROR(F44/D44,"") -> 0
A45: =A44+7 -> 45858 | B45: 8 | C45: =IF(B45=0,"",B45/C$5) -> 1 | D45: 6600 | E45: =IFERROR(D45/B45,"") -> 825 | F45: 1825 | G45: =IFERROR(F45/D45,"") -> 0.27651515
A46: =A45+7 -> 45865 | B46: 8 | C46: =IF(B46=0,"",B46/C$5) -> 1 | D46: 6600 | E46: =IFERROR(D46/B46,"") -> 825 | F46: 1825 | G46: =IFERROR(F46/D46,"") -> 0.27651515
A47: =A46+7 -> 45872 | B47: 8 | C47: =IF(B47=0,"",B47/C$5) -> 1 | D47: 6600 | E47: =IFERROR(D47/B47,"") -> 825 | F47: 1825 | G47: =IFERROR(F47/D47,"") -> 0.27651515
A48: Monthly Target | B48: 7 | C48: =IF(B48=0,"",B48/C$5) -> 0.875 | D48: 6072 | E48: =D48/B48 -> 867.42857 | F48: 6072 | G48: =IFERROR(F48/D48,"") -> 1 | I48: 6072 | J48: =IF(H48=0,"",H48-I48) | K48: =IFERROR((H48-I48)/H48,"") | M48: 3500 | N48: =IF(L48=0,"",L48-M48) | O48: =IFERROR((L48-M48)/L48,"") | P48: =H48-L48 -> 0 | Q48: =I48-M48 -> 2572
A49: =A47+7 -> 45879 | C49: =IF(B49=0,"",B49/C$5) | E49: =IFERROR(D49/B49,"") | G49: =IFERROR(F49/D49,"")
A50: =A49+7 -> 45886 | C50: =IF(B50=0,"",B50/C$5) | E50: =IFERROR(D50/B50,"") | G50: =IFERROR(F50/D50,"")
A51: =A50+7 -> 45893 | C51: =IF(B51=0,"",B51/C$5) | E51: =IFERROR(D51/B51,"") | G51: =IFERROR(F51/D51,"")
A52: =A51+7 -> 45900 | C52: =IF(B52=0,"",B52/C$5) | E52: =IFERROR(D52/B52,"") | G52: =IFERROR(F52/D52,"")
A53: Monthly Target | B53: 7 | C53: =IF(B53=0,"",B53/C$5) -> 0.875 | D53: 6072 | E53: =D53/B53 -> 867.42857 | F53: 6072 | G53: =IFERROR(F53/D53,"") -> 1 | I53: 6072 | J53: =IF(H53=0,"",H53-I53) | K53: =IFERROR((H53-I53)/H53,"") | M53: 3500 | N53: =IF(L53=0,"",L53-M53) | O53: =IFERROR((L53-M53)/L53,"") | P53: =H53-L53 -> 0 | Q53: =I53-M53 -> 2572
A54: =A52+7 -> 45907 | C54: =IF(B54=0,"",B54/C$5) | E54: =IFERROR(D54/B54,"") | G54: =IFERROR(F54/D54,"")
A55: =A54+7 -> 45914 | C55: =IF(B55=0,"",B55/C$5) | E55: =IFERROR(D55/B55,"") | G55: =IFERROR(F55/D55,"")
A56: =A55+7 -> 45921 | C56: =IF(B56=0,"",B56/C$5) | E56: =IFERROR(D56/B56,"") | G56: =IFERROR(F56/D56,"")
A57: =A56+7 -> 45928 | C57: =IF(B57=0,"",B57/C$5) | G57: =IFERROR(F57/D57,"")
A58: Monthly Target | B58: 7 | C58: =IF(B58=0,"",B58/C$5) -> 0.875 | D58: 6072 | E58: =D58/B58 -> 867.42857 | F58: 6072 | G58: =IFERROR(F58/D58,"") -> 1 | I58: 6072 | J58: =IF(H58=0,"",H58-I58) | K58: =IFERROR((H58-I58)/H58,"") | M58: 3500 | N58: =IF(L58=0,"",L58-M58) | O58: =IFERROR((L58-M58)/L58,"") | P58: =H58-L58 -> 0 | Q58: =I58-M58 -> 2572
A59: =A57+7 -> 45935 | C59: =IF(B59=0,"",B59/C$5) | E59: =IFERROR(D59/B59,"") | G59: =IFERROR(F59/D59,"")
A60: =A59+7 -> 45942 | C60: =IF(B60=0,"",B60/C$5) | E60: =IFERROR(D60/B60,"") | G60: =IFERROR(F60/D60,"")
A61: =A60+7 -> 45949 | C61: =IF(B61=0,"",B61/C$5) | E61: =IFERROR(D61/B61,"") | G61: =IFERROR(F61/D61,"")
A62: =A61+7 -> 45956 | C62: =IF(B62=0,"",B62/C$5) | E62: =IFERROR(D62/B62,"") | G62: =IFERROR(F62/D62,"")
A63: =A62+7 -> 45963 | C63: =IF(B63=0,"",B63/C$5) | E63: =IFERROR(D63/B63,"") | G63: =IFERROR(F63/D63,"")
A64: Monthly Target | B64: 7 | C64: =IF(B64=0,"",B64/C$5) -> 0.875 | D64: 6072 | E64: =D64/B64 -> 867.42857 | F64: 6072 | G64: =IFERROR(F64/D64,"") -> 1 | I64: 6072 | J64: =IF(H64=0,"",H64-I64) | K64: =IFERROR((H64-I64)/H64,"") | M64: 3500 | N64: =IF(L64=0,"",L64-M64) | O64: =IFERROR((L64-M64)/L64,"") | P64: =H64-L64 -> 0 | Q64: =I64-M64 -> 2572
A65: =A63+7 -> 45970 | C65: =IF(B65=0,"",B65/C$5) | E65: =IFERROR(D65/B65,"") | G65: =IFERROR(F65/D65,"")
A66: =A65+7 -> 45977 | C66: =IF(B66=0,"",B66/C$5) | E66: =IFERROR(D66/B66,"") | G66: =IFERROR(F66/D66,"")
A67: =A66+7 -> 45984 | C67: =IF(B67=0,"",B67/C$5) | E67: =IFERROR(D67/B67,"") | G67: =IFERROR(F67/D67,"")
A68: =A67+7 -> 45991 | C68: =IF(B68=0,"",B68/C$5) | E68: =IFERROR(D68/B68,"") | G68: =IFERROR(F68/D68,"")
A69: Monthly Target | B69: 7 | C69: =IF(B69=0,"",B69/C$5) -> 0.875 | D69: 6072 | E69: =D69/B69 -> 867.42857 | F69: 6072 | G69: =IFERROR(F69/D69,"") -> 1 | I69: 6072 | J69: =IF(H69=0,"",H69-I69) | K69: =IFERROR((H69-I69)/H69,"") | M69: 3500 | N69: =IF(L69=0,"",L69-M69) | O69: =IFERROR((L69-M69)/L69,"") | P69: =H69-L69 -> 0 | Q69: =I69-M69 -> 2572
A70: =A68+7 -> 45998 | C70: =IF(B70=0,"",B70/C$5) | E70: =IFERROR(D70/B70,"") | G70: =IFERROR(F70/D70,"")
A71: =A70+7 -> 46005 | C71: =IF(B71=0,"",B71/C$5) | E71: =IFERROR(D71/B71,"") | G71: =IFERROR(F71/D71,"")
A72: =A71+7 -> 46012 | C72: =IF(B72=0,"",B72/C$5) | E72: =IFERROR(D72/B72,"") | G72: =IFERROR(F72/D72,"")
A73: =A72+7 -> 46019 | C73: =IF(B73=0,"",B73/C$5) | E73: =IFERROR(D73/B73,"") | G73: =IFERROR(F73/D73,"")
A74: Monthly Target | B74: 7 | C74: =IF(B74=0,"",B74/C$5) -> 0.875 | D74: 6072 | E74: =D74/B74 -> 867.42857 | F74: 6072 | G74: =IFERROR(F74/D74,"") -> 1 | I74: 6072 | J74: =IF(H74=0,"",H74-I74) | K74: =IFERROR((H74-I74)/H74,"") | M74: 3500 | N74: =IF(L74=0,"",L74-M74) | O74: =IFERROR((L74-M74)/L74,"") | P74: =H74-L74 -> 0 | Q74: =I74-M74 -> 2572
A75: Annual Total | C75: =IF(B75=0,"",B75/C$5) | E75: =IFERROR(D75/B75,"") | G75: =IFERROR(F75/D75,"") | H75: =H15+H20+H26+H31+H36+H42+H48+H53+H58+H64+H69+H74 -> 35908 | I75: =I15+I20+I26+I31+I36+I42+I48+I53+I58+I64+I69+I74 -> 72864 | J75: =IF(H75=0,"",H75-I75) -> -36956 | K75: =IFERROR((H75-I75)/H75,"") -> -1.0291857 | L75: =L15+L20+L26+L31+L36+L42+L48+L53+L58+L64+L69+L74 -> 22895 | M75: =M15+M20+M26+M31+M36+M42+M48+M53+M58+M64+M69+M74 -> 42000 | N75: =IF(L75=0,"",L75-M75) -> -19105 | O75: =IFERROR((L75-M75)/L75,"") -> -0.83446167 | P75: =P15+P20+P26+P31+P36+P42+P48+P53+P58+P64+P69+P74 -> 13013 | Q75: =Q15+Q20+Q26+Q31+Q36+Q42+Q48+Q53+Q58+Q64+Q69+Q74 -> 30864
A76: ** | B76: ** | C76: ** | D76: ** | E76: ** | F76: ** | G76: ** | H76: ** | I76: ** | J76: ** | K76: ** | L76: ** | M76: ** | N76: ** | O76: ** | P76: ** | Q76: ** | R76: **

Sheet New Lex MHP
A1: KEY
A2: Manual Input
A3: Owner Input or Formula
A4: Formula | B4: New Lex MHP
B5: # of Units | C5: 22 | I5: KPI Tracker
A10: Week Ending Sunday | B10: # of Occupied Units | C10: Occupancy % | D10: Total Leased Rent Amount $ | E10: Average Rent | F10: Total Collections to Date $ | G10: Collection Percentage | H10: Actual Revenue (Monthly Only) | I10: Budgeted Revenue (Monthly Only) | J10: Variance $ | K10: Variance % | L10: Actual Expense (Monthly Only) | M10: Budgeted Expense (Monthly Only | N10: Variance $ | O10: Variance % | P10: Net Income | Q10: Net Income Projected | R10: Total Expenses
A11: 45662 | B11: 19 | C11: =IF(B11=0,"",B11/C$5) -> 0.86363636 | D11: 8380.22 | E11: =IFERROR(D11/B11,"") -> 441.06421 | F11: 3425 | G11: =IFERROR(F11/D11,"") -> 0.40870049 | R11: 308 W Broadway Street, New Lexington Ohio (21 Real Pads)
A12: =A11+7 -> 45669 | B12: 19 | C12: =IF(B12=0,"",B12/C$5) -> 0.86363636 | D12: 8130 | E12: =IFERROR(D12/B12,"") -> 427.89474 | F12: 3925 | G12: =IFERROR(F12/D12,"") -> 0.48277983
A13: =A12+7 -> 45676 | B13: 19 | C13: =IF(B13=0,"",B13/C$5) -> 0.86363636 | D13: 8130 | E13: =IFERROR(D13/B13,"") -> 427.89474 | F13: 4238 | G13: =IFERROR(F13/D13,"") -> 0.52127921
A14: =A13+7 -> 45683 | B14: 19 | C14: =IF(B14=0,"",B14/C$5) -> 0.86363636 | D14: 8130 | E14: =IFERROR(D14/B14,"") -> 427.89474 | F14: 5084 | G14: =IFERROR(F14/D14,"") -> 0.62533825
A15: Monthly Target | B15: 20 | C15: =IF(B15=0,"",B15/C$5) -> 0.90909091 | D15: 8000 | E15: =D15/B15 -> 400 | F15: 8000 | G15: =IFERROR(F15/D15,"") -> 1 | H15: 5959 | I15: 8000 | J15: =IF(H15=0,"",H15-I15) -> -2041 | K15: =IFERROR((H15-I15)/H15,"") -> -0.34250713 | L15: 3181 | M15: 5000 | N15: =IF(L15=0,"",L15-M15) -> -1819 | O15: =IFERROR((L15-M15)/L15,"") -> -0.57183276 | P15: =H15-L15 -> 2778 | Q15: =I15-M15 -> 3000
A16: =A14+7 -> 45690 | B16: 19 | C16: =IF(B16=0,"",B16/C$5) -> 0.86363636 | D16: 8130 | E16: =IFERROR(D16/B16,"") -> 427.89474 | F16: 1850 | G16: =IFERROR(F16/D16,"") -> 0.22755228
A17: =A16+7 -> 45697 | B17: 19 | C17: =IF(B17=0,"",B17/C$5) -> 0.86363636 | D17: 8130 | E17: =IFERROR(D17/B17,"") -> 427.89474 | F17: 4200 | G17: =IFERROR(F17/D17,"") -> 0.51660517
A18: =A17+7 -> 45704 | B18: 19 | C18: =IF(B18=0,"",B18/C$5) -> 0.86363636 | D18: 8130 | E18: =IFERROR(D18/B18,"") -> 427.89474 | F18: 3800 | G18: =IFERROR(F18/D18,"") -> 0.46740467
A19: =A18+7 -> 45711 | B19: 19 | C19: =IF(B19=0,"",B19/C$5) -> 0.86363636 | D19: 8130 | E19: =IFERROR(D19/B19,"") -> 427.89474 | F19: 4613 | G19: =IFERROR(F19/D19,"") -> 0.56740467
A20: Monthly Target | B20: 20 | C20: =IF(B20=0,"",B20/C$5) -> 0.90909091 | D20: 8000 | E20: =D20/B20 -> 400 | F20: 8000 | G20: =IFERROR(F20/D20,"") -> 1 | H20: 7043 | I20: 8000 | J20: =IF(H20=0,"",H20-I20) -> -957 | K20: =IFERROR((H20-I20)/H20,"") -> -0.1358796 | L20: 13342 | M20: 5000 | N20: =IF(L20=0,"",L20-M20) -> 8342 | O20: =IFERROR((L20-M20)/L20,"") -> 0.62524359 | P20: =H20-L20 -> -6299 | Q20: =I20-M20 -> 3000 | R20: Back paid Insurance owed to RDE and 1/2 year property taxes
A21: =A19+7 -> 45718 | B21: 19 | C21: =IF(B21=0,"",B21/C$5) -> 0.86363636 | D21: 8130 | E21: =IFERROR(D21/B21,"") -> 427.89474 | F21: 1400 | G21: =IFERROR(F21/D21,"") -> 0.17220172
A22: =A21+7 -> 45725 | B22: 19 | C22: =IF(B22=0,"",B22/C$5) -> 0.86363636 | D22: 8130 | E22: =IFERROR(D22/B22,"") -> 427.89474 | F22: 4900 | G22: =IFERROR(F22/D22,"") -> 0.60270603
A23: =A22+7 -> 45732 | B23: 18 | C23: =IF(B23=0,"",B23/C$5) -> 0.81818182 | D23: 7650 | E23: =IFERROR(D23/B23,"") -> 425 | F23: 4813 | G23: =IFERROR(F23/D23,"") -> 0.62915033
A24: =A23+7 -> 45739 | B24: 18 | C24: =IF(B24=0,"",B24/C$5) -> 0.81818182 | D24: 7650 | E24: =IFERROR(D24/B24,"") -> 425 | F24: 4813 | G24: =IFERROR(F24/D24,"") -> 0.62915033
A25: =A24+7 -> 45746 | B25: 18 | C25: =IF(B25=0,"",B25/C$5) -> 0.81818182 | D25: 7650 | E25: =IFERROR(D25/B25,"") -> 425 | F25: 4813 | G25: =IFERROR(F25/D25,"") -> 0.62915033
A26: Monthly Target | B26: 20 | C26: =IF(B26=0,"",B26/C$5) -> 0.90909091 | D26: 8000 | E26: =D26/B26 -> 400 | F26: 8000 | G26: =IFERROR(F26/D26,"") -> 1 | H26: 6973 | I26: 8000 | J26: =IF(H26=0,"",H26-I26) -> -1027 | K26: =IFERROR((H26-I26)/H26,"") -> -0.14728237 | L26: 6171 | M26: 5000 | N26: =IF(L26=0,"",L26-M26) -> 1171 | O26: =IFERROR((L26-M26)/L26,"") -> 0.18975855 | P26: =H26-L26 -> 802 | Q26: =I26-M26 -> 3000
A27: =A25+7 -> 45753 | B27: 18 | C27: =IF(B27=0,"",B27/C$5) -> 0.81818182 | D27: 6827 | E27: =D27/B27 -> 379.27778 | F27: 5194 | G27: =IFERROR(F27/D27,"") -> 0.7608027
A28: =A27+7 -> 45760 | B28: 18 | C28: =IF(B28=0,"",B28/C$5) -> 0.81818182 | D28: 6827 | E28: =D28/B28 -> 379.27778 | F28: 6594 | G28: =IFERROR(F28/D28,"") -> 0.96587081
A29: =A28+7 -> 45767 | B29: 18 | C29: =IF(B29=0,"",B29/C$5) -> 0.81818182 | D29: 6827 | E29: =D29/B29 -> 379.27778 | F29: 6993 | G29: =IFERROR(F29/D29,"") -> 1.0243152
A30: =A29+7 -> 45774 | B30: 18 | C30: =IF(B30=0,"",B30/C$5) -> 0.81818182 | D30: 6827 | E30: =D30/B30 -> 379.27778 | F30: 6993 | G30: =IFERROR(F30/D30,"") -> 1.0243152
A31: Monthly Target | B31: 20 | C31: =IF(B31=0,"",B31/C$5) -> 0.90909091 | D31: 8000 | E31: =D31/B31 -> 400 | F31: 8000 | G31: =IFERROR(F31/D31,"") -> 1 | H31: 8138 | I31: 8000 | J31: =IF(H31=0,"",H31-I31) -> 138 | K31: =IFERROR((H31-I31)/H31,"") -> 0.016957483 | L31: 2464 | M31: 5000 | N31: =IF(L31=0,"",L31-M31) -> -2536 | O31: =IFERROR((L31-M31)/L31,"") -> -1.0292208 | P31: =H31-L31 -> 5674 | Q31: =I31-M31 -> 3000
A32: =A30+7 -> 45781 | B32: 18 | C32: =IF(B32=0,"",B32/C$5) -> 0.81818182 | D32: 7127 | E32: =D32/B32 -> 395.94444 | F32: 5265 | G32: =IFERROR(F32/D32,"") -> 0.73874
A33: =A32+7 -> 45788 | B33: 18 | C33: =IF(B33=0,"",B33/C$5) -> 0.81818182 | D33: 7127 | E33: =IFERROR(D33/B33,"") -> 395.94444 | F33: 6528 | G33: =IFERROR(F33/D33,"") -> 0.91595342
A34: =A33+7 -> 45795 | B34: 18 | C34: =IF(B34=0,"",B34/C$5) -> 0.81818182 | D34: 7127 | E34: =IFERROR(D34/B34,"") -> 395.94444 | F34: 7227 | G34: =IFERROR(F34/D34,"") -> 1.0140311
A35: =A34+7 -> 45802 | B35: 18 | C35: =IF(B35=0,"",B35/C$5) -> 0.81818182 | D35: 7127 | E35: =IFERROR(D35/B35,"") -> 395.94444 | F35: 7227 | G35: =IFERROR(F35/D35,"") -> 1.0140311
A36: Monthly Target | B36: 20 | C36: =IF(B36=0,"",B36/C$5) -> 0.90909091 | D36: 8000 | E36: =D36/B36 -> 400 | F36: 8000 | G36: =IFERROR(F36/D36,"") -> 1 | H36: 7327 | I36: 8000 | J36: =IF(H36=0,"",H36-I36) -> -673 | K36: =IFERROR((H36-I36)/H36,"") -> -0.091852054 | L36: 8401 | M36: 5000 | N36: =IF(L36=0,"",L36-M36) -> 3401 | O36: =IFERROR((L36-M36)/L36,"") -> 0.40483276 | P36: =H36-L36 -> -1074 | Q36: =I36-M36 -> 3000 | R36: Trailer Turn Expenses $5,000
A37: =A35+7 -> 45809 | B37: 18 | C37: =IF(B37=0,"",B37/C$5) -> 0.81818182 | D37: 7127 | E37: =IFERROR(D37/B37,"") -> 395.94444 | F37: 3290 | G37: =IFERROR(F37/D37,"") -> 0.46162481
A38: =A37+7 -> 45816 | B38: 18 | C38: =IF(B38=0,"",B38/C$5) -> 0.81818182 | D38: 7127 | E38: =IFERROR(D38/B38,"") -> 395.94444 | F38: 6878 | G38: =IFERROR(F38/D38,"") -> 0.96506244
A39: =A38+7 -> 45823 | B39: 18 | C39: =IF(B39=0,"",B39/C$5) -> 0.81818182 | D39: 7127 | E39: =IFERROR(D39/B39,"") -> 395.94444 | F39: 6878 | G39: =IFERROR(F39/D39,"") -> 0.96506244
A40: =A39+7 -> 45830 | B40: 18 | C40: =IF(B40=0,"",B40/C$5) -> 0.81818182 | D40: 7127 | E40: =IFERROR(D40/B40,"") -> 395.94444 | F40: 6878 | G40: =IFERROR(F40/D40,"") -> 0.96506244
A41: =A40+7 -> 45837 | B41: 18 | C41: =IF(B41=0,"",B41/C$5) -> 0.81818182 | D41: 7127 | E41: =IFERROR(D41/B41,"") -> 395.94444 | F41: 6878.52 | G41: =IFERROR(F41/D41,"") -> 0.9651354
A42: Monthly Target | B42: 20 | C42: =IF(B42=0,"",B42/C$5) -> 0.90909091 | D42: 8000 | E42: =D42/B42 -> 400 | F42: 8000 | G42: =IFERROR(F42/D42,"") -> 1 | H42: 5977 | I42: 8000 | J42: =IF(H42=0,"",H42-I42) -> -2023 | K42: =IFERROR((H42-I42)/H42,"") -> -0.33846411 | L42: 13784 | M42: 5000 | N42: =IF(L42=0,"",L42-M42) -> 8784 | O42: =IFERROR((L42-M42)/L42,"") -> 0.63726059 | P42: =H42-L42 -> -7807 | Q42: =I42-M42 -> 3000 | R42: MH Turns for Sell Offs
A43: =A41+7 -> 45844 | B43: 19 | C43: =IF(B43=0,"",B43/C$5) -> 0.86363636 | D43: 7427 | E43: =IFERROR(D43/B43,"") -> 390.89474 | F43: 6728 | G43: =IFERROR(F43/D43,"") -> 0.90588394
A44: =A43+7 -> 45851 | B44: 19 | C44: =IF(B44=0,"",B44/C$5) -> 0.86363636 | D44: 7427 | E44: =IFERROR(D44/B44,"") -> 390.89474 | F44: 6728 | G44: =IFERROR(F44/D44,"") -> 0.90588394
A45: =A44+7 -> 45858 | B45: 21 | C45: =IF(B45=0,"",B45/C$5) -> 0.95454545 | D45: 8027 | E45: =IFERROR(D45/B45,"") -> 382.2381 | F45: 6728 | G45: =IFERROR(F45/D45,"") -> 0.83817117
A46: =A45+7 -> 45865 | B46: 21 | C46: =IF(B46=0,"",B46/C$5) -> 0.95454545 | D46: 8027 | E46: =IFERROR(D46/B46,"") -> 382.2381 | F46: 6728 | G46: =IFERROR(F46/D46,"") -> 0.83817117
A47: Monthly Target | B47: 20 | C47: =IF(B47=0,"",B47/C$5) -> 0.90909091 | D47: 8000 | E47: =D47/B47 -> 400 | F47: 8000 | G47: =IFERROR(F47/D47,"") -> 1 | H47: 6978 | I47: 8000 | J47: =IF(H47=0,"",H47-I47) -> -1022 | K47: =IFERROR((H47-I47)/H47,"") -> -0.1464603 | L47: 23457 | M47: 5000 | N47: =IF(L47=0,"",L47-M47) -> 18457 | O47: =IFERROR((L47-M47)/L47,"") -> 0.78684401 | P47: =H47-L47 -> -16479 | Q47: =I47-M47 -> 3000 | R47: Property Taxes & Unit Turns
A48: =A46+7 -> 45872 | B48: 21 | C48: =IF(B48=0,"",B48/C$5) -> 0.95454545 | D48: 7127 | E48: =IFERROR(D48/B48,"") -> 339.38095 | F48: 5265 | G48: =IFERROR(F48/D48,"") -> 0.73874
A49: =A48+7 -> 45879 | B49: 21 | C49: =IF(B49=0,"",B49/C$5) -> 0.95454545 | D49: 7127 | E49: =IFERROR(D49/B49,"") -> 339.38095 | F49: 6065 | G49: =IFERROR(F49/D49,"") -> 0.8509892
A50: =A49+7 -> 45886 | B50: 21 | C50: =IF(B50=0,"",B50/C$5) -> 0.95454545 | D50: 7127 | E50: =IFERROR(D50/B50,"") -> 339.38095 | F50: 6178 | G50: =IFERROR(F50/D50,"") -> 0.86684439
A51: =A50+7 -> 45893 | B51: 21 | C51: =IF(B51=0,"",B51/C$5) -> 0.95454545 | D51: 7127 | E51: =IFERROR(D51/B51,"") -> 339.38095 | F51: 6178 | G51: =IFERROR(F51/D51,"") -> 0.86684439
A52: =A51+7 -> 45900 | B52: 21 | C52: =IF(B52=0,"",B52/C$5) -> 0.95454545 | D52: 7127 | E52: =IFERROR(D52/B52,"") -> 339.38095 | F52: 6178 | G52: =IFERROR(F52/D52,"") -> 0.86684439
A53: Monthly Target | B53: 20 | C53: =IF(B53=0,"",B53/C$5) -> 0.90909091 | D53: 8000 | E53: =D53/B53 -> 400 | F53: 8000 | G53: =IFERROR(F53/D53,"") -> 1 | H53: 6178 | I53: 8000 | J53: =IF(H53=0,"",H53-I53) -> -1822 | K53: =IFERROR((H53-I53)/H53,"") -> -0.29491745 | L53: 3010 | M53: 5000 | N53: =IF(L53=0,"",L53-M53) -> -1990 | O53: =IFERROR((L53-M53)/L53,"") -> -0.66112957 | P53: =H53-L53 -> 3168 | Q53: =I53-M53 -> 3000 | R53: Plus $14,000 MH sale income
A54: =A52+7 -> 45907 | B54: 21 | C54: =IF(B54=0,"",B54/C$5) -> 0.95454545 | D54: 7677 | E54: =IFERROR(D54/B54,"") -> 365.57143 | F54: 7162 | G54: =IFERROR(F54/D54,"") -> 0.9329165
A55: =A54+7 -> 45914 | B55: 21 | C55: =IF(B55=0,"",B55/C$5) -> 0.95454545 | D55: 7677 | E55: =IFERROR(D55/B55,"") -> 365.57143 | F55: 7762 | G55: =IFERROR(F55/D55,"") -> 1.011072
A56: =A55+7 -> 45921 | B56: 21 | C56: =IF(B56=0,"",B56/C$5) -> 0.95454545 | D56: 7677 | E56: =IFERROR(D56/B56,"") -> 365.57143 | F56: 7762 | G56: =IFERROR(F56/D56,"") -> 1.011072
A57: =A56+7 -> 45928 | B57: 21 | C57: =IF(B57=0,"",B57/C$5) -> 0.95454545 | D57: 7677 | E57: =IFERROR(D57/B57,"") -> 365.57143 | F57: 7762 | G57: =IFERROR(F57/D57,"") -> 1.011072
A58: Monthly Target | B58: 20 | C58: =IF(B58=0,"",B58/C$5) -> 0.90909091 | D58: 8000 | E58: =D58/B58 -> 400 | F58: 8000 | G58: =IFERROR(F58/D58,"") -> 1 | H58: 7487 | I58: 8000 | J58: =IF(H58=0,"",H58-I58) -> -513 | K58: =IFERROR((H58-I58)/H58,"") -> -0.068518766 | L58: 3579 | M58: 5000 | N58: =IF(L58=0,"",L58-M58) -> -1421 | O58: =IFERROR((L58-M58)/L58,"") -> -0.39703828 | P58: =H58-L58 -> 3908 | Q58: =I58-M58 -> 3000
A59: =A57+7 -> 45935 | B59: 21 | C59: =IF(B59=0,"",B59/C$5) -> 0.95454545 | D59: 7927 | E59: =IFERROR(D59/B59,"") -> 377.47619 | F59: 5666 | G59: =IFERROR(F59/D59,"") -> 0.7147723
A60: =A59+7 -> 45942 | B60: 21 | C60: =IF(B60=0,"",B60/C$5) -> 0.95454545 | D60: 7927 | E60: =IFERROR(D60/B60,"") -> 377.47619 | F60: 7266 | G60: =IFERROR(F60/D60,"") -> 0.9166141
A61: =A60+7 -> 45949 | B61: 21 | C61: =IF(B61=0,"",B61/C$5) -> 0.95454545 | D61: 7927 | E61: =IFERROR(D61/B61,"") -> 377.47619 | F61: 7916 | G61: =IFERROR(F61/D61,"") -> 0.99861234
A62: =A61+7 -> 45956 | B62: 21 | C62: =IF(B62=0,"",B62/C$5) -> 0.95454545 | D62: 7927 | E62: =IFERROR(D62/B62,"") -> 377.47619 | F62: 8891 | G62: =IFERROR(F62/D62,"") -> 1.1216097
A63: Monthly Target | B63: 20 | C63: =IF(B63=0,"",B63/C$5) -> 0.90909091 | D63: 8000 | E63: =D63/B63 -> 400 | F63: 8000 | G63: =IFERROR(F63/D63,"") -> 1 | H63: 9866 | I63: 8000 | J63: =IF(H63=0,"",H63-I63) -> 1866 | K63: =IFERROR((H63-I63)/H63,"") -> 0.1891344 | L63: 4201 | M63: 5000 | N63: =IF(L63=0,"",L63-M63) -> -799 | O63: =IFERROR((L63-M63)/L63,"") -> -0.19019281 | P63: =H63-L63 -> 5665 | Q63: =I63-M63 -> 3000
A64: =A62+7 -> 45963 | B64: 21 | C64: =IF(B64=0,"",B64/C$5) -> 0.95454545 | D64: 7927 | E64: =IFERROR(D64/B64,"") -> 377.47619 | F64: 3965 | G64: =IFERROR(F64/D64,"") -> 0.50018923
A65: =A64+7 -> 45970 | B65: 21 | C65: =IF(B65=0,"",B65/C$5) -> 0.95454545 | D65: 7927 | E65: =IFERROR(D65/B65,"") -> 377.47619 | F65: 6615 | G65: =IFERROR(F65/D65,"") -> 0.83448972
A66: =A65+7 -> 45977 | B66: 21 | C66: =IF(B66=0,"",B66/C$5) -> 0.95454545 | D66: 7927 | E66: =IFERROR(D66/B66,"") -> 377.47619 | F66: 6615 | G66: =IFERROR(F66/D66,"") -> 0.83448972
A67: =A66+7 -> 45984 | B67: 21 | C67: =IF(B67=0,"",B67/C$5) -> 0.95454545 | D67: 7927 | E67: =IFERROR(D67/B67,"") -> 377.47619 | F67: 7115 | G67: =IFERROR(F67/D67,"") -> 0.89756528
A68: =A67+7 -> 45991 | B68: 21 | C68: =IF(B68=0,"",B68/C$5) -> 0.95454545 | D68: 7927 | E68: =IFERROR(D68/B68,"") -> 377.47619 | F68: 7728 | G68: =IFERROR(F68/D68,"") -> 0.97489593
A69: Monthly Target | B69: 20 | C69: =IF(B69=0,"",B69/C$5) -> 0.90909091 | D69: 8000 | E69: =D69/B69 -> 400 | F69: 8000 | G69: =IFERROR(F69/D69,"") -> 1 | I69: 8000 | J69: =IF(H69=0,"",H69-I69) | K69: =IFERROR((H69-I69)/H69,"") | M69: 5000 | N69: =IF(L69=0,"",L69-M69) | O69: =IFERROR((L69-M69)/L69,"") | P69: =H69-L69 -> 0 | Q69: =I69-M69 -> 3000
A70: =A68+7 -> 45998 | B70: 22 | C70: =IF(B70=0,"",B70/C$5) -> 1 | D70: 9131 | E70: =IFERROR(D70/B70,"") -> 415.04545 | F70: 6721 | G70: =IFERROR(F70/D70,"") -> 0.73606396
A71: =A70+7 -> 46005 | B71: 22 | C71: =IF(B71=0,"",B71/C$5) -> 1 | D71: 9131 | E71: =IFERROR(D71/B71,"") -> 415.04545 | F71: 7328 | G71: =IFERROR(F71/D71,"") -> 0.8025408
A72: =A71+7 -> 46012 | C72: =IF(B72=0,"",B72/C$5) | E72: =IFERROR(D72/B72,"") | G72: =IFERROR(F72/D72,"")
A73: =A72+7 -> 46019 | C73: =IF(B73=0,"",B73/C$5) | E73: =IFERROR(D73/B73,"") | G73: =IFERROR(F73/D73,"")
A74: Monthly Target | B74: 20 | C74: =IF(B74=0,"",B74/C$5) -> 0.90909091 | D74: 8000 | E74: =D74/B74 -> 400 | F74: 8000 | G74: =IFERROR(F74/D74,"") -> 1 | I74: 8000 | J74: =IF(H74=0,"",H74-I74) | K74: =IFERROR((H74-I74)/H74,"") | M74: 5000 | N74: =IF(L74=0,"",L74-M74) | O74: =IFERROR((L74-M74)/L74,"") | P74: =H74-L74 -> 0 | Q74: =I74-M74 -> 3000
A75: Annual Total | C75: =IF(B75=0,"",B75/C$5) | E75: =IFERROR(D75/B75,"") | G75: =IFERROR(F75/D75,"") | H75: =H15+H20+H26+H31+H36+H42+H47+H53+H58+H63+H69+H74 -> 71926 | I75: =I15+I20+I26+I31+I36+I42+I47+I53+I58+I63+I69+I74 -> 96000 | J75: =IF(H75=0,"",H75-I75) -> -24074 | K75: =IFERROR((H75-I75)/H75,"") -> -0.33470511 | L75: =L15+L20+L26+L31+L36+L42+L47+L53+L58+L63+L69+L74 -> 81590 | M75: =M15+M20+M26+M31+M36+M42+M47+M53+M58+M63+M69+M74 -> 60000 | N75: =IF(L75=0,"",L75-M75) -> 21590 | O75: =IFERROR((L75-M75)/L75,"") -> 0.26461576 | P75: =P15+P20+P26+P31+P36+P42+P47+P53+P58+P63+P69+P74 -> -9664 | Q75: =Q15+Q20+Q26+Q31+Q36+Q42+Q47+Q53+Q58+Q63+Q69+Q74 -> 36000
A76: ** | B76: ** | C76: ** | D76: ** | E76: ** | F76: ** | G76: ** | H76: ** | I76: ** | J76: ** | K76: ** | L76: ** | M76: ** | N76: ** | O76: ** | P76: ** | Q76: ** | R76: **

Sheet TRS Portfolio
A1: KEY
A2: Manual Input
A3: Owner Input or Formula
A4: Formula | B4: TRS Portfolio
B5: # of Units | C5: 16 | I5: KPI Tracker
A10: Week Ending Sunday | B10: # of Occupied Units | C10: Occupancy % | D10: Total Leased Rent Amount $ | E10: Average Rent | F10: Total Collections to Date $ | G10: Collection Percentage | H10: Actual Revenue (Monthly Only) | I10: Budgeted Revenue (Monthly Only) | J10: Variance $ | K10: Variance % | L10: Actual Expense (Monthly Only) | M10: Budgeted Expense (Monthly Only | N10: Variance $ | O10: Variance % | P10: Net Income | Q10: Net Income Projected | R10: Total Expenses
A11: 45662 | C11: =IF(B11=0,"",B11/C$5) | E11: =IFERROR(D11/B11,"") | G11: =IFERROR(F11/D11,"") | R11: 308 W Broadway Street, New Lexington Ohio (21 Real Pads)
A12: =A11+7 -> 45669 | C12: =IF(B12=0,"",B12/C$5) | E12: =IFERROR(D12/B12,"") | G12: =IFERROR(F12/D12,"")
A13: =A12+7 -> 45676 | C13: =IF(B13=0,"",B13/C$5) | E13: =IFERROR(D13/B13,"") | G13: =IFERROR(F13/D13,"")
A14: =A13+7 -> 45683 | C14: =IF(B14=0,"",B14/C$5) | E14: =IFERROR(D14/B14,"") | G14: =IFERROR(F14/D14,"")
A15: Monthly Target | C15: =IF(B15=0,"",B15/C$5) | G15: =IFERROR(F15/D15,"") | J15: =IF(H15=0,"",H15-I15) | K15: =IFERROR((H15-I15)/H15,"") | N15: =IF(L15=0,"",L15-M15) | O15: =IFERROR((L15-M15)/L15,"") | P15: =H15-L15 -> 0 | Q15: =I15-M15 -> 0
A16: =A14+7 -> 45690 | C16: =IF(B16=0,"",B16/C$5) | E16: =IFERROR(D16/B16,"") | G16: =IFERROR(F16/D16,"")
A17: =A16+7 -> 45697 | C17: =IF(B17=0,"",B17/C$5) | E17: =IFERROR(D17/B17,"") | G17: =IFERROR(F17/D17,"")
A18: =A17+7 -> 45704 | C18: =IF(B18=0,"",B18/C$5) | E18: =IFERROR(D18/B18,"") | G18: =IFERROR(F18/D18,"")
A19: =A18+7 -> 45711 | C19: =IF(B19=0,"",B19/C$5) | E19: =IFERROR(D19/B19,"") | G19: =IFERROR(F19/D19,"")
A20: Monthly Target | C20: =IF(B20=0,"",B20/C$5) | G20: =IFERROR(F20/D20,"") | J20: =IF(H20=0,"",H20-I20) | K20: =IFERROR((H20-I20)/H20,"") | N20: =IF(L20=0,"",L20-M20) | O20: =IFERROR((L20-M20)/L20,"") | P20: =H20-L20 -> 0 | Q20: =I20-M20 -> 0
A21: =A19+7 -> 45718 | C21: =IF(B21=0,"",B21/C$5) | E21: =IFERROR(D21/B21,"") | G21: =IFERROR(F21/D21,"")
A22: =A21+7 -> 45725 | C22: =IF(B22=0,"",B22/C$5) | E22: =IFERROR(D22/B22,"") | G22: =IFERROR(F22/D22,"")
A23: =A22+7 -> 45732 | C23: =IF(B23=0,"",B23/C$5) | E23: =IFERROR(D23/B23,"") | G23: =IFERROR(F23/D23,"")
A24: =A23+7 -> 45739 | C24: =IF(B24=0,"",B24/C$5) | E24: =IFERROR(D24/B24,"") | G24: =IFERROR(F24/D24,"")
A25: =A24+7 -> 45746 | C25: =IF(B25=0,"",B25/C$5) | E25: =IFERROR(D25/B25,"") | G25: =IFERROR(F25/D25,"")
A26: Monthly Target | C26: =IF(B26=0,"",B26/C$5) | G26: =IFERROR(F26/D26,"") | J26: =IF(H26=0,"",H26-I26) | K26: =IFERROR((H26-I26)/H26,"") | N26: =IF(L26=0,"",L26-M26) | O26: =IFERROR((L26-M26)/L26,"") | P26: =H26-L26 -> 0 | Q26: =I26-M26 -> 0
A27: =A25+7 -> 45753 | B27: 14 | C27: =IF(B27=0,"",B27/C$5) -> 0.875 | D27: 12974 | E27: =D27/B27 -> 926.71429 | F27: 10150 | G27: =IFERROR(F27/D27,"") -> 0.7823339
A28: =A27+7 -> 45760 | B28: 14 | C28: =IF(B28=0,"",B28/C$5) -> 0.875 | D28: 12974 | E28: =D28/B28 -> 926.71429 | F28: 11100 | G28: =IFERROR(F28/D28,"") -> 0.85555727
A29: =A28+7 -> 45767 | B29: 14 | C29: =IF(B29=0,"",B29/C$5) -> 0.875 | D29: 12974 | E29: =D29/B29 -> 926.71429 | F29: 11100 | G29: =IFERROR(F29/D29,"") -> 0.85555727
A30: =A29+7 -> 45774 | B30: 14 | C30: =IF(B30=0,"",B30/C$5) -> 0.875 | D30: 12974 | E30: =D30/B30 -> 926.71429 | F30: 11100 | G30: =IFERROR(F30/D30,"") -> 0.85555727
A31: Monthly Target | B31: 14 | C31: =IF(B31=0,"",B31/C$5) -> 0.875 | D31: 12974 | E31: =D31/B31 -> 926.71429 | F31: 12974 | G31: =IFERROR(F31/D31,"") -> 1 | H31: 14204 | I31: 13000 | J31: =IF(H31=0,"",H31-I31) -> 1204 | K31: =IFERROR((H31-I31)/H31,"") -> 0.084764855 | L31: 11556 | M31: 13150 | N31: =IF(L31=0,"",L31-M31) -> -1594 | O31: =IFERROR((L31-M31)/L31,"") -> -0.137937 | P31: =H31-L31 -> 2648 | Q31: =I31-M31 -> -150
A32: =A30+7 -> 45781 | B32: 15 | C32: =IF(B32=0,"",B32/C$5) -> 0.9375 | D32: 14074 | E32: =D32/B32 -> 938.26667 | F32: 12810 | G32: =IFERROR(F32/D32,"") -> 0.910189
A33: =A32+7 -> 45788 | B33: 15 | C33: =IF(B33=0,"",B33/C$5) -> 0.9375 | D33: 14074 | E33: =IFERROR(D33/B33,"") -> 938.26667 | F33: 12899 | G33: =IFERROR(F33/D33,"") -> 0.91651272
A34: =A33+7 -> 45795 | B34: 15 | C34: =IF(B34=0,"",B34/C$5) -> 0.9375 | D34: 14074 | E34: =IFERROR(D34/B34,"") -> 938.26667 | F34: 15249 | G34: =IFERROR(F34/D34,"") -> 1.0834873
A35: =A34+7 -> 45802 | B35: 15 | C35: =IF(B35=0,"",B35/C$5) -> 0.9375 | D35: 14074 | E35: =IFERROR(D35/B35,"") -> 938.26667 | F35: 15249 | G35: =IFERROR(F35/D35,"") -> 1.0834873
A36: Monthly Target | B36: 15 | C36: =IF(B36=0,"",B36/C$5) -> 0.9375 | D36: 14000 | E36: =D36/B36 -> 933.33333 | F36: 14000 | G36: =IFERROR(F36/D36,"") -> 1 | H36: 17500 | I36: 14000 | J36: =IF(H36=0,"",H36-I36) -> 3500 | K36: =IFERROR((H36-I36)/H36,"") -> 0.2 | L36: 14025 | M36: 13150 | N36: =IF(L36=0,"",L36-M36) -> 875 | O36: =IFERROR((L36-M36)/L36,"") -> 0.062388592 | P36: =H36-L36 -> 3475 | Q36: =I36-M36 -> 850
A37: =A35+7 -> 45809 | B37: 16 | C37: =IF(B37=0,"",B37/C$5) -> 1 | D37: 15274 | E37: =IFERROR(D37/B37,"") -> 954.625 | F37: 5526 | G37: =IFERROR(F37/D37,"") -> 0.36179128
A38: =A37+7 -> 45816 | B38: 16 | C38: =IF(B38=0,"",B38/C$5) -> 1 | D38: 15274 | E38: =IFERROR(D38/B38,"") -> 954.625 | F38: 15188 | G38: =IFERROR(F38/D38,"") -> 0.99436952
A39: =A38+7 -> 45823 | B39: 16 | C39: =IF(B39=0,"",B39/C$5) -> 1 | D39: 15274 | E39: =IFERROR(D39/B39,"") -> 954.625 | F39: 15274 | G39: =IFERROR(F39/D39,"") -> 1
A40: =A39+7 -> 45830 | B40: 16 | C40: =IF(B40=0,"",B40/C$5) -> 1 | D40: 15274 | E40: =IFERROR(D40/B40,"") -> 954.625 | F40: 15274 | G40: =IFERROR(F40/D40,"") -> 1
A41: =A40+7 -> 45837 | B41: 16 | C41: =IF(B41=0,"",B41/C$5) -> 1 | D41: 15274 | E41: =IFERROR(D41/B41,"") -> 954.625 | F41: 15274 | G41: =IFERROR(F41/D41,"") -> 1
A42: Monthly Target | B42: 15 | C42: =IF(B42=0,"",B42/C$5) -> 0.9375 | D42: 14000 | E42: =D42/B42 -> 933.33333 | F42: 14000 | G42: =IFERROR(F42/D42,"") -> 1 | H42: 14057 | I42: 14000 | J42: =IF(H42=0,"",H42-I42) -> 57 | K42: =IFERROR((H42-I42)/H42,"") -> 0.0040549193 | L42: 12539 | M42: 13150 | N42: =IF(L42=0,"",L42-M42) -> -611 | O42: =IFERROR((L42-M42)/L42,"") -> -0.048727969 | P42: =H42-L42 -> 1518 | Q42: =I42-M42 -> 850
A43: =A41+7 -> 45844 | B43: 16 | C43: =IF(B43=0,"",B43/C$5) -> 1 | D43: 15800 | E43: =IFERROR(D43/B43,"") -> 987.5 | F43: 14539 | G43: =IFERROR(F43/D43,"") -> 0.92018987
A44: =A43+7 -> 45851 | B44: 16 | C44: =IF(B44=0,"",B44/C$5) -> 1 | D44: 15800 | E44: =IFERROR(D44/B44,"") -> 987.5 | F44: 14625 | G44: =IFERROR(F44/D44,"") -> 0.92563291
A45: =A44+7 -> 45858 | B45: 16 | C45: =IF(B45=0,"",B45/C$5) -> 1 | D45: 15800 | E45: =IFERROR(D45/B45,"") -> 987.5 | F45: 15800 | G45: =IFERROR(F45/D45,"") -> 1
A46: =A45+7 -> 45865 | B46: 16 | C46: =IF(B46=0,"",B46/C$5) -> 1 | D46: 15800 | E46: =IFERROR(D46/B46,"") -> 987.5 | F46: 15800 | G46: =IFERROR(F46/D46,"") -> 1
A47: Monthly Target | B47: 15 | C47: =IF(B47=0,"",B47/C$5) -> 0.9375 | D47: 15627 | E47: =D47/B47 -> 1041.8 | F47: 15627 | G47: =IFERROR(F47/D47,"") -> 1 | H47: 18136 | I47: 15627 | J47: =IF(H47=0,"",H47-I47) -> 2509 | K47: =IFERROR((H47-I47)/H47,"") -> 0.13834363 | L47: 11863 | M47: 13150 | N47: =IF(L47=0,"",L47-M47) -> -1287 | O47: =IFERROR((L47-M47)/L47,"") -> -0.10848858 | P47: =H47-L47 -> 6273 | Q47: =I47-M47 -> 2477 | R47: Clean
A48: =A46+7 -> 45872 | B48: 16 | C48: =IF(B48=0,"",B48/C$5) -> 1 | D48: 15910 | E48: =IFERROR(D48/B48,"") -> 994.375 | F48: 15711 | G48: =IFERROR(F48/D48,"") -> 0.98749214
A49: =A48+7 -> 45879 | B49: 15 | C49: =IF(B49=0,"",B49/C$5) -> 0.9375 | D49: 14735 | E49: =IFERROR(D49/B49,"") -> 982.33333 | F49: 15797 | G49: =IFERROR(F49/D49,"") -> 1.0720733
A50: =A49+7 -> 45886 | B50: 15 | C50: =IF(B50=0,"",B50/C$5) -> 0.9375 | D50: 14735 | E50: =IFERROR(D50/B50,"") -> 982.33333 | F50: 15797 | G50: =IFERROR(F50/D50,"") -> 1.0720733
A51: =A50+7 -> 45893 | B51: 15 | C51: =IF(B51=0,"",B51/C$5) -> 0.9375 | D51: 14735 | E51: =IFERROR(D51/B51,"") -> 982.33333 | F51: 15797 | G51: =IFERROR(F51/D51,"") -> 1.0720733
A52: =A51+7 -> 45900 | B52: 15 | C52: =IF(B52=0,"",B52/C$5) -> 0.9375 | D52: 14735 | E52: =IFERROR(D52/B52,"") -> 982.33333 | F52: 15797 | G52: =IFERROR(F52/D52,"") -> 1.0720733
A53: Monthly Target | B53: 15 | C53: =IF(B53=0,"",B53/C$5) -> 0.9375 | D53: 15627 | E53: =D53/B53 -> 1041.8 | F53: 15627 | G53: =IFERROR(F53/D53,"") -> 1 | H53: 17652 | I53: 15627 | J53: =IF(H53=0,"",H53-I53) -> 2025 | K53: =IFERROR((H53-I53)/H53,"") -> 0.11471788 | L53: 11329 | M53: 13150 | N53: =IF(L53=0,"",L53-M53) -> -1821 | O53: =IFERROR((L53-M53)/L53,"") -> -0.16073793 | P53: =H53-L53 -> 6323 | Q53: =I53-M53 -> 2477 | R53: Clean
A54: =A52+7 -> 45907 | B54: 14 | C54: =IF(B54=0,"",B54/C$5) -> 0.875 | D54: 14044 | E54: =IFERROR(D54/B54,"") -> 1003.1429 | F54: 13878 | G54: =IFERROR(F54/D54,"") -> 0.98818001
A55: =A54+7 -> 45914 | B55: 14 | C55: =IF(B55=0,"",B55/C$5) -> 0.875 | D55: 14044 | E55: =IFERROR(D55/B55,"") -> 1003.1429 | F55: 14041 | G55: =IFERROR(F55/D55,"") -> 0.99978639
A56: =A55+7 -> 45921 | B56: 15 | C56: =IF(B56=0,"",B56/C$5) -> 0.9375 | D56: 15094 | E56: =IFERROR(D56/B56,"") -> 1006.2667 | F56: 14041 | G56: =IFERROR(F56/D56,"") -> 0.93023718
A57: =A56+7 -> 45928 | B57: 15 | C57: =IF(B57=0,"",B57/C$5) -> 0.9375 | D57: 15094 | E57: =IFERROR(D57/B57,"") -> 1006.2667 | F57: 14041 | G57: =IFERROR(F57/D57,"") -> 0.93023718
A58: Monthly Target | B58: 15 | C58: =IF(B58=0,"",B58/C$5) -> 0.9375 | D58: 15627 | E58: =D58/B58 -> 1041.8 | F58: 15627 | G58: =IFERROR(F58/D58,"") -> 1 | H58: 14907 | I58: 15627 | J58: =IF(H58=0,"",H58-I58) -> -720 | K58: =IFERROR((H58-I58)/H58,"") -> -0.048299457 | L58: 13528 | M58: 13150 | N58: =IF(L58=0,"",L58-M58) -> 378 | O58: =IFERROR((L58-M58)/L58,"") -> 0.027942046 | P58: =H58-L58 -> 1379 | Q58: =I58-M58 -> 2477
A59: =A57+7 -> 45935 | B59: 15 | C59: =IF(B59=0,"",B59/C$5) -> 0.9375 | D59: 15014 | E59: =IFERROR(D59/B59,"") -> 1000.9333 | F59: 11992 | G59: =IFERROR(F59/D59,"") -> 0.79872119
A60: =A59+7 -> 45942 | B60: 15 | C60: =IF(B60=0,"",B60/C$5) -> 0.9375 | D60: 15014 | E60: =IFERROR(D60/B60,"") -> 1000.9333 | F60: 12864 | G60: =IFERROR(F60/D60,"") -> 0.85680032
A61: =A60+7 -> 45949 | B61: 15 | C61: =IF(B61=0,"",B61/C$5) -> 0.9375 | D61: 15014 | E61: =IFERROR(D61/B61,"") -> 1000.9333 | F61: 12864 | G61: =IFERROR(F61/D61,"") -> 0.85680032
A62: =A61+7 -> 45956 | B62: 16 | C62: =IF(B62=0,"",B62/C$5) -> 1 | D62: 16264 | E62: =IFERROR(D62/B62,"") -> 1016.5 | F62: 13187 | G62: =IFERROR(F62/D62,"") -> 0.81080915
A63: Monthly Target | B63: 15 | C63: =IF(B63=0,"",B63/C$5) -> 0.9375 | D63: 15627 | E63: =D63/B63 -> 1041.8 | F63: 15627 | G63: =IFERROR(F63/D63,"") -> 1 | H63: 17916 | I63: 15627 | J63: =IF(H63=0,"",H63-I63) -> 2289 | K63: =IFERROR((H63-I63)/H63,"") -> 0.12776289 | L63: 14788 | M63: 13150 | N63: =IF(L63=0,"",L63-M63) -> 1638 | O63: =IFERROR((L63-M63)/L63,"") -> 0.11076549 | P63: =H63-L63 -> 3128 | Q63: =I63-M63 -> 2477
A64: =A62+7 -> 45963 | B64: 16 | C64: =IF(B64=0,"",B64/C$5) -> 1 | D64: 16264 | E64: =IFERROR(D64/B64,"") -> 1016.5 | F64: 9030 | G64: =IFERROR(F64/D64,"") -> 0.55521397
A65: =A64+7 -> 45970 | B65: 16 | C65: =IF(B65=0,"",B65/C$5) -> 1 | D65: 16264 | E65: =IFERROR(D65/B65,"") -> 1016.5 | F65: 16207 | G65: =IFERROR(F65/D65,"") -> 0.99649533
A66: =A65+7 -> 45977 | B66: 15 | C66: =IF(B66=0,"",B66/C$5) -> 0.9375 | D66: 15104 | E66: =IFERROR(D66/B66,"") -> 1006.9333 | F66: 16370 | G66: =IFERROR(F66/D66,"") -> 1.0838189
A67: =A66+7 -> 45984 | B67: 15 | C67: =IF(B67=0,"",B67/C$5) -> 0.9375 | D67: 15104 | E67: =IFERROR(D67/B67,"") -> 1006.9333 | F67: 16370 | G67: =IFERROR(F67/D67,"") -> 1.0838189
A68: Monthly Target | B68: 15 | C68: =IF(B68=0,"",B68/C$5) -> 0.9375 | D68: 15627 | E68: =D68/B68 -> 1041.8 | F68: 15627 | G68: =IFERROR(F68/D68,"") -> 1 | I68: 15627 | J68: =IF(H68=0,"",H68-I68) | K68: =IFERROR((H68-I68)/H68,"") | M68: 13150 | N68: =IF(L68=0,"",L68-M68) | O68: =IFERROR((L68-M68)/L68,"") | P68: =H68-L68 -> 0 | Q68: =I68-M68 -> 2477
A69: =A67+7 -> 45991 | B69: 16 | C69: =IF(B69=0,"",B69/C$5) -> 1 | D69: 15104 | E69: =IFERROR(D69/B69,"") -> 944 | F69: 16370 | G69: =IFERROR(F69/D69,"") -> 1.0838189
A70: =A69+7 -> 45998 | B70: 16 | C70: =IF(B70=0,"",B70/C$5) -> 1 | D70: 15104 | E70: =IFERROR(D70/B70,"") -> 944 | F70: 13967 | G70: =IFERROR(F70/D70,"") -> 0.92472193
A71: =A70+7 -> 46005 | B71: 16 | C71: =IF(B71=0,"",B71/C$5) -> 1 | D71: 15104 | E71: =IFERROR(D71/B71,"") -> 944 | F71: 13967 | G71: =IFERROR(F71/D71,"") -> 0.92472193
A72: =A71+7 -> 46012 | C72: =IF(B72=0,"",B72/C$5) | E72: =IFERROR(D72/B72,"") | G72: =IFERROR(F72/D72,"")
A73: =A72+7 -> 46019 | C73: =IF(B73=0,"",B73/C$5) | E73: =IFERROR(D73/B73,"") | G73: =IFERROR(F73/D73,"")
A74: Monthly Target | B74: 15 | C74: =IF(B74=0,"",B74/C$5) -> 0.9375 | D74: 15627 | E74: =D74/B74 -> 1041.8 | F74: 15627 | G74: =IFERROR(F74/D74,"") -> 1 | I74: 15627 | J74: =IF(H74=0,"",H74-I74) | K74: =IFERROR((H74-I74)/H74,"") | M74: 13150 | N74: =IF(L74=0,"",L74-M74) | O74: =IFERROR((L74-M74)/L74,"") | P74: =H74-L74 -> 0 | Q74: =I74-M74 -> 2477
A75: Annual Total | C75: =IF(B75=0,"",B75/C$5) | E75: =IFERROR(D75/B75,"") | G75: =IFERROR(F75/D75,"") | H75: =H15+H20+H26+H31+H36+H42+H47+H53+H58+H63+H68+H74 -> 114372 | I75: =I15+I20+I26+I31+I36+I42+I47+I53+I58+I63+I68+I74 -> 134762 | J75: =IF(H75=0,"",H75-I75) -> -20390 | K75: =IFERROR((H75-I75)/H75,"") -> -0.1782779 | L75: =L15+L20+L26+L31+L36+L42+L47+L53+L58+L63+L68+L74 -> 89628 | M75: =M15+M20+M26+M31+M36+M42+M47+M53+M58+M63+M68+M74 -> 118350 | N75: =IF(L75=0,"",L75-M75) -> -28722 | O75: =IFERROR((L75-M75)/L75,"") -> -0.32045789 | P75: =P15+P20+P26+P31+P36+P42+P47+P53+P58+P63+P68+P74 -> 24744 | Q75: =Q15+Q20+Q26+Q31+Q36+Q42+Q47+Q53+Q58+Q63+Q68+Q74 -> 16412
A76: ** | B76: ** | C76: ** | D76: ** | E76: ** | F76: ** | G76: ** | H76: ** | I76: ** | J76: ** | K76: ** | L76: ** | M76: ** | N76: ** | O76: ** | P76: ** | Q76: ** | R76: **

Sheet MT Vernon Studios
A1: KEY
A2: Manual Input
A3: Owner Input or Formula
A4: Formula | B4: Mt Vernon
B5: # of Units | C5: 51 | I5: KPI Tracker
A10: Week Ending Sunday | B10: # of Occupied Units | C10: Occupancy % | D10: Total Leased Rent Amount $ | E10: Average Rent | F10: Total Collections to Date $ | G10: Collection Percentage | H10: Actual Revenue (Monthly Only) | I10: Budgeted Revenue (Monthly Only) | J10: Variance $ | K10: Variance % | L10: Actual Expense (Monthly Only) | M10: Budgeted Expense (Monthly Only | N10: Variance $ | O10: Variance % | P10: Net Income | Q10: Net Income Budgeteted | R10: Total Expenses
A11: 45662 | C11: =IF(B11=0,"",B11/C$5) | E11: =IFERROR(D11/B11,"") | G11: =IFERROR(F11/D11,"") | R11: 123 N Broad Street, Lancaster, Ohio 43130
A12: =A11+7 -> 45669 | C12: =IF(B12=0,"",B12/C$5) | E12: =IFERROR(D12/B12,"") | G12: =IFERROR(F12/D12,"")
A13: =A12+7 -> 45676 | C13: =IF(B13=0,"",B13/C$5) | E13: =IFERROR(D13/B13,"") | G13: =IFERROR(F13/D13,"")
A14: =A13+7 -> 45683 | C14: =IF(B14=0,"",B14/C$5) | E14: =IFERROR(D14/B14,"")
A15: Monthly Target | C15: =IF(B15=0,"",B15/C$5) | G15: =IFERROR(F15/D15,"") | J15: =IF(H15=0,"",H15-I15) | K15: =IFERROR((H15-I15)/H15,"") | N15: =IF(L15=0,"",L15-M15) | O15: =IFERROR((L15-M15)/L15,"") | P15: =H15-L15 -> 0 | Q15: =I15-M15 -> 0
A16: =A14+7 -> 45690 | C16: =IF(B16=0,"",B16/C$5) | E16: =IFERROR(D16/B16,"") | G16: =IFERROR(F16/D16,"")
A17: =A16+7 -> 45697 | C17: =IF(B17=0,"",B17/C$5) | E17: =IFERROR(D17/B17,"") | G17: =IFERROR(F17/D17,"")
A18: =A17+7 -> 45704 | C18: =IF(B18=0,"",B18/C$5) | E18: =IFERROR(D18/B18,"") | G18: =IFERROR(F18/D18,"")
A19: =A18+7 -> 45711 | C19: =IF(B19=0,"",B19/C$5) | E19: =IFERROR(D19/B19,"") | G19: =IFERROR(F19/D19,"")
A20: Monthly Target | C20: =IF(B20=0,"",B20/C$5) | G20: =IFERROR(F20/D20,"") | J20: =IF(H20=0,"",H20-I20) | K20: =IFERROR((H20-I20)/H20,"") | N20: =IF(L20=0,"",L20-M20) | O20: =IFERROR((L20-M20)/L20,"") | P20: =H20-L20 -> 0 | Q20: =I20-M20 -> 0
A21: =A19+7 -> 45718 | C21: =IF(B21=0,"",B21/C$5) | E21: =IFERROR(D21/B21,"") | G21: =IFERROR(F21/D21,"")
A22: =A21+7 -> 45725 | C22: =IF(B22=0,"",B22/C$5) | E22: =IFERROR(D22/B22,"") | G22: =IFERROR(F22/D22,"")
A23: =A22+7 -> 45732 | C23: =IF(B23=0,"",B23/C$5) | E23: =IFERROR(D23/B23,"") | G23: =IFERROR(F23/D23,"")
A24: =A23+7 -> 45739 | C24: =IF(B24=0,"",B24/C$5) | E24: =IFERROR(D24/B24,"") | G24: =IFERROR(F24/D24,"")
A25: =A24+7 -> 45746 | C25: =IF(B25=0,"",B25/C$5) | E25: =IFERROR(D25/B25,"") | G25: =IFERROR(F25/D25,"")
A26: Monthly Target | C26: =IF(B26=0,"",B26/C$5) | G26: =IFERROR(F26/D26,"") | J26: =IF(H26=0,"",H26-I26) | K26: =IFERROR((H26-I26)/H26,"") | N26: =IF(L26=0,"",L26-M26) | O26: =IFERROR((L26-M26)/L26,"") | P26: =H26-L26 -> 0 | Q26: =I26-M26 -> 0
A27: =A25+7 -> 45753 | C27: =IF(B27=0,"",B27/C$5) | E27: =IFERROR(D27/B27,"") | G27: =IFERROR(F27/D27,"")
A28: =A27+7 -> 45760 | C28: =IF(B28=0,"",B28/C$5) | E28: =IFERROR(D28/B28,"") | G28: =IFERROR(F28/D28,"")
A29: =A28+7 -> 45767 | C29: =IF(B29=0,"",B29/C$5) | E29: =IFERROR(D29/B29,"") | G29: =IFERROR(F29/D29,"")
A30: =A29+7 -> 45774 | C30: =IF(B30=0,"",B30/C$5) | E30: =IFERROR(D30/B30,"") | G30: =IFERROR(F30/D30,"")
A31: Monthly Target | C31: =IF(B31=0,"",B31/C$5) | G31: =IFERROR(F31/D31,"") | J31: =IF(H31=0,"",H31-I31) | K31: =IFERROR((H31-I31)/H31,"") | N31: =IF(L31=0,"",L31-M31) | O31: =IFERROR((L31-M31)/L31,"") | P31: =H31-L31 -> 0 | Q31: =I31-M31 -> 0
A32: =A30+7 -> 45781 | C32: =IF(B32=0,"",B32/C$5) | E32: =IFERROR(D32/B32,"") | G32: =IFERROR(F32/D32,"")
A33: =A32+7 -> 45788 | C33: =IF(B33=0,"",B33/C$5) | E33: =IFERROR(D33/B33,"") | G33: =IFERROR(F33/D33,"")
A34: =A33+7 -> 45795 | B34: 49 | C34: =IF(B34=0,"",B34/C$5) -> 0.96078431 | D34: 23941 | E34: =IFERROR(D34/B34,"") -> 488.59184 | F34: 11888 | G34: =IFERROR(F34/D34,"") -> 0.49655403
A35: =A34+7 -> 45802 | B35: 48 | C35: =IF(B35=0,"",B35/C$5) -> 0.94117647 | D35: 23462 | E35: =IFERROR(D35/B35,"") -> 488.79167 | F35: 11888 | G35: =IFERROR(F35/D35,"") -> 0.50669167
A36: Monthly Target | B36: 43 | C36: =IF(B36=0,"",B36/C$5) -> 0.84313725 | D36: 25850 | E36: =D36/B36 -> 601.16279 | F36: 25850 | G36: =IFERROR(F36/D36,"") -> 1 | H36: 21516 | I36: 12925 | J36: =IF(H36=0,"",H36-I36) -> 8591 | K36: =IFERROR((H36-I36)/H36,"") -> 0.39928425 | L36: 27028 | M36: 24704 | N36: =IF(L36=0,"",L36-M36) -> 2324 | O36: =IFERROR((L36-M36)/L36,"") -> 0.085984905 | P36: =H36-L36 -> -5512 | Q36: =I36-M36 -> -11779 | R36: Property Insurance for the year and an additional $28,000 in building improvmeents
A37: =A35+7 -> 45809 | B37: 47 | C37: =IF(B37=0,"",B37/C$5) -> 0.92156863 | D37: 22943 | E37: =IFERROR(D37/B37,"") -> 488.14894 | F37: 11489 | G37: =IFERROR(F37/D37,"") -> 0.50076276
A38: =A37+7 -> 45816 | B38: 47 | C38: =IF(B38=0,"",B38/C$5) -> 0.92156863 | D38: 22943 | E38: =IFERROR(D38/B38,"") -> 488.14894 | F38: 19530 | G38: =IFERROR(F38/D38,"") -> 0.85124003
A39: =A38+7 -> 45823 | B39: 47 | C39: =IF(B39=0,"",B39/C$5) -> 0.92156863 | D39: 22943 | E39: =IFERROR(D39/B39,"") -> 488.14894 | F39: 20009 | G39: =IFERROR(F39/D39,"") -> 0.87211786
A40: =A39+7 -> 45830 | B40: 46 | C40: =IF(B40=0,"",B40/C$5) -> 0.90196078 | D40: 22464 | E40: =IFERROR(D40/B40,"") -> 488.34783 | F40: 20627 | G40: =IFERROR(F40/D40,"") -> 0.91822472
A41: =A40+7 -> 45837 | B41: 46 | C41: =IF(B41=0,"",B41/C$5) -> 0.90196078 | D41: 22464 | E41: =IFERROR(D41/B41,"") -> 488.34783 | F41: 21835 | G41: =IFERROR(F41/D41,"") -> 0.97199964
A42: Monthly Target | B42: 43 | C42: =IF(B42=0,"",B42/C$5) -> 0.84313725 | D42: 25850 | E42: =D42/B42 -> 601.16279 | F42: 25850 | G42: =IFERROR(F42/D42,"") -> 1 | H42: 21381 | I42: 25850 | J42: =IF(H42=0,"",H42-I42) -> -4469 | K42: =IFERROR((H42-I42)/H42,"") -> -0.20901735 | L42: 22246 | M42: 24704 | N42: =IF(L42=0,"",L42-M42) -> -2458 | O42: =IFERROR((L42-M42)/L42,"") -> -0.11049177 | P42: =H42-L42 -> -865 | Q42: =I42-M42 -> 1146 | R42: $28,000 in building improvements / proeprty stabalization not in Expense number
A43: =A41+7 -> 45844 | B43: 42 | C43: =IF(B43=0,"",B43/C$5) -> 0.82352941 | D43: 21912 | E43: =IFERROR(D43/B43,"") -> 521.71429 | F43: 21071 | G43: =IFERROR(F43/D43,"") -> 0.9616192
A44: =A43+7 -> 45851 | B44: 42 | C44: =IF(B44=0,"",B44/C$5) -> 0.82352941 | D44: 21912 | E44: =IFERROR(D44/B44,"") -> 521.71429 | F44: 21577 | G44: =IFERROR(F44/D44,"") -> 0.98471157
A45: =A44+7 -> 45858 | B45: 42 | C45: =IF(B45=0,"",B45/C$5) -> 0.82352941 | D45: 21912 | E45: =IFERROR(D45/B45,"") -> 521.71429 | F45: 21577 | G45: =IFERROR(F45/D45,"") -> 0.98471157
A46: =A45+7 -> 45865 | B46: 42 | C46: =IF(B46=0,"",B46/C$5) -> 0.82352941 | D46: 21912 | E46: =IFERROR(D46/B46,"") -> 521.71429 | F46: 22077 | G46: =IFERROR(F46/D46,"") -> 1.0075301
A47: Monthly Target | B47: 43 | C47: =IF(B47=0,"",B47/C$5) -> 0.84313725 | D47: 25850 | E47: =D47/B47 -> 601.16279 | F47: 25850 | G47: =IFERROR(F47/D47,"") -> 1 | H47: 22956 | I47: 25850 | J47: =IF(H47=0,"",H47-I47) -> -2894 | K47: =IFERROR((H47-I47)/H47,"") -> -0.12606726 | L47: 18831 | M47: 24704 | N47: =IF(L47=0,"",L47-M47) -> -5873 | O47: =IFERROR((L47-M47)/L47,"") -> -0.31187935 | P47: =H47-L47 -> 4125 | Q47: =I47-M47 -> 1146 | R47: $49,000 in Property Stabalization & Building Improvements
A48: =A46+7 -> 45872 | B48: 40 | C48: =IF(B48=0,"",B48/C$5) -> 0.78431373 | D48: 21433 | E48: =IFERROR(D48/B48,"") -> 535.825 | F48: 18082 | G48: =IFERROR(F48/D48,"") -> 0.84365231
A49: =A48+7 -> 45879 | B49: 40 | C49: =IF(B49=0,"",B49/C$5) -> 0.78431373 | D49: 20908 | E49: =IFERROR(D49/B49,"") -> 522.7 | F49: 20182 | G49: =IFERROR(F49/D49,"") -> 0.96527645
A50: =A49+7 -> 45886 | B50: 40 | C50: =IF(B50=0,"",B50/C$5) -> 0.78431373 | D50: 20908 | E50: =IFERROR(D50/B50,"") -> 522.7 | F50: 20444 | G50: =IFERROR(F50/D50,"") -> 0.97780754
A51: =A50+7 -> 45893 | B51: 40 | C51: =IF(B51=0,"",B51/C$5) -> 0.78431373 | D51: 20908 | E51: =IFERROR(D51/B51,"") -> 522.7 | F51: 21168 | G51: =IFERROR(F51/D51,"") -> 1.0124354
A52: =A51+7 -> 45900 | B52: 40 | C52: =IF(B52=0,"",B52/C$5) -> 0.78431373 | D52: 20908 | E52: =IFERROR(D52/B52,"") -> 522.7 | F52: 21168 | G52: =IFERROR(F52/D52,"") -> 1.0124354
A53: Monthly Target | B53: 43 | C53: =IF(B53=0,"",B53/C$5) -> 0.84313725 | D53: 25850 | E53: =D53/B53 -> 601.16279 | F53: 25850 | G53: =IFERROR(F53/D53,"") -> 1 | H53: 21549 | I53: 25850 | J53: =IF(H53=0,"",H53-I53) -> -4301 | K53: =IFERROR((H53-I53)/H53,"") -> -0.19959163 | L53: 18551 | M53: 24704 | N53: =IF(L53=0,"",L53-M53) -> -6153 | O53: =IFERROR((L53-M53)/L53,"") -> -0.33168023 | P53: =H53-L53 -> 2998 | Q53: =I53-M53 -> 1146 | R53: PLus $29,000 in building improvements
A54: =A52+7 -> 45907 | B54: 38 | C54: =IF(B54=0,"",B54/C$5) -> 0.74509804 | D54: 19695 | E54: =IFERROR(D54/B54,"") -> 518.28947 | F54: 18623 | G54: =IFERROR(F54/D54,"") -> 0.94556994
A55: =A54+7 -> 45914 | B55: 38 | C55: =IF(B55=0,"",B55/C$5) -> 0.74509804 | D55: 19695 | E55: =IFERROR(D55/B55,"") -> 518.28947 | F55: 18623 | G55: =IFERROR(F55/D55,"") -> 0.94556994
A56: =A55+7 -> 45921 | B56: 38 | C56: =IF(B56=0,"",B56/C$5) -> 0.74509804 | D56: 20444 | E56: =IFERROR(D56/B56,"") -> 538 | F56: 19521 | G56: =IFERROR(F56/D56,"") -> 0.95485228
A57: =A56+7 -> 45928 | B57: 40 | C57: =IF(B57=0,"",B57/C$5) -> 0.78431373 | D57: 22034 | E57: =IFERROR(D57/B57,"") -> 550.85 | F57: 21111 | G57: =IFERROR(F57/D57,"") -> 0.95811019
A58: Monthly Target | B58: 43 | C58: =IF(B58=0,"",B58/C$5) -> 0.84313725 | D58: 25850 | E58: =D58/B58 -> 601.16279 | F58: 25850 | G58: =IFERROR(F58/D58,"") -> 1 | H58: 22385 | I58: 25850 | J58: =IF(H58=0,"",H58-I58) -> -3465 | K58: =IFERROR((H58-I58)/H58,"") -> -0.15479115 | L58: 18401 | M58: 24704 | N58: =IF(L58=0,"",L58-M58) -> -6303 | O58: =IFERROR((L58-M58)/L58,"") -> -0.34253573 | P58: =H58-L58 -> 3984 | Q58: =I58-M58 -> 1146 | R58: PLus $38,280 in building improvements
A59: =A57+7 -> 45935 | B59: 39 | C59: =IF(B59=0,"",B59/C$5) -> 0.76470588 | D59: 21779 | E59: =IFERROR(D59/B59,"") -> 558.4359 | F59: 18345 | G59: =IFERROR(F59/D59,"") -> 0.84232518
A60: =A59+7 -> 45942 | B60: 40 | C60: =IF(B60=0,"",B60/C$5) -> 0.78431373 | D60: 22574 | E60: =IFERROR(D60/B60,"") -> 564.35 | F60: 19485 | G60: =IFERROR(F60/D60,"") -> 0.86316116
A61: =A60+7 -> 45949 | B61: 40 | C61: =IF(B61=0,"",B61/C$5) -> 0.78431373 | D61: 22574 | E61: =IFERROR(D61/B61,"") -> 564.35 | F61: 20280 | G61: =IFERROR(F61/D61,"") -> 0.89837867
A62: =A61+7 -> 45956 | B62: 41 | C62: =IF(B62=0,"",B62/C$5) -> 0.80392157 | D62: 23369 | E62: =IFERROR(D62/B62,"") -> 569.97561 | F62: 20865 | G62: =IFERROR(F62/D62,"") -> 0.8928495
A63: Monthly Target | B63: 43 | C63: =IF(B63=0,"",B63/C$5) -> 0.84313725 | D63: 25850 | E63: =D63/B63 -> 601.16279 | F63: 25850 | G63: =IFERROR(F63/D63,"") -> 1 | H63: 20786 | I63: 25850 | J63: =IF(H63=0,"",H63-I63) -> -5064 | K63: =IFERROR((H63-I63)/H63,"") -> -0.24362552 | L63: 19275 | M63: 24704 | N63: =IF(L63=0,"",L63-M63) -> -5429 | O63: =IFERROR((L63-M63)/L63,"") -> -0.28166018 | P63: =H63-L63 -> 1511 | Q63: =I63-M63 -> 1146 | R63: Plus 37k property stabalization
A64: =A62+7 -> 45963 | B64: 41 | C64: =IF(B64=0,"",B64/C$5) -> 0.80392157 | D64: 23369 | E64: =IFERROR(D64/B64,"") -> 569.97561 | F64: 17518 | G64: =IFERROR(F64/D64,"") -> 0.74962557
A65: =A64+7 -> 45970 | B65: 41 | C65: =IF(B65=0,"",B65/C$5) -> 0.80392157 | D65: 23369 | E65: =IFERROR(D65/B65,"") -> 569.97561 | F65: 20624 | G65: =IFERROR(F65/D65,"") -> 0.88253669
A66: =A65+7 -> 45977 | B66: 40 | C66: =IF(B66=0,"",B66/C$5) -> 0.78431373 | D66: 22844 | E66: =IFERROR(D66/B66,"") -> 571.1 | F66: 20624 | G66: =IFERROR(F66/D66,"") -> 0.90281912
A67: =A66+7 -> 45984 | B67: 40 | C67: =IF(B67=0,"",B67/C$5) -> 0.78431373 | D67: 22844 | E67: =IFERROR(D67/B67,"") -> 571.1 | F67: 21364 | G67: =IFERROR(F67/D67,"") -> 0.93521275
A68: =A67+7 -> 45991 | B68: 40 | C68: =IF(B68=0,"",B68/C$5) -> 0.78431373 | D68: 22844 | E68: =IFERROR(D68/B68,"") -> 571.1 | F68: 22493 | G68: =IFERROR(F68/D68,"") -> 0.98463492
A69: Monthly Target | B69: 43 | C69: =IF(B69=0,"",B69/C$5) -> 0.84313725 | D69: 25850 | E69: =D69/B69 -> 601.16279 | F69: 25850 | G69: =IFERROR(F69/D69,"") -> 1 | I69: 25850 | J69: =IF(H69=0,"",H69-I69) | K69: =IFERROR((H69-I69)/H69,"") | M69: 24704 | N69: =IF(L69=0,"",L69-M69) | O69: =IFERROR((L69-M69)/L69,"") | P69: =H69-L69 -> 0 | Q69: =I69-M69 -> 1146
A70: =A68+7 -> 45998 | B70: 40 | C70: =IF(B70=0,"",B70/C$5) -> 0.78431373 | D70: 22844 | E70: =IFERROR(D70/B70,"") -> 571.1 | F70: 20192 | G70: =IFERROR(F70/D70,"") -> 0.88390825
A71: =A70+7 -> 46005 | B71: 40 | C71: =IF(B71=0,"",B71/C$5) -> 0.78431373 | D71: 22844 | E71: =IFERROR(D71/B71,"") -> 571.1 | F71: 20412 | G71: =IFERROR(F71/D71,"") -> 0.89353878
A72: =A71+7 -> 46012 | C72: =IF(B72=0,"",B72/C$5) | E72: =IFERROR(D72/B72,"") | G72: =IFERROR(F72/D72,"")
A73: =A72+7 -> 46019 | C73: =IF(B73=0,"",B73/C$5) | E73: =IFERROR(D73/B73,"") | G73: =IFERROR(F73/D73,"")
A74: Monthly Target | B74: 43 | C74: =IF(B74=0,"",B74/C$5) -> 0.84313725 | D74: 25850 | E74: =D74/B74 -> 601.16279 | F74: 25850 | G74: =IFERROR(F74/D74,"") -> 1 | I74: 25850 | J74: =IF(H74=0,"",H74-I74) | K74: =IFERROR((H74-I74)/H74,"") | M74: 24704 | N74: =IF(L74=0,"",L74-M74) | O74: =IFERROR((L74-M74)/L74,"") | P74: =H74-L74 -> 0 | Q74: =I74-M74 -> 1146
A75: Annual Total | C75: =IF(B75=0,"",B75/C$5) | E75: =IFERROR(D75/B75,"") | G75: =IFERROR(F75/D75,"") | H75: =H15+H20+H26+H31+H36+H42+H47+H53+H58+H63+H69+H74 -> 130573 | I75: =I15+I20+I26+I31+I36+I42+I47+I53+I58+I63+I69+I74 -> 193875 | J75: =IF(H75=0,"",H75-I75) -> -63302 | K75: =IFERROR((H75-I75)/H75,"") -> -0.48480161 | L75: =L15+L20+L26+L31+L36+L42+L47+L53+L58+L63+L69+L74 -> 124332 | M75: =M15+M20+M26+M31+M36+M42+M47+M53+M58+M63+M69+M74 -> 197632 | N75: =IF(L75=0,"",L75-M75) -> -73300 | O75: =IFERROR((L75-M75)/L75,"") -> -0.58955056 | P75: =P15+P20+P26+P31+P36+P42+P47+P53+P58+P63+P69+P74 -> 6241 | Q75: =Q15+Q20+Q26+Q31+Q36+Q42+Q47+Q53+Q58+Q63+Q69+Q74 -> -3757
A76: ** | B76: ** | C76: ** | D76: ** | E76: ** | F76: ** | G76: ** | H76: ** | I76: ** | J76: ** | K76: ** | L76: ** | M76: ** | N76: ** | O76: ** | P76: ** | Q76: ** | R76: **
